Workbook

Sheet Home
B1: POONAWALLA FINCORP LIMITED — FP&A MODEL INDEX
B2: Click any sheet name below to jump to that tab
B4: SECTION / REF | C4: SHEET | D4: WHAT IT COVERS
B5: A — BUSINESS MODEL
B6: A1 | C6: Business Operating Model | D6: End-to-end lending value chain
B7: A2 | C7: FP&A Value Creation Framework | D7: Strategy to value
B8: A3 | C8: Distribution Analytics | D8: Acquisition channels (illustrative)
B9: A4 | C9: Customer Economics | D9: CAC, CLTV, payback (illustrative)
B10: A5 | C10: Customer Analytics | D10: Customer base & cross-sell
B11: B — STRATEGIC FINANCE
B12: B1 | C12: Executive Board Cockpit | D12: One-page board overview + KPI trends
B13: B2 | C13: Business Performance Scorecard | D13: Cited historical KPIs, Q1 FY27, guidance
B14: B3 | C14: Business Drivers | D14: Growth engine
B15: B4 | C15: KPIs & Ratios | D15: Performance (actual + forecast)
B16: C — PLANNING & FORECASTING
B17: C1 | C17: Assumptions | D17: All editable forecast inputs, each with rationale and source
B18: C2 | C18: Revenue Forecast | D18: Growth forecast — Average AUM × Yield
B19: C3 | C19: Funding Forecast | D19: Financing growth — borrowings and cost of funds
B20: C4 | C20: Treasury | D20: Borrowing mix and liquidity position
B21: C5 | C21: Credit Cost Forecast | D21: Risk outlook — GNPA/NNPA/PCR glide path
B22: C6 | C22: Operating Cost Forecast | D22: Efficiency — cost lines on their own drivers
B23: C7 | C23: Regulatory Capital | D23: RWA → CRAR → capital requirement
B24: C8 | C24: CapEx & Depreciation Schedule | D24: Investment planning and net block roll-forward
B25: D — PERFORMANCE & RISK MANAGEMENT
B26: D1 | C26: Portfolio Mix | D26: Product mix & capital allocation decisions
B27: D2 | C27: Product Profitability | D27: Portfolio optimisation — RAROC by product
B28: D3 | C28: Branch Profitability | D28: Network optimisation
B29: D4 | C29: Collections Analytics | D29: Roll rates & recovery (illustrative)
B30: D5 | C30: Digital Transformation | D30: Digital KPIs and cost flow-through
B31: D6 | C31: Enterprise Risk Cockpit | D31: Risk management — RAG status and heat map
B32: D7 | C32: Scenario Analysis | D32: Strategic alternatives — Base / Upside / Downside
B33: E — EXECUTIVE DECISION SUPPORT
B34: E1 | C34: Management Recommendations | D34: Executive actions, each citing its supporting cell
B35: E2 | C35: Value Creation Tracker | D35: Benefits realisation — initiative, owner, impact
B36: F — FINANCIAL STATEMENTS
B37: F1 | C37: Profit & Loss | D37: Consolidated P&L, actuals and forecast
B38: F2 | C38: Balance Sheet | D38: Consolidated Balance Sheet with ties-to-zero check
B39: F3 | C39: Cash Flow Statement | D39: Consolidated Cash Flow with reconciling memo
B40: F4 | C40: Statement of Changes in Equity | D40: Equity movements per annual report
B43: THE CORE DECISION PATH — the 9 tabs that actually drive the recommendation
B44: The other 27 tabs provide operating context, evidence and monitoring. If you only read nine, read these, in this order:
B45: 1 | C45: Business Drivers | D45: Customers, disbursement and AUM build — every forecast line starts here
B46: 2 | C46: Portfolio Mix | D46: Where the disclosed ₹60,348 Cr book actually sits, by product
B47: 3 | C47: Product Profitability | D47: Modelled RAROC by product — return per unit of regulatory capital consumed
B48: 4 | C48: Credit Cost Forecast | D48: The largest single forecast risk — read the limitation block at row 15
B49: 5 | C49: Funding Forecast | D49: Cost of funds and the borrowing mix that funds the residual
B50: 6 | C50: Profit & Loss | D50: Where drivers, credit cost and funding converge into earnings
B51: 7 | C51: Regulatory Capital | D51: RWA → target CRAR → capital requirement → Balance Sheet equity. Sections 7-8 answer the equity-freeze and feasibility questions
B52: 8 | C52: Scenario Analysis | D52: P&L and CAPITAL consequences of each case — sizes the risk
B53: 9 | C53: Management Recommendations | D53: The conclusions, each citing the tab and cell that supports it
B54: The one question this chain is built to answer: given incremental capital, where should it be deployed to raise sustainable return without breaching the 18% target CRAR — and what happens if that capital is not available?

Sheet A - Business Model
B2: A | C2: SECTION A — BUSINESS MODEL | F2: ⌂ Home
C4: How Poonawalla actually operates. This section starts with the customer — not the P&L — and traces the full lending journey through to shareholder value. Everything in Sections B–F is downstream of what happens here.
B6: WHAT THIS SECTION COVERS
C7: • The end-to-end lending value chain: lead generation → acquisition → underwriting → disbursement → collections → cross-sell
C8: • The distribution engine: which channels source customers, at what cost and conversion
C9: • Customer unit economics: acquisition cost, lifetime value, payback period, cross-sell depth
C10: • The conceptual bridge linking business strategy to measurable shareholder value
B12: SHEETS IN THIS SECTION
B13: Ref | C13: Sheet | D13: What it does
B14: A1 | C14: Business Operating Model | D14: The 11-stage lending value chain, each stage showing its live metric and the tab that models it, plus the management flywheel
B15: A2 | C15: FP&A Value Creation Framework | D15: Conceptual loop connecting strategy to shareholder value
B16: A3 | C16: Distribution Analytics | D16: Acquisition channel mix, CAC and conversion by channel (illustrative — channel data not disclosed)
B17: A4 | C17: Customer Economics | D17: CAC, CLTV, CAC payback and CLTV:CAC ratio (illustrative — unit economics not disclosed)
B18: A5 | C18: Customer Analytics | D18: Customer base growth, cross-sell rate, AUM per customer

Sheet Business Operating Model
B1: POONAWALLA FINCORP — BUSINESS OPERATING MODEL | H1: ⌂ Home
B2: The end-to-end lending value chain. Every stage below maps to a tab in this workbook — operations drive the financial outcome, not the reverse.
B4: STAGE | C4: WHAT HAPPENS | D4: KEY METRIC | E4: CURRENT VALUE | F4: WHERE MODELLED
B5: 1. Lead Generation | C5: Demand captured via branch, DSA, digital and partner channels | D5: Channel mix % | E5: See Distribution Analytics | F5: Distribution Analytics
B6: 2. Customer Acquisition | C6: Onboarding, KYC, credit assessment initiation | D6: Cumulative customers (Lakh) | E6: ='Business Drivers'!C9 -> 22 | F6: Customer Economics
B7: 3. Digital Journey | C7: Digital sourcing, straight-through processing, e-KYC | D7: DDP share of disbursement % | E7: ='KPIs & Ratios'!F76 -> 0.82 | F7: Digital Transformation
B8: 4. Credit Underwriting | C8: Risk scoring, policy checks, AI-led decisioning | D8: Approval discipline → GNPA % | E8: ='Business Performance Scorecard'!C192 -> 0.0137 | F8: Credit Cost Forecast
B9: 5. Disbursement | C9: Loan booked and funds released | D9: Total disbursement (₹ Cr) | E9: ='Business Drivers'!D14 -> 50008 | F9: Business Drivers
B10: 6. Portfolio Build | C10: AUM accumulates net of runoff; product mix shifts | D10: AUM (₹ Cr) | E10: ='KPIs & Ratios'!H95 -> 60348 | F10: Portfolio Mix
B11: 7. Collections | C11: EMI recovery, bucket management, early-warning action | D11: Credit cost % of avg AUM | E11: ='KPIs & Ratios'!H43*100 -> 2.4910868 | F11: Collections Analytics
B12: 8. Cross-sell & Retention | C12: Repeat lending to existing base at lower acquisition cost | D12: Cross-sell rate % | E12: ='Customer Analytics'!F8 -> 0.27 | F12: Customer Economics
B13: 9. Funding | C13: Liability raising across banks, NCDs, CP; ALM management | D13: Cost of funds % | E13: ='KPIs & Ratios'!H26*100 -> 7.4796242 | F13: Treasury / Funding Forecast
B14: 10. Profitability | C14: NII after credit cost and opex converts to PAT | D14: PAT (₹ Cr) | E14: ='KPIs & Ratios'!H35 -> 541.81 | F14: Profit & Loss
B15: 11. Shareholder Value | C15: Returns compound into ROE, EPS and book value growth | D15: ROE % | E15: ='KPIs & Ratios'!H34*100 -> 5.8501639 | F15: Board Cockpit
B18: MANAGEMENT FLYWHEEL — how the model self-reinforces
B19: Better Customer Selection | D19: →
B20: Better Portfolio Quality | D20: →
B21: Lower Credit Cost | D21: →
B22: Higher ROE | D22: →
B23: Stronger Capital Base | D23: →
B24: Higher Growth Capacity | D24: →
B25: More Customers ⟳ (loop repeats)

Sheet FP&A Value Creation Framework
B1: FP&A Value Creation Framework | M1: ⌂ Home
B2: The conceptual loop connecting strategy to shareholder value — every tab in this workbook maps to one stage below.
D4: 1. BUSINESS STRATEGY | G4: Diversify product mix (13 loan products), scale secured lending (Gold Loan, LAP), deepen phygital distribution, AI-led underwriting & collections.
D5: ↓
D6: 2. BUSINESS DRIVERS | G6: AUM growth, disbursement volumes, yield on AUM, cost of funds, credit cost, branch/channel productivity, customer acquisition & cross-sell.
D7: ↓
D8: 3. FP&A ANALYSIS | G8: Driver-based forecasting (Driver-Based Forecast tab), product/branch/customer profitability, scenario & sensitivity analysis, budget-vs-actual variance.
D9: ↓
D10: 4. EXECUTIVE INSIGHTS | G10: Distil analysis into a small number of decision-ready insights — e.g. cost-of-borrowing headroom, branch productivity gaps, product-mix profitability skew.
D11: ↓
D12: 5. MANAGEMENT DECISIONS | G12: Capital allocation, pricing & risk-appetite calibration, treasury funding strategy, branch network investment, cost actions (Value Creation Tracker tab).
D13: ↓
D14: 6. BUSINESS PERFORMANCE | G14: Realised AUM growth, NIM, GNPA/NNPA, Cost-to-Income, ROA/ROE — tracked on the Executive Dashboard tab.
D15: ↓
D16: 7. SHAREHOLDER VALUE | G16: Sustainable PAT growth, improving ROE, capital efficiency, stronger credit ratings and lower cost of capital.
D18: ↺ Continuous loop: realised Business Performance and Shareholder Value outcomes feed back into the next Business Strategy review.

Sheet Distribution Analytics
B1: POONAWALLA FINCORP — DISTRIBUTION ANALYTICS | H1: ⌂ Home
B2: ⚠ ILLUSTRATIVE MODEL — Poonawalla does not publicly disclose acquisition-channel mix, channel-level CAC or conversion rates. Only the FY26 branch network (500+, incl. 400 gold-loan branches, AR pg.2) and DDP digital-sourcing share for FY23/FY24 (81%/82%, AR FY24 pg.14) are disclosed. All channel splits below are modelled assumptions.
B4: Acquisition Channel | C4: Share of Sourcing % | D4: Illustrative CAC (₹) | E4: Illustrative Conversion % | F4: Strategic Role
B5: Branch (physical network) | C5: 0.3 | D5: 3200 | E5: 0.22 | F5: Secured products, gold loan, relationship depth
B6: DSA / Channel Partners | C6: 0.22 | D6: 2900 | E6: 0.18 | F6: Volume scale in LAP and business loans
B7: Digital / Direct (DDP) | C7: 0.32 | D7: 1400 | E7: 0.12 | F7: Lowest-cost acquisition; consumer/personal loans
B8: Marketplace / Aggregator | C8: 0.1 | D8: 2100 | E8: 0.15 | F8: Incremental reach, price-sensitive segments
B9: Embedded / Ecosystem Partner | C9: 0.06 | D9: 1800 | E9: 0.25 | F9: Consumer durable, POS-linked lending
B10: TOTAL / BLENDED | C10: =SUM(C5:C9) -> 1 | D10: =SUMPRODUCT(C5:C9,D5:D9)/C10 -> 2364 | E10: =SUMPRODUCT(C5:C9,E5:E9)/C10 -> 0.174
B12: DISCLOSED DISTRIBUTION FACTS (cited)
B13: Branch network (count, FY26) | C13: ='KPIs & Ratios'!H83 -> 500 | F13: AR FY2026 pg.2 — "500+ branches incl. 400 gold loan branches"
B14: Digital (DDP) share of disbursement % (FY24, last disclosed) | C14: ='KPIs & Ratios'!F76 -> 0.82 | F14: AR FY2024 pg.14
B15: Gold-loan dedicated branches opened in FY26 | C15: 400 | F15: AR FY2026 pg.2 — ">90% in Tier II/III locations"
B16: Planned branch additions FY27E | C16: =Assumptions!D13 -> 150 | F16: Assumptions tab (calibrated to management's ~400 gold-loan branch guidance)

Sheet Customer Economics
B1: POONAWALLA FINCORP — CUSTOMER ECONOMICS | H1: ⌂ Home
B2: ⚠ ILLUSTRATIVE MODEL — Only the FY26 customer base (22+ lakh, AR FY26 pg.35) is Company-disclosed. CAC, CLTV, retention, payback and cross-sell economics are NOT publicly disclosed by Poonawalla and are modelled assumptions (yellow cells) for framework demonstration only. Do not present these as company figures.
B4: Metric | C4: FY2024 | D4: FY2025 | E4: FY2026 | F4: Source / Basis
B5: Cumulative Customer Base (Lakh) | C5: ='Customer Analytics'!D5 -> 15 | D5: ='Customer Analytics'!E5 -> 18 | E5: ='Customer Analytics'!F5 -> 22 | F5: FY26 disclosed (AR pg.35); prior years illustrative
B6: New Customers Added (Lakh) | C6: ='Customer Analytics'!D6 -> 4 | D6: ='Customer Analytics'!E6 -> 3 | E6: ='Customer Analytics'!F6 -> 4 | F6: Derived from base movement
B7: Customer Acquisition Cost — CAC (₹) | C7: ='Customer Analytics'!D7 -> 3000 | D7: ='Customer Analytics'!E7 -> 2750 | E7: ='Customer Analytics'!F7 -> 2500 | F7: ILLUSTRATIVE — not disclosed
B8: Average AUM per Customer (₹) | C8: ='Customer Analytics'!D10 -> 166686.67 | D8: ='Customer Analytics'!E10 -> 197950 | E8: ='Customer Analytics'!F10 -> 274309.09 | F8: Derived: AUM ÷ customer base
B9: Cross-sell / Repeat Rate % | C9: ='Customer Analytics'!D8 -> 0.21 | D9: ='Customer Analytics'!E8 -> 0.24 | E9: ='Customer Analytics'!F8 -> 0.27 | F9: ILLUSTRATIVE — not disclosed
B11: DERIVED UNIT ECONOMICS (all illustrative)
B12: Illustrative Revenue per Customer (₹) | E12: =E8*'KPIs & Ratios'!H25 -> 38004.455 | F12: Avg AUM/customer × portfolio yield
B13: Illustrative Contribution per Customer (₹, after funding + credit cost) | E13: =E8*('KPIs & Ratios'!H25-'KPIs & Ratios'!H26-'KPIs & Ratios'!H43) -> 10653.888 | F13: Avg AUM × (yield − cost of funds − credit cost)
B14: Illustrative CAC Payback (years) | E14: =IFERROR(E7/E13,"") -> 0.23465611 | F14: CAC ÷ annual contribution per customer
B15: Illustrative Customer Lifetime Value — CLTV (₹) | E15: =E13*C18 -> 31961.665 | F15: Annual contribution × assumed tenure
B16: Illustrative CLTV : CAC ratio (x) | E16: =IFERROR(E15/E7,"") -> 12.784666 | F16: Target >3x is typical retail-lending benchmark
B18: Assumed average customer tenure (years) | C18: 3

Sheet Customer Analytics
B1: POONAWALLA FINCORP LIMITED — Customer Analytics (Illustrative) | H1: ⌂ Home
B2: ILLUSTRATIVE MODEL: Only the FY2026 customer base (22+ lakh) is company-disclosed (blue, cited). Customer counts for other years, acquisition, retention, CAC and cross-sell figures are illustrative assumptions (yellow) for demonstration purposes only.
B4: Particulars | C4: FY2023 | D4: FY2024 | E4: FY2025 | F4: FY2026
B5: Cumulative Customer Base (Lakh) – illustrative trend to disclosed FY26 actual | C5: 11 | D5: 15 | E5: 18 | F5: 22
B6: New Customers Added (Lakh) | D6: =D5-C5 -> 4 | E6: =E5-D5 -> 3 | F6: =F5-E5 -> 4
B7: Illustrative Customer Acquisition Cost – CAC (₹) | C7: 3200 | D7: 3000 | E7: 2750 | F7: 2500
B8: Illustrative Repeat / Cross-sell Rate % | C8: 0.18 | D8: 0.21 | E8: 0.24 | F8: 0.27
B9: AUM (₹ Cr, Reported/Standalone — linked from Executive Dashboard) | C9: ='Business Performance Scorecard'!E161 -> 16143 | D9: ='Business Performance Scorecard'!F161 -> 25003 | E9: ='Business Performance Scorecard'!G161 -> 35631 | F9: ='Business Performance Scorecard'!H161 -> 60348
B10: Avg. AUM per Customer (₹) | C10: =IFERROR(C9/(C5*100000)*10000000,"") -> 146754.55 | D10: =IFERROR(D9/(D5*100000)*10000000,"") -> 166686.67 | E10: =IFERROR(E9/(E5*100000)*10000000,"") -> 197950 | F10: =IFERROR(F9/(F5*100000)*10000000,"") -> 274309.09

Sheet B - Strategic Finance
B2: B | C2: SECTION B — STRATEGIC FINANCE | F2: ⌂ Home
C4: The board-level view: what happened, why it happened, and what management should do next. This is the section a CFO or VP Finance reads first.
B6: WHAT THIS SECTION COVERS
C7: • A single-page board cockpit: business health RAG, executive narrative, driver engine, decision box and value creation
C8: • The cited disclosure backbone — every historical KPI traced to an annual report page, plus Q1 FY27 actuals and management guidance
C9: • The driver chain that builds AUM from customers, ticket size, cross-sell and portfolio runoff
C10: • The full ratio suite across FY2021–FY2026 actuals and FY2027E–FY2031E forecast
B12: SHEETS IN THIS SECTION
B13: Ref | C13: Sheet | D13: What it does
B14: B1 | C14: Executive Board Cockpit | D14: One-page board overview: business health, narrative, driver engine, CEO heat map, capital allocation, and 10 KPI trend charts (actuals vs forecast)
B15: B2 | C15: Business Performance Scorecard | D15: Cited historical KPIs (FY21–FY26), Q1 FY27 latest-quarter actuals, and management's stated guidance
B16: B3 | C16: Business Drivers | D16: The growth engine — AUM is derived here from customers, loan size, cross-sell and runoff, not assumed
B17: B4 | C17: KPIs & Ratios | D17: ~90 ratios across growth, profitability, asset quality, capital, liquidity, per-share and efficiency — actual and forecast

Sheet Executive Board Cockpit
B1: POONAWALLA FINCORP — EXECUTIVE STRATEGIC FINANCE COCKPIT | I1: ⌂ Home
B2: ="""Driving Sustainable Shareholder Value"" — Board Pack — "&'Scenario Analysis'!C5&" Case Scenario" -> "Driving Sustainable Shareholder Value" — Board Pack — Base Case Scenario
B4: 1. BUSINESS HEALTH (5-SECOND VIEW)
B5: Dimension | C5: KPI | D5: Actual (Q1 FY27 / FY26A) | E5: ="Target (FY27E, "&'Scenario Analysis'!C5&" Case)" -> Target (FY27E, Base Case) | F5: Trend | G5: Status
B6: Growth | C6: AUM (₹ Cr, FY26A vs FY27E target) | D6: ='Balance Sheet'!H14 -> 55951.49 | E6: ='Business Drivers'!D21 -> 86376.468 | F6: =IF(D6>'Balance Sheet'!G14,"▲","▼") -> ▲ | G6: =IF(D6>=E6*0.6,"GREEN",IF(D6>=E6*0.5,"YELLOW","RED")) -> GREEN
B7: Profitability | C7: ROE % (Consolidated) | D7: ='KPIs & Ratios'!H34*100 -> 5.8501639 | E7: ='KPIs & Ratios'!I34*100 -> 12.977669 | F7: =IF(E7>D7,"▲","▼") -> ▲ | G7: =IF(D7>15,"GREEN",IF(D7>8,"YELLOW","RED")) -> RED
B8: Risk | C8: GNPA % | D8: ='Business Performance Scorecard'!C192 -> 0.0137 | E8: ='Credit Cost Forecast'!D6 -> 0.0135 | F8: =IF(D8<'KPIs & Ratios'!H44/100,"▼","▲") -> ▼ | G8: =IF(D8<0.013,"GREEN",IF(D8<0.02,"YELLOW","RED")) -> YELLOW
B9: Efficiency | C9: Cost-to-Income % | D9: ='KPIs & Ratios'!H30*100 -> 52.009442 | E9: ='KPIs & Ratios'!I30*100 -> 41.033648 | F9: =IF(E9<D9,"▲","▼") -> ▲ | G9: =IF(D9<45,"GREEN",IF(D9<55,"YELLOW","RED")) -> YELLOW
B10: Liquidity | C10: LCR % (FY26A) | D10: ='KPIs & Ratios'!H54 -> 181 | E10: >150% target | F10: → | G10: =IF(D10>150,"GREEN",IF(D10>120,"YELLOW","RED")) -> GREEN
B11: Value | C11: Basic EPS (₹) | D11: ='KPIs & Ratios'!H64 -> 6.84 | E11: ='KPIs & Ratios'!I64 -> 13.336712 | F11: =IF(E11>D11,"▲","▼") -> ▲ | G11: =IF(D11>15,"GREEN",IF(D11>5,"YELLOW","RED")) -> YELLOW
B13: 2. EXECUTIVE NARRATIVE
B14: ="AUM reached ₹"&TEXT('Business Performance Scorecard'!H161,"#,##0")&" Cr in FY26 (+"&TEXT('KPIs & Ratios'!H8,"0.0%")&" YoY), driven by continued expansion of secured and unsecured retail lending, while Gross NPA improved to "&TEXT('Business Performance Scorecard'!C192,"0.00%")&" (Q1 FY27). Funding costs remain manageable at "&TEXT('Business Performance Scorecard'!C200,"0.00%")&", though operating efficiency — Cost-to-Income at "&TEXT('KPIs & Ratios'!H30*100,"0.0")&"% — requires further improvement. The Base Case forecast projects PAT growing from ₹"&TEXT('KPIs & Ratios'!H35,"#,##0")&" Cr (FY26A) to ₹"&TEXT('KPIs & Ratios'!I35,"#,##0")&" Cr by FY27E, supported by disciplined capital allocation (₹"&TEXT('Value Creation Tracker'!G10,"#,##0")&" Cr of identified value-creation impact) and enhanced branch productivity." -> AUM reached ₹60,348 Cr in FY26 (+69.4% YoY), driven by continued expansion of secured and unsecured retail lending, while Gross NPA improved to 1.37% (Q1 FY27). Funding costs remain manageable at 7.72%, though operating efficiency — Cost-to-Income at 52.0% — requires further improvement. The Base Case forecast projects PAT growing from ₹542 Cr (FY26A) to ₹1,782 Cr by FY27E, supported by disciplined capital allocation (₹350 Cr of identified value-creation impact) and enhanced branch productivity.
B19: 3. BUSINESS DRIVER ENGINE | D19: Driver Performance
B20: Customer Growth | D20: Driver | E20: Current | F20: Trend | G20: Impact
B21: ↓ | D21: Customers (Lakh) | E21: ='Business Drivers'!C9 -> 22 | F21: =IF('Business Drivers'!C9>'Customer Analytics'!E5,"▲","▼") -> ▲ | G21: High
B22: Disbursement → AUM | D22: AUM Growth % | E22: ='KPIs & Ratios'!H8*100 -> 69.369369 | F22: =IF('KPIs & Ratios'!H8>'KPIs & Ratios'!G8,"▲","▼") -> ▲ | G22: High
B23: ↓ | D23: Yield on Advances % | E23: ='KPIs & Ratios'!H25*100 -> 13.85461 | F23: → | G23: Medium
B24: Interest Income → NII | D24: Credit Cost % | E24: ='KPIs & Ratios'!H43*100 -> 2.4910868 | F24: =IF('KPIs & Ratios'!H43<'KPIs & Ratios'!G43,"▼","▲") -> ▼ | G24: High
B25: ↓
B26: PAT
B27: ↓
B28: ROE → Shareholder Value
B30: 4. CEO HEAT MAP — BUSINESS PRIORITY VIEW
B31: Business Area | C31: Key Metric | D31: Status | E31: Priority
B32: Growth | C32: ="AUM +"&TEXT('KPIs & Ratios'!H8,"0.0%")&" YoY" -> AUM +69.4% YoY | D32: =IF('KPIs & Ratios'!H8>0.2,"GREEN",IF('KPIs & Ratios'!H8>0.1,"YELLOW","RED")) -> GREEN | E32: =IF(D32="GREEN","Maintain",IF(D32="YELLOW","Improve","Immediate Focus")) -> Maintain
B33: Asset Quality | C33: ="GNPA "&TEXT('Business Performance Scorecard'!C192,"0.00%") -> GNPA 1.37% | D33: =IF('Business Performance Scorecard'!C192<0.013,"GREEN",IF('Business Performance Scorecard'!C192<0.02,"YELLOW","RED")) -> YELLOW | E33: =IF(D33="GREEN","Maintain",IF(D33="YELLOW","Improve","Immediate Focus")) -> Improve
B34: Treasury | C34: ="Cost of Borrowing "&TEXT('Business Performance Scorecard'!C200,"0.00%") -> Cost of Borrowing 7.72% | D34: =IF('Business Performance Scorecard'!C200<0.07,"GREEN",IF('Business Performance Scorecard'!C200<0.08,"YELLOW","RED")) -> YELLOW | E34: =IF(D34="GREEN","Maintain",IF(D34="YELLOW","Improve","Immediate Focus")) -> Improve
B35: Branch Productivity | C35: ="Avg. AUM/Branch ₹"&TEXT('Branch Profitability'!F7,"0.0")&" Cr" -> Avg. AUM/Branch ₹36.2 Cr | D35: =IF('Branch Profitability'!F7>'Branch Profitability'!E7*1.15,"GREEN",IF('Branch Profitability'!F7>'Branch Profitability'!E7,"YELLOW","RED")) -> GREEN | E35: =IF(D35="GREEN","Maintain",IF(D35="YELLOW","Improve","Immediate Focus")) -> Maintain
B36: Cost Efficiency | C36: ="Cost-to-Income "&TEXT('KPIs & Ratios'!H30*100,"0.0")&"%" -> Cost-to-Income 52.0% | D36: =IF('KPIs & Ratios'!H30*100<45,"GREEN",IF('KPIs & Ratios'!H30*100<55,"YELLOW","RED")) -> YELLOW | E36: =IF(D36="GREEN","Maintain",IF(D36="YELLOW","Improve","Immediate Focus")) -> Improve
B37: Digital Business | C37: ="DDP Share "&TEXT('KPIs & Ratios'!F76,"0.0%")&" (last disclosed FY24)" -> DDP Share 82.0% (last disclosed FY24) | D37: GREEN | E37: =IF(D37="GREEN","Accelerate",IF(D37="YELLOW","Improve","Immediate Focus")) -> Accelerate
B39: ="5. FORECAST OUTLOOK ("&'Scenario Analysis'!C5&" Case)" -> 5. FORECAST OUTLOOK (Base Case)
B40: Metric | C40: FY26A | D40: FY27E | E40: Direction | F40: Key Driver
B41: Total Income (₹ Cr) | C41: ='Profit & Loss'!H15 -> 6795.65 | D41: ='Profit & Loss'!I15 -> 11250.409 | E41: =IF(D41>C41,"▲","▼") -> ▲ | F41: Higher AUM
B42: PAT (₹ Cr) | C42: ='KPIs & Ratios'!H35 -> 541.81 | D42: ='KPIs & Ratios'!I35 -> 1781.8731 | E42: =IF(D42>C42,"▲","▼") -> ▲ | F42: Lower Credit Cost
B43: ROE % (Consolidated) | C43: ='KPIs & Ratios'!H34*100 -> 5.8501639 | D43: ='KPIs & Ratios'!I34*100 -> 12.977669 | E43: =IF(D43>C43,"▲","▼") -> ▲ | F43: Better Productivity
B44: Total Borrowings (₹ Cr) | C44: ='KPIs & Ratios'!H49 -> 48098.3 | D44: ='KPIs & Ratios'!I49 -> 73402.767 | E44: =IF(D44>C44,"▲","▼") -> ▲ | F44: Portfolio Growth
B46: 6. VALUE CREATION ENGINE (linked to Value Creation Tracker)
B47: Initiative | C47: KPI Impact | D47: Business Impact | E47: ₹ Cr p.a.
B48: ='Value Creation Tracker'!C7 -> Treasury diversification — higher NCD mix, longer tenor | C48: Cost of Funds ↓ | D48: NIM ↑ | E48: ='Value Creation Tracker'!G7 -> 120
B49: ='Value Creation Tracker'!C5 -> Branch productivity uplift (staggered gold-loan branch ramp-up) | C49: Cost-to-Income ↓ | D49: ROE ↑ | E49: ='Value Creation Tracker'!G5 -> 90
B50: ='Value Creation Tracker'!C8 -> Predictive collections analytics for early-bucket flows | C50: GNPA ↓ | D50: Shareholder Value ↑ | E50: ='Value Creation Tracker'!G8 -> 60
B51: ='Value Creation Tracker'!C9 -> Cross-sell to existing customer base via analytics-led targeting | C51: Revenue ↑ | D51: ROA ↑ | E51: ='Value Creation Tracker'!G9 -> 35
B52: AI Underwriting & Collections Automation (AR FY26 pg.24-26 initiatives) | C52: Credit Cost ↓ | D52: PAT ↑ | E52: n/a
B54: 7. CAPITAL ALLOCATION MATRIX (linked to Product Profitability tab)
B55: Business | C55: AUM Mix % | D55: Modelled RAROC % (Profitability) | E55: Credit Cost % (Risk) | F55: Screening flag
B56: ='Product Profitability'!B13 -> Gold Loan | C56: ='Product Profitability'!C13 -> 0.021525154 | D56: ='Product Profitability'!L13*100 -> 2.0555556 | E56: ='Product Profitability'!H13*100 -> 0.4 | F56: =IF(AND(D56>'Portfolio Mix'!$C$27*100,E56<'Portfolio Mix'!$C$28*100),"Expand",IF(D56>'Portfolio Mix'!$C$27*100,"Grow Selectively",IF(E56>'Portfolio Mix'!$C$29*100,"Review","Maintain"))) -> Maintain
B57: ='Product Profitability'!B12 -> Prime Personal Loan | C57: ='Product Profitability'!C12 -> 0.079571817 | D57: ='Product Profitability'!L12*100 -> 3.4222222 | E57: ='Product Profitability'!H12*100 -> 2 | F57: =IF(AND(D57>'Portfolio Mix'!$C$27*100,E57<'Portfolio Mix'!$C$28*100),"Expand",IF(D57>'Portfolio Mix'!$C$27*100,"Grow Selectively",IF(E57>'Portfolio Mix'!$C$29*100,"Review","Maintain"))) -> Maintain
B58: ='Product Profitability'!B8 -> Loan Against Property (LAP) | C58: ='Product Profitability'!C8 -> 0.28062239 | D58: ='Product Profitability'!L8*100 -> 1.0740741 | E58: ='Product Profitability'!H8*100 -> 1 | F58: =IF(AND(D58>'Portfolio Mix'!$C$27*100,E58<'Portfolio Mix'!$C$28*100),"Expand",IF(D58>'Portfolio Mix'!$C$27*100,"Grow Selectively",IF(E58>'Portfolio Mix'!$C$29*100,"Review","Maintain"))) -> Maintain
B59: ='Product Profitability'!B11 -> Business Loan | C59: ='Product Profitability'!C11 -> 0.12101478 | D59: ='Product Profitability'!L11*100 -> 37.555556 | E59: ='Product Profitability'!H11*100 -> 3.5 | F59: =IF(AND(D59>'Portfolio Mix'!$C$27*100,E59<'Portfolio Mix'!$C$28*100),"Expand",IF(D59>'Portfolio Mix'!$C$27*100,"Grow Selectively",IF(E59>'Portfolio Mix'!$C$29*100,"Review","Maintain"))) -> Grow Selectively
B61: 8. MANAGEMENT ACTION TRACKER (linked to Value Creation Tracker)
B62: Decision | C62: Owner | D62: Timeline | E62: Expected Impact
B63: Optimise Funding Mix | C63: ='Value Creation Tracker'!I7 -> Treasury | D63: ='Value Creation Tracker'!H7 -> 12 months | E63: Lower Cost of Funds
B64: Expand Gold Loan / Branch Network | C64: ='Value Creation Tracker'!I5 -> Branch Operations | D64: ='Value Creation Tracker'!H5 -> 6 months | E64: Higher AUM
B65: AI Credit Model / Collections Analytics | C65: ='Value Creation Tracker'!I8 -> Risk & Collections | D65: ='Value Creation Tracker'!H8 -> 9 months | E65: Lower Credit Cost
B66: Branch Optimisation | C66: ='Value Creation Tracker'!I5 -> Branch Operations | D66: ='Value Creation Tracker'!H5 -> 6 months | E66: Better Cost-to-Income
B68: 9. SHAREHOLDER VALUE DASHBOARD
B69: Growth | C69: ="AUM +"&TEXT('KPIs & Ratios'!H8,"0.0%")&" YoY" -> AUM +69.4% YoY
B70: ↓
B71: Profitability | C71: ="PAT ₹"&TEXT('KPIs & Ratios'!H35,"#,##0")&" Cr" -> PAT ₹542 Cr
B72: ↓
B73: Efficiency | C73: ="Cost-to-Income "&TEXT('KPIs & Ratios'!H30*100,"0.0")&"%" -> Cost-to-Income 52.0%
B74: ↓
B75: Risk | C75: ="GNPA "&TEXT('Business Performance Scorecard'!C192,"0.00%") -> GNPA 1.37%
B76: ↓
B77: ROE | C77: =TEXT('KPIs & Ratios'!H34*100,"0.00")&"%" -> 5.85%
B78: ↓
B79: EPS | C79: ="₹"&TEXT('KPIs & Ratios'!H64,"0.00") -> ₹6.84
B80: ↓
B81: Book Value | C81: ="₹"&TEXT('KPIs & Ratios'!H66,"0.00") -> ₹128.08
B82: ↓
B83: Shareholder Value

Sheet Business Performance Scorecard
B1: VISUAL KPI SUMMARY | J1: ⌂ Home
B2: Poonawalla Fincorp Limited | Actuals FY2024–FY2026 & Forecast FY2027E–FY2031E
B3: ="VISUAL KPI TRENDS — bars run newest at top: FY31E → FY24 (bottom). Teal = actuals FY24-26. Green = "&UPPER('Scenario Analysis'!C5)&" case forecast FY27E-31E." -> VISUAL KPI TRENDS — bars run newest at top: FY31E → FY24 (bottom). Teal = actuals FY24-26. Green = BASE case forecast FY27E-31E.
B4: Assets under Management | D4: Net Interest Income (NII) | F4: Gross NPA
B5: (₹ Crore, Consolidated basis for forecast) | D5: (₹ Crore) | F5: (%)
B15: ="AUM reached ₹"&TEXT('KPIs & Ratios'!H95,"#,##0")&" Cr in FY26 (+"&TEXT('KPIs & Ratios'!H8,"0.0%")&" YoY) and is projected to scale further under the driver-based forecast, reaching ~₹"&TEXT('KPIs & Ratios'!M95/100000,"0.00")&" lakh Cr by FY31E in the "&'Scenario Analysis'!C5&" Case." -> AUM reached ₹60,348 Cr in FY26 (+69.4% YoY) and is projected to scale further under the driver-based forecast, reaching ~₹2.46 lakh Cr by FY31E in the Base Case. | D15: NII rose to ₹4,029 Cr in FY26 from ₹2,708 Cr in FY25. The forecast (green bars) is driven by the Revenue Forecast tab's average-AUM × yield methodology. | F15: Gross NPA improved to 1.44% in FY26. The forecast glide path (Credit Cost Forecast tab) assumes continued underwriting discipline, easing further through FY31E.
B24: Net NPA | D24: Profit After Tax* | F24: Pre-Provision Operating Profit
B25: (%) | D25: (₹ Crore) | F25: (₹ Crore)
B35: Net NPA eased to 0.74% in FY26, moving in line with Gross NPA. Forecast years assume the PCR ratio holds broadly steady. | D35: ="PAT (excl. exceptional items) recovered to ₹"&TEXT('KPIs & Ratios'!H35,"#,##0")&" Cr in FY26. The "&'Scenario Analysis'!C5&" Case forecast projects PAT of ₹"&TEXT('KPIs & Ratios'!M35,"#,##0")&" Cr by FY31E as credit costs normalise and scale benefits compound." -> PAT (excl. exceptional items) recovered to ₹542 Cr in FY26. The Base Case forecast projects PAT of ₹7,832 Cr by FY31E as credit costs normalise and scale benefits compound. | F35: PPOP rose to ₹1,934 Cr in FY26. Forecast PPOP growth reflects NII scaling faster than the modelled opex build-out (Operating Cost Forecast tab).
B44: Cost of Borrowing | D44: Return on Assets (ROA)* | F44: Shareholders' Funds
B45: (%) | D45: (%) | F45: (₹ Crore)
B55: Cost of borrowing declined to 7.73% in FY26. The forecast (Funding Forecast tab) assumes gradual further easing as the funding mix diversifies. | D55: ="ROA improved to "&TEXT('KPIs & Ratios'!H33*100,"0.00")&"% in FY26. The "&'Scenario Analysis'!C5&" Case reaches "&TEXT('KPIs & Ratios'!K33*100,"0.0")&"% by FY29E — against management's stated 3.0-3.5% exit guidance (see KPIs & Ratios guidance cross-check)." -> ROA improved to 1.14% in FY26. The Base Case reaches 3.0% by FY29E — against management's stated 3.0-3.5% exit guidance (see KPIs & Ratios guidance cross-check). | F55: Shareholders' funds reached ₹10,298 Cr in FY26. Forecast growth (Balance Sheet tab) assumes retained earnings plus periodic capital raises to sustain the CRAR.
B64: Capital Adequacy Ratio (CRAR)
B65: (%, forecast is an approximation)
B75: CRAR moderated to 16.83% in FY26. True regulatory CRAR forecasting needs a risk-weighted-assets model beyond this workbook's scope, so FY27E-31E (green) uses the Equity/Assets % trend as a directional proxy, anchored to the FY26A level — not a substitute for a real capital calculation.
B84: CEO SUMMARY
B85: ="What happened? AUM grew "&TEXT('KPIs & Ratios'!H8,"0.0%")&" YoY to ₹"&TEXT('Business Performance Scorecard'!H161,"#,##0")&" Cr, with PAT of ₹"&TEXT('KPIs & Ratios'!H35,"#,##0")&" Cr in FY26, supported by strong secured lending momentum." -> What happened? AUM grew 69.4% YoY to ₹60,348 Cr, with PAT of ₹542 Cr in FY26, supported by strong secured lending momentum.
B86: ="Why? Disciplined underwriting held Gross NPA at "&TEXT('Business Performance Scorecard'!C192,"0.00%")&" (Q1 FY27), funding costs stayed manageable at "&TEXT('Business Performance Scorecard'!C200,"0.00%")&", and average earning assets scaled with the branch network." -> Why? Disciplined underwriting held Gross NPA at 1.37% (Q1 FY27), funding costs stayed manageable at 7.72%, and average earning assets scaled with the branch network.
B87: ="What next? Focus on funding cost optimisation, operating efficiency (Cost-to-Income at "&TEXT('KPIs & Ratios'!H30*100,"0.0")&"%), and branch productivity to sustain ROE expansion toward the FY27E Base Case of "&TEXT('KPIs & Ratios'!I34*100,"0.0")&"%." -> What next? Focus on funding cost optimisation, operating efficiency (Cost-to-Income at 52.0%), and branch productivity to sustain ROE expansion toward the FY27E Base Case of 13.0%.
B90: BUSINESS HEALTH
B91: Dimension | C91: KPI | D91: Actual | E91: Target (FY27E) | F91: YoY % | G91: Trend | H91: Status
B92: Growth | C92: AUM (₹ Cr) | D92: ='Business Performance Scorecard'!H161 -> 60348 | E92: ='Business Drivers'!D21 -> 86376.468 | F92: ='KPIs & Ratios'!H8 -> 0.69369369 | G92: =IF(F92>0,"▲","▼") -> ▲ | H92: =IF(F92>0.2,"GREEN",IF(F92>0.1,"YELLOW","RED")) -> GREEN
B93: Profitability | C93: ROA % | D93: ='Business Performance Scorecard'!C196*100 -> 1.98 | E93: ='KPIs & Ratios'!I33*100 -> 2.3208797 | F93: n/a | G93: =IF(E93>D93,"▲","▼") -> ▲ | H93: =IF(D93>2,"GREEN",IF(D93>1,"YELLOW","RED")) -> YELLOW
B94: Risk | C94: GNPA % | D94: ='Business Performance Scorecard'!C192 -> 0.0137 | E94: ='Credit Cost Forecast'!D6 -> 0.0135 | F94: n/a | G94: =IF(D94<0.0144,"▼","▲") -> ▼ | H94: =IF(D94<0.01,"GREEN",IF(D94<0.02,"YELLOW","RED")) -> YELLOW
B95: Efficiency | C95: Cost-to-Income % | D95: ='KPIs & Ratios'!H30*100 -> 52.009442 | E95: ='KPIs & Ratios'!I30*100 -> 41.033648 | F95: n/a | G95: =IF(E95<D95,"▲","▼") -> ▲ | H95: =IF(D95<45,"GREEN",IF(D95<55,"YELLOW","RED")) -> YELLOW
B96: Liquidity | C96: LCR % | D96: ='KPIs & Ratios'!H54 -> 181 | E96: >150% target | F96: n/a | G96: → | H96: =IF(D96>150,"GREEN",IF(D96>120,"YELLOW","RED")) -> GREEN
B97: Shareholder | C97: ROE % (Consolidated) | D97: ='KPIs & Ratios'!H34*100 -> 5.8501639 | E97: ='KPIs & Ratios'!I34*100 -> 12.977669 | F97: n/a | G97: =IF(E97>D97,"▲","▼") -> ▲ | H97: =IF(D97>15,"GREEN",IF(D97>8,"YELLOW","RED")) -> RED
B99: EXECUTIVE NARRATIVE
B100: ="Business Performance: Growth remained strong, driven by secured lending expansion (AUM +"&TEXT('KPIs & Ratios'!H8,"0.0%")&" YoY to ₹"&TEXT('Business Performance Scorecard'!H161,"#,##0")&" Cr), while asset quality was broadly maintained (GNPA "&TEXT('Business Performance Scorecard'!C192,"0.00%")&", Q1 FY27)." -> Business Performance: Growth remained strong, driven by secured lending expansion (AUM +69.4% YoY to ₹60,348 Cr), while asset quality was broadly maintained (GNPA 1.37%, Q1 FY27).
B103: ="Profitability: PAT reached ₹"&TEXT('KPIs & Ratios'!H35,"#,##0")&" Cr in FY26, aided by higher NII and stable funding costs ("&TEXT('Business Performance Scorecard'!C200,"0.00%")&"). The primary management focus is now improving operating efficiency (Cost-to-Income "&TEXT('KPIs & Ratios'!H30*100,"0.0")&"%) without compromising the growth trajectory." -> Profitability: PAT reached ₹542 Cr in FY26, aided by higher NII and stable funding costs (7.72%). The primary management focus is now improving operating efficiency (Cost-to-Income 52.0%) without compromising the growth trajectory.
B106: ="Outlook: The Base Case forecast projects PAT scaling to ₹"&TEXT('KPIs & Ratios'!I35,"#,##0")&" Cr by FY27E as credit costs normalise and branch productivity improves — with ₹"&TEXT('Value Creation Tracker'!G10,"#,##0")&" Cr of identified value-creation impact already quantified across five initiatives (see Value Creation section below)." -> Outlook: The Base Case forecast projects PAT scaling to ₹1,782 Cr by FY27E as credit costs normalise and branch productivity improves — with ₹350 Cr of identified value-creation impact already quantified across five initiatives (see Value Creation section below).
B110: VALUE DRIVER ENGINE
B111: Customers → Disbursement → AUM → Yield → NII → PAT → ROE → Shareholder Value
D112: Driver | E112: Status | F112: Impact
D113: Customer Growth | E113: =IF('Business Drivers'!C9>'Customer Analytics'!G5,"GREEN","YELLOW") -> GREEN | F113: High
D114: Yield | E114: =IF('KPIs & Ratios'!H25>'KPIs & Ratios'!G25,"GREEN","YELLOW") -> YELLOW | F114: High
D115: Credit Cost | E115: =IF('KPIs & Ratios'!H43<'KPIs & Ratios'!G43,"GREEN","YELLOW") -> GREEN | F115: High
D116: Operating Cost | E116: =IF('KPIs & Ratios'!H30<'KPIs & Ratios'!G30,"GREEN","YELLOW") -> YELLOW | F116: Medium
D117: Cost of Funds | E117: =IF('KPIs & Ratios'!H26<'KPIs & Ratios'!G26,"GREEN","YELLOW") -> YELLOW | F117: Medium
B119: CEO DECISION BOX
B120: Business Issue | D120: Recommendation | F120: Expected Outcome
B121: Funding costs elevated | D121: ='Value Creation Tracker'!C7 -> Treasury diversification — higher NCD mix, longer tenor | F121: Lower Cost of Funds
B122: Strong Gold Loan demand | D122: Expand secured portfolio (Gold Loan, LAP) | F122: Higher AUM
B123: Branch productivity gap | D123: ='Value Creation Tracker'!C5 -> Branch productivity uplift (staggered gold-loan branch ramp-up) | F123: Better Cost-to-Income
B124: Stable asset quality | D124: Accelerate growth selectively toward highest-ROE products | F124: Higher ROE
B127: ="FORECAST OUTLOOK ("&'Scenario Analysis'!C5&" Case)" -> FORECAST OUTLOOK (Base Case)
B128: Metric | C128: FY26A | D128: FY27E | E128: FY28E | F128: Trend
B129: Revenue (₹ Cr) | C129: ='Profit & Loss'!H15 -> 6795.65 | D129: ='Profit & Loss'!I15 -> 11250.409 | E129: ='Profit & Loss'!J15 -> 15954.192 | F129: =IF(E129>C129,"▲","▼") -> ▲
B130: PAT (₹ Cr) | C130: ='KPIs & Ratios'!H35 -> 541.81 | D130: ='KPIs & Ratios'!I35 -> 1781.8731 | E130: ='KPIs & Ratios'!J35 -> 3117.5046 | F130: =IF(E130>C130,"▲","▼") -> ▲
B131: ROE % | C131: ='KPIs & Ratios'!H34*100 -> 5.8501639 | D131: ='KPIs & Ratios'!I34*100 -> 12.977669 | E131: ='KPIs & Ratios'!J34*100 -> 14.978737 | F131: =IF(E131>C131,"▲","▼") -> ▲
B132: Borrowings (₹ Cr) | C132: ='KPIs & Ratios'!H49 -> 48098.3 | D132: ='KPIs & Ratios'!I49 -> 73402.767 | E132: ='KPIs & Ratios'!J49 -> 101898.67 | F132: =IF(E132>C132,"▲","▼") -> ▲
B133: Credit Cost % | C133: ='KPIs & Ratios'!H43*100 -> 2.4910868 | D133: ='KPIs & Ratios'!I43*100 -> 2.2 | E133: ='KPIs & Ratios'!J43*100 -> 1.9 | F133: =IF(E133<C133,"▼","▲") -> ▼
B135: VALUE CREATION
B136: Initiative | D136: Financial Impact | F136: KPI Impact | G136: ₹ Cr p.a.
B137: ='Value Creation Tracker'!C7 -> Treasury diversification — higher NCD mix, longer tenor | D137: Lower funding cost | F137: Cost of Funds ↓ | G137: ='Value Creation Tracker'!G7 -> 120
B138: ='Value Creation Tracker'!C8 -> Predictive collections analytics for early-bucket flows | D138: Lower credit cost | F138: GNPA ↓ | G138: ='Value Creation Tracker'!G8 -> 60
B139: ='Value Creation Tracker'!C5 -> Branch productivity uplift (staggered gold-loan branch ramp-up) | D139: Higher productivity | F139: Cost-to-Income ↓ | G139: ='Value Creation Tracker'!G5 -> 90
B140: ='Value Creation Tracker'!C6 -> Digital/DSA channel mix optimisation to lower CAC | D140: Revenue growth | F140: AUM ↑ | G140: ='Value Creation Tracker'!G6 -> 45
B141: ='Value Creation Tracker'!C9 -> Cross-sell to existing customer base via analytics-led targeting | D141: Higher profitability | F141: ROE ↑ | G141: ='Value Creation Tracker'!G9 -> 35
B144: ACTION DASHBOARD
B145: Priority | C145: Owner | D145: Timeline | E145: Target KPI
B146: Funding optimisation | C146: ='Value Creation Tracker'!I7 -> Treasury | D146: ='Value Creation Tracker'!H7 -> 12 months | E146: Cost of Funds
B147: Gold Loan expansion | C147: ='Value Creation Tracker'!I5 -> Branch Operations | D147: ='Value Creation Tracker'!H5 -> 6 months | E147: AUM
B148: Branch productivity | C148: ='Value Creation Tracker'!I5 -> Branch Operations | D148: ='Value Creation Tracker'!H5 -> 6 months | E148: Cost-to-Income
B149: AI underwriting | C149: ='Value Creation Tracker'!I8 -> Risk & Collections | D149: ='Value Creation Tracker'!H8 -> 9 months | E149: Credit Cost
B154: POONAWALLA FINCORP LIMITED — Executive Dashboard (Key Performance Indicators)
B155: Basis: Mixed — company-disclosed figures use each year's reported basis (Standalone unless marked Consol.); rows explicitly linked from the KPIs & Ratios tab (green font) use that tab's Consolidated-basis formulas. Blank = not disclosed/not computable for that year.
B156: Source: Poonawalla Fincorp Annual Reports FY2022 (MD&A pg.100), FY2023 (MD&A pg.77-78), FY2024 (Board's Report pg.28), FY2025 (KPI pg.22, pg.34), FY2026 (KPI pg.19, Board's Report pg.35) | J156: Chart source data (linked) | L156: Sector benchmark
J157: FY24 | K157: ='KPIs & Ratios'!F95 -> 25003
B158: Particulars | C158: FY2021 | D158: FY2022 | E158: FY2023 | F158: FY2024 | G158: FY2025 | H158: FY2026 | J158: FY25 | K158: ='KPIs & Ratios'!G95 -> 35631
J159: FY26 | K159: ='KPIs & Ratios'!H95 -> 60348
B160: GROWTH | J160: FY27E | K160: ='KPIs & Ratios'!I95 -> 84810.861
B161: Assets Under Management / Loan Book (₹ Cr) | D161: 11765 | E161: 16143 | F161: 25003 | G161: 35631 | H161: 60348 | J161: FY28E | K161: ='KPIs & Ratios'!J95 -> 118563.48
B162: AUM YoY Growth % | E162: =IFERROR(E161/D161-1,"") -> 0.3721207 | F162: =IFERROR(F161/E161-1,"") -> 0.5488447 | G162: =IFERROR(G161/F161-1,"") -> 0.42506899 | H162: =IFERROR(H161/G161-1,"") -> 0.69369369 | J162: FY29E | K162: ='KPIs & Ratios'!K95 -> 156797.64
B163: Disbursements (₹ Cr) | C163: ='KPIs & Ratios'!C12 -> 3680.21 | D163: ='KPIs & Ratios'!D12 -> 7524 | E163: ='KPIs & Ratios'!E12 -> 15751 | F163: ='KPIs & Ratios'!F12 -> 33289 | G163: =IF('KPIs & Ratios'!G12=0,"",'KPIs & Ratios'!G12) | H163: =IF('KPIs & Ratios'!H12=0,"",'KPIs & Ratios'!H12) | J163: FY30E | K163: ='KPIs & Ratios'!L95 -> 198928.52
B164: Customer Base (Lakh) | E164: ='KPIs & Ratios'!E14 -> 11 | F164: ='KPIs & Ratios'!F14 -> 15 | G164: ='KPIs & Ratios'!G14 -> 18 | H164: ='KPIs & Ratios'!H14 -> 22 | J164: FY31E | K164: ='KPIs & Ratios'!M95 -> 246011.83
B165: Branch Network (count) | H165: 500
J166: FY24 | K166: ='KPIs & Ratios'!F21 -> 1949.26
B167: PROFITABILITY | J167: FY25 | K167: ='KPIs & Ratios'!G21 -> 2359.41
B168: Net Interest Income incl. fee/other income (₹ Cr) | E168: 1414.75 | F168: 2196.72 | G168: 2707.75 | H168: 4028.98 | J168: FY26 | K168: ='KPIs & Ratios'!H21 -> 3374.14
B169: Pre-Provisioning Operating Profit – PPOP (₹ Cr) | D169: 453 | E169: 611.7 | F169: 1389.36 | G169: 1417.18 | H169: 1933.53 | J169: FY27E | K169: ='KPIs & Ratios'!I21 -> 5761.7377
B170: Profit After Tax (₹ Cr) | D170: 293 | E170: 584.94 | F170: 2055.96 | G170: -98.34 | H170: 541.81 | J170: FY28E | K170: ='KPIs & Ratios'!J21 -> 8195.5298
B171: PAT (Consolidated, per Statement of P&L in this workbook) (₹ Cr) | C171: ='Profit & Loss'!C38 -> -558.9644 | D171: ='Profit & Loss'!D38 -> 375.41 | E171: ='Profit & Loss'!E38 -> 685.03 | F171: ='Profit & Loss'!F38 -> 1683.06 | G171: ='Profit & Loss'!G38 -> -98.34 | H171: ='Profit & Loss'!H38 -> 541.81 | J171: FY29E | K171: ='KPIs & Ratios'!K21 -> 10726.008
B172: Return on Assets – ROA % | C172: -3.7 | D172: 2.7 | E172: 4.4 | F172: 5.24 | G172: -0.35 | H172: 1.16 | J172: FY30E | K172: ='KPIs & Ratios'!L21 -> 13286.769
B173: Return on Equity – ROE % (Consolidated) | C173: -22.8 | D173: 7 | J173: FY31E | K173: ='KPIs & Ratios'!M21 -> 16306.535
B174: Net Interest Margin – NIM % | C174: 8.2 | D174: 9.81 | E174: 10.7 | F174: 11.2
J175: FY24 | K175: ='KPIs & Ratios'!F44 -> 1.16 | L175: =$O$158 -> 0
B176: ASSET QUALITY & CAPITAL | J176: FY25 | K176: ='KPIs & Ratios'!G44 -> 1.84 | L176: =$O$158 -> 0
B177: Gross NPA % | D177: 3.29 | E177: 1.44 | F177: 1.16 | G177: 1.84 | H177: 1.44 | J177: FY26 | K177: ='KPIs & Ratios'!H44 -> 1.44 | L177: =$O$158 -> 0
B178: Net NPA % | D178: 1.3 | E178: 0.78 | F178: 0.59 | G178: 0.85 | H178: 0.74 | J178: FY27E | K178: ='KPIs & Ratios'!I44 -> 1.35 | L178: =$O$158 -> 0
B179: Capital Adequacy Ratio – CRAR % (Standalone) | D179: 49.06 | F179: 33.8 | G179: 22.94 | H179: 16.83 | J179: FY28E | K179: ='KPIs & Ratios'!J44 -> 1.3 | L179: =$O$158 -> 0
B180: Shareholders' Funds, net of treasury shares (₹ Cr) | F180: 8116 | G180: 8124 | H180: 10298 | J180: FY29E | K180: ='KPIs & Ratios'!K44 -> 1.25 | L180: =$O$158 -> 0
J181: FY30E | K181: ='KPIs & Ratios'!L44 -> 1.2 | L181: =$O$158 -> 0
B182: COST & EFFICIENCY | J182: FY31E | K182: ='KPIs & Ratios'!M44 -> 1.15 | L182: =$O$158 -> 0
B183: Total Income, Standalone (₹ Cr) – input | E183: 2010.03 | F183: 3151.82 | G183: 4222.84 | H183: 6795.65
B184: Operating Expenses, Standalone (₹ Cr) – input | E184: 803.05 | F184: 807.36 | G184: 1290.57 | H184: 2095.45 | J184: FY24 | K184: ='KPIs & Ratios'!F45 -> 0.59 | L184: =$O$159 -> 0
B185: Cost-to-Income Ratio % | D185: =IFERROR('KPIs & Ratios'!D30*100,"") -> 56.734339 | E185: ='KPIs & Ratios'!E30*100 -> 56.832979 | F185: =F184/F168*100 -> 36.752977 | G185: =G184/G168*100 -> 47.662081 | H185: =H184/H168*100 -> 52.009442 | J185: FY25 | K185: ='KPIs & Ratios'!G45 -> 0.85 | L185: =$O$159 -> 0
B186: Cost of Borrowing % | F186: 8.06 | G186: 8.09 | H186: 7.73 | J186: FY26 | K186: ='KPIs & Ratios'!H45 -> 0.74 | L186: =$O$159 -> 0
J187: FY27E | K187: ='KPIs & Ratios'!I45 -> 0.68 | L187: =$O$159 -> 0
B188: LATEST QUARTER UPDATE — Q1 FY2027 (Quarter Ended 30-Jun-2026) | J188: FY28E | K188: ='KPIs & Ratios'!J45 -> 0.63 | L188: =$O$159 -> 0
...

Sheet Business Drivers
B1: POONAWALLA FINCORP LIMITED — Business Drivers (Customers → Loan Size → Disbursement → AUM) | L1: ⌂ Home
B2: This is the core driver chain. AUM is DERIVED from Customers, Avg Loan Size, Cross-sell and Portfolio Runoff — it is not assumed directly. Branches and Employees are forecast separately and feed the Operating Cost Forecast sheet.
B4: Particulars | C4: FY2026A | D4: FY2027E | E4: FY2028E | F4: FY2029E | G4: FY2030E | H4: FY2031E | I4: Rationale / Source
B6: 1. CUSTOMER & DISBURSEMENT DRIVERS
B7: New Customers Added (Lakh) — Base Case (scenario multiplier applied below) | D7: 7 | E7: 8 | F7: 8.5 | G7: 9 | H7: 9.5 | I7: Illustrative acquisition pace, scaled to branch expansion (row 25) and the Company's disclosed multi-product distribution build-out. FY2026A base: "over twenty two lakh customers" (AR FY2026 pg.35).
B8: Cross-sell Penetration Rate % (of prior cumulative customers) | C8: 0.27 | D8: 0.28 | E8: 0.3 | F8: 0.32 | G8: 0.33 | H8: 0.34 | I8: Linked from Customer Analytics tab (illustrative FY2026 rate 27%); gradual improvement assumed, consistent with the Company's stated "cross-sell to high-value cohorts at low acquisition cost" strategy (AR FY2025 pg.4).
B9: Cumulative Customers (Lakh) — scenario-adjusted | C9: 22 | D9: =C9+D7*'Scenario Analysis'!$C$16 -> 29 | E9: =D9+E7*'Scenario Analysis'!$C$16 -> 37 | F9: =E9+F7*'Scenario Analysis'!$C$16 -> 45.5 | G9: =F9+G7*'Scenario Analysis'!$C$16 -> 54.5 | H9: =G9+H7*'Scenario Analysis'!$C$16 -> 64 | I9: FY2026A: "over twenty two lakh customers as of March 31, 2026" (AR FY2026 pg.35).
B10: Average Loan Size (₹ Lakh) | D10: 3.8 | E10: 3.95 | F10: 4.1 | G10: 4.25 | H10: 4.4 | I10: Illustrative blended ticket size across the secured (LAP ~₹3-8L, Gold Loan smaller) and unsecured (Personal/Business Loan ~₹1-3L) mix, rising gradually with ticket-size inflation. Individual product ticket ranges disclosed in AR FY2026 pg.60-61.
B12: Disbursement to New Customers (₹ Cr) — scenario-adjusted | D12: =D7*'Scenario Analysis'!$C$16*D10*1000 -> 26600 | E12: =E7*'Scenario Analysis'!$C$16*E10*1000 -> 31600 | F12: =F7*'Scenario Analysis'!$C$16*F10*1000 -> 34850 | G12: =G7*'Scenario Analysis'!$C$16*G10*1000 -> 38250 | H12: =H7*'Scenario Analysis'!$C$16*H10*1000 -> 41800
B13: Disbursement to Existing Customers / Cross-sell (₹ Cr) | D13: =C9*D8*D10*1000 -> 23408 | E13: =D9*E8*E10*1000 -> 34365 | F13: =E9*F8*F10*1000 -> 48544 | G13: =F9*G8*G10*1000 -> 63813.75 | H13: =G9*H8*H10*1000 -> 81532
B14: Total Disbursement (₹ Cr) | D14: =D12+D13 -> 50008 | E14: =E12+E13 -> 65965 | F14: =F12+F13 -> 83394 | G14: =G12+G13 -> 102063.75 | H14: =H12+H13 -> 123332
B16: 2. LOAN BOOK ROLL-FORWARD (AUM is DERIVED here, not assumed)
B17: Portfolio Runoff Rate % (repayments/amortisation, % of opening AUM) | D17: 0.35 | E17: 0.35 | F17: 0.35 | G17: 0.35 | H17: 0.35 | I17: Illustrative assumption for a mixed-tenure retail/MSME book (loan tenures typically range 6-72 months per AR FY2026 pg.60-61); ~35% straight-line runoff approximates a blended average tenure of ~3 years. Held flat as the mix is assumed broadly stable.
B18: Opening AUM (₹ Cr) | D18: =C21 -> 55951.49 | E18: =D21 -> 86376.468 | F18: =E21 -> 122109.7 | G18: =F21 -> 162765.31 | H18: =G21 -> 207861.2
B19: (+) Disbursements (₹ Cr) | D19: =D14 -> 50008 | E19: =E14 -> 65965 | F19: =F14 -> 83394 | G19: =G14 -> 102063.75 | H19: =H14 -> 123332
B20: (−) Repayments / Runoff (₹ Cr) | D20: =-D18*D17 -> -19583.021 | E20: =-E18*E17 -> -30231.764 | F20: =-F18*F17 -> -42738.397 | G20: =-G18*G17 -> -56967.858 | H20: =-H18*H17 -> -72751.42
B21: Closing AUM / Loan Book (₹ Cr) | C21: ='Balance Sheet'!H14 -> 55951.49 | D21: =D18+D19+D20 -> 86376.468 | E21: =E18+E19+E20 -> 122109.7 | F21: =F18+F19+F20 -> 162765.31 | G21: =G18+G19+G20 -> 207861.2 | H21: =H18+H19+H20 -> 258441.78
B22: AUM Growth % YoY | D22: =IFERROR(D21/C21-1,"") -> 0.54377423 | E22: =IFERROR(E21/D21-1,"") -> 0.41369179 | F22: =IFERROR(F21/E21-1,"") -> 0.33294326 | G22: =IFERROR(G21/F21-1,"") -> 0.27706084 | H22: =IFERROR(H21/G21-1,"") -> 0.24333825
B23: (Memo) AUM as multiple of FY2025A base (₹35,631 Cr) | D23: =IFERROR(D21/35631,"") -> 2.4241943 | E23: =IFERROR(E21/35631,"") -> 3.4270636 | F23: =IFERROR(F21/35631,"") -> 4.5680814 | G23: =IFERROR(G21/35631,"") -> 5.8337178 | H23: =IFERROR(H21/35631,"") -> 7.2532845 | I23: Cross-check vs management's disclosed guidance of "5-6x AUM growth over the next 5 years (FY25 onwards)" (AR FY2026 pg.2-3). FY2030E (5 years from FY25) shows here.
B25: 3. BRANCH & EMPLOYEE DRIVERS
B26: Net Branch Additions (count, linked from Assumptions) | D26: =Assumptions!D13 -> 150 | E26: =Assumptions!E13 -> 130 | F26: =Assumptions!F13 -> 100 | G26: =Assumptions!G13 -> 90 | H26: =Assumptions!H13 -> 80
B27: Branch Count (cumulative) | C27: 500 | D27: =C27+D26 -> 650 | E27: =D27+E26 -> 780 | F27: =E27+F26 -> 880 | G27: =F27+G26 -> 970 | H27: =G27+H26 -> 1050 | I27: FY2026A: "500+ branches (including 400 gold loan branches)" (AR FY2026 pg.2).
B28: Employees per Branch (linked from Assumptions) | C28: =Assumptions!C14 -> 11.72 | D28: =Assumptions!D14 -> 11.5 | E28: =Assumptions!E14 -> 11.2 | F28: =Assumptions!F14 -> 11 | G28: =Assumptions!G14 -> 10.8 | H28: =Assumptions!H14 -> 10.6
B29: Employees (count) | C29: 5860 | D29: =ROUND(D27*D28,0) -> 7475 | E29: =ROUND(E27*E28,0) -> 8736 | F29: =ROUND(F27*F28,0) -> 9680 | G29: =ROUND(G27*G28,0) -> 10476 | H29: =ROUND(H27*H28,0) -> 11130 | I29: FY2026A: "5,860 Employees" (AR FY2026 pg.4). Forecast = Branch Count × Employees per Branch ratio (row 28).
B30: Average AUM per Branch (₹ Cr) | C30: =IFERROR(C21/C27,"") -> 111.90298 | D30: =IFERROR(AVERAGE(C21,D21)/AVERAGE(C27,D27),"") -> 123.76344 | E30: =IFERROR(AVERAGE(D21,E21)/AVERAGE(D27,E27),"") -> 145.79453 | F30: =IFERROR(AVERAGE(E21,F21)/AVERAGE(E27,F27),"") -> 171.61145 | G30: =IFERROR(AVERAGE(F21,G21)/AVERAGE(F27,G27),"") -> 200.33865 | H30: =IFERROR(AVERAGE(G21,H21)/AVERAGE(G27,H27),"") -> 230.84306

Sheet KPIs & Ratios
B1: POONAWALLA FINCORP LIMITED — NBFC KPIs & Financial Ratios (Consolidated) | O1: ⌂ Home
B2: All ratios below are LIVE FORMULAS linked to the Balance Sheet, Profit & Loss, and Treasury sheets (FY2021-FY2026A) and to the integrated forecast sheets — Business Drivers, Funding/Credit Cost Forecast — for FY2027E-FY2031E. Ratios requiring an opening balance (Average-based) start from FY2022. Rows that depend on tabs without a forecast extension (Customer Analytics, Branch/Product Profitability, Treasury, Executive Dashboard's disclosed-only metrics) are left blank for FY2027E-FY2031E with a note, rather than estimated.
B4: Particulars | C4: FY2021 | D4: FY2022 | E4: FY2023 | F4: FY2024 | G4: FY2025 | H4: FY2026 | I4: FY2027E | J4: FY2028E | K4: FY2029E | L4: FY2030E | M4: FY2031E
B6: GROWTH METRICS (YoY %)
B7: Total Assets Growth % | D7: =IFERROR('Balance Sheet'!D31/'Balance Sheet'!C31-1,"") -> 0.24451057 | E7: =IFERROR('Balance Sheet'!E31/'Balance Sheet'!D31-1,"") -> 0.41221388 | F7: =IFERROR('Balance Sheet'!F31/'Balance Sheet'!E31-1,"") -> 0.037306944 | G7: =IFERROR('Balance Sheet'!G31/'Balance Sheet'!F31-1,"") -> 0.454315 | H7: =IFERROR('Balance Sheet'!H31/'Balance Sheet'!G31-1,"") -> 0.72057274 | I7: =IFERROR('Balance Sheet'!I31/'Balance Sheet'!H31-1,"") -> 0.54766136 | J7: =IFERROR('Balance Sheet'!J31/'Balance Sheet'!I31-1,"") -> 0.39662582 | K7: =IFERROR('Balance Sheet'!K31/'Balance Sheet'!J31-1,"") -> 0.32172306 | ... M7: =IFERROR('Balance Sheet'!M31/'Balance Sheet'!L31-1,"") -> 0.23633683
B8: Loans / AUM Growth % (Reported, Standalone — linked from Executive Dashboard) | E8: ='Business Performance Scorecard'!E162 -> 0.3721207 | F8: ='Business Performance Scorecard'!F162 -> 0.5488447 | G8: ='Business Performance Scorecard'!G162 -> 0.42506899 | H8: ='Business Performance Scorecard'!H162 -> 0.69369369 | I8: ='Business Drivers'!D22 -> 0.54377423 | J8: ='Business Drivers'!E22 -> 0.41369179 | K8: ='Business Drivers'!F22 -> 0.33294326 | L8: ='Business Drivers'!G22 -> 0.27706084 | M8: ='Business Drivers'!H22 -> 0.24333825
B9: Total Income Growth % | D9: =IFERROR('Profit & Loss'!D15/'Profit & Loss'!C15-1,"") -> -0.13239153 | E9: =IFERROR('Profit & Loss'!E15/'Profit & Loss'!D15-1,"") -> -0.016045531 | F9: =IFERROR('Profit & Loss'!F15/'Profit & Loss'!E15-1,"") -> 0.56717689 | G9: =IFERROR('Profit & Loss'!G15/'Profit & Loss'!F15-1,"") -> 0.3417214 | H9: =IFERROR('Profit & Loss'!H15/'Profit & Loss'!G15-1,"") -> 0.60926059 | I9: =IFERROR('Profit & Loss'!I15/'Profit & Loss'!H15-1,"") -> 0.65553092 | J9: =IFERROR('Profit & Loss'!J15/'Profit & Loss'!I15-1,"") -> 0.4180989 | K9: =IFERROR('Profit & Loss'!K15/'Profit & Loss'!J15-1,"") -> 0.31711665 | ... M9: =IFERROR('Profit & Loss'!M15/'Profit & Loss'!L15-1,"") -> 0.23602943
B10: PAT Growth % | D10: =IFERROR('Profit & Loss'!D38/'Profit & Loss'!C38-1,"") -> -1.671617 | E10: =IFERROR('Profit & Loss'!E38/'Profit & Loss'!D38-1,"") -> 0.8247516 | F10: =IFERROR('Profit & Loss'!F38/'Profit & Loss'!E38-1,"") -> 1.4569143 | G10: =IFERROR('Profit & Loss'!G38/'Profit & Loss'!F38-1,"") -> -1.0584293 | H10: =IFERROR('Profit & Loss'!H38/'Profit & Loss'!G38-1,"") -> -6.5095587 | I10: =IFERROR('Profit & Loss'!I38/'Profit & Loss'!H38-1,"") -> 2.2887415 | J10: =IFERROR('Profit & Loss'!J38/'Profit & Loss'!I38-1,"") -> 0.74956607 | K10: =IFERROR('Profit & Loss'!K38/'Profit & Loss'!J38-1,"") -> 0.44824919 | ... M10: =IFERROR('Profit & Loss'!M38/'Profit & Loss'!L38-1,"") -> 0.31864324
B11: Net Worth (Total Equity) Growth % | D11: =IFERROR('Balance Sheet'!D55/'Balance Sheet'!C55-1,"") -> 1.7608842 | E11: =IFERROR('Balance Sheet'!E55/'Balance Sheet'!D55-1,"") -> 0.13451964 | F11: =IFERROR('Balance Sheet'!F55/'Balance Sheet'!E55-1,"") -> 0.1882552 | G11: =IFERROR('Balance Sheet'!G55/'Balance Sheet'!F55-1,"") -> 0.00092811629 | H11: =IFERROR('Balance Sheet'!H55/'Balance Sheet'!G55-1,"") -> 0.2658924 | I11: =IFERROR('Balance Sheet'!I55/'Balance Sheet'!H55-1,"") -> 0.65364962 | J11: =IFERROR('Balance Sheet'!J55/'Balance Sheet'!I55-1,"") -> 0.4324948 | K11: =IFERROR('Balance Sheet'!K55/'Balance Sheet'!J55-1,"") -> 0.33728963 | ... M11: =IFERROR('Balance Sheet'!M55/'Balance Sheet'!L55-1,"") -> 0.24009603
B12: Disbursements (₹ Cr, company-disclosed) | C12: 3680.21 | D12: 7524 | E12: 15751 | F12: 33289 | I12: ='Business Drivers'!D14 -> 50008 | J12: ='Business Drivers'!E14 -> 65965 | K12: ='Business Drivers'!F14 -> 83394 | L12: ='Business Drivers'!G14 -> 102063.75 | M12: ='Business Drivers'!H14 -> 123332
B13: Disbursement Growth % | D13: =IFERROR(D12/C12-1,"") -> 1.0444486 | E13: =IFERROR(E12/D12-1,"") -> 1.0934343 | F13: =IFERROR(F12/E12-1,"") -> 1.1134531 | I13: =IFERROR(I12/H12-1,"") | J13: =IFERROR(J12/I12-1,"") -> 0.31908895 | K13: =IFERROR(K12/J12-1,"") -> 0.26421587 | L13: =IFERROR(L12/K12-1,"") -> 0.22387402 | M13: =IFERROR(M12/L12-1,"") -> 0.20838202
B14: Customer Base (Lakh, linked from Customer Analytics tab) | E14: ='Customer Analytics'!C5 -> 11 | F14: ='Customer Analytics'!D5 -> 15 | G14: ='Customer Analytics'!E5 -> 18 | H14: ='Customer Analytics'!F5 -> 22 | I14: ='Business Drivers'!D9 -> 29 | J14: ='Business Drivers'!E9 -> 37 | K14: ='Business Drivers'!F9 -> 45.5 | L14: ='Business Drivers'!G9 -> 54.5 | M14: ='Business Drivers'!H9 -> 64
B15: Customer Growth % | F15: =IFERROR(F14/E14-1,"") -> 0.36363636 | G15: =IFERROR(G14/F14-1,"") -> 0.2 | H15: =IFERROR(H14/G14-1,"") -> 0.22222222 | I15: =IFERROR(I14/H14-1,"") -> 0.31818182 | J15: =IFERROR(J14/I14-1,"") -> 0.27586207 | K15: =IFERROR(K14/J14-1,"") -> 0.22972973 | L15: =IFERROR(L14/K14-1,"") -> 0.1978022 | M15: =IFERROR(M14/L14-1,"") -> 0.17431193
B16: Market Share % — not numerically disclosed by the Company (only qualitative “gaining market share each year”, AR FY2025 pg.4); left blank rather than estimated
B17: Number of Loan Products (count, company-disclosed) | H17: 13
B18: Cross-sell / Repeat Rate % (illustrative — linked from Customer Analytics tab) | E18: ='Customer Analytics'!C8 -> 0.18 | F18: ='Customer Analytics'!D8 -> 0.21 | G18: ='Customer Analytics'!E8 -> 0.24 | H18: ='Customer Analytics'!F8 -> 0.27
B20: PROFITABILITY RATIOS
B21: Net Interest Income – NII (₹ Cr) [Interest Income − Finance Costs] | C21: ='Profit & Loss'!C8-'Profit & Loss'!C17 -> 1065.2235 | D21: ='Profit & Loss'!D8-'Profit & Loss'!D17 -> 1194.3176 | E21: ='Profit & Loss'!E8-'Profit & Loss'!E17 -> 1219.91 | F21: ='Profit & Loss'!F8-'Profit & Loss'!F17 -> 1949.26 | G21: ='Profit & Loss'!G8-'Profit & Loss'!G17 -> 2359.41 | H21: ='Profit & Loss'!H8-'Profit & Loss'!H17 -> 3374.14 | I21: ='Profit & Loss'!I8-'Profit & Loss'!I17 -> 5761.7377 | J21: ='Profit & Loss'!J8-'Profit & Loss'!J17 -> 8195.5298 | ... M21: ='Profit & Loss'!M8-'Profit & Loss'!M17 -> 16306.535
B22: Average Total Assets (₹ Cr) | D22: =AVERAGE('Balance Sheet'!C31,'Balance Sheet'!D31) -> 14827.442 | E22: =AVERAGE('Balance Sheet'!D31,'Balance Sheet'!E31) -> 19831.655 | F22: =AVERAGE('Balance Sheet'!E31,'Balance Sheet'!F31) -> 23653.755 | G22: =AVERAGE('Balance Sheet'!F31,'Balance Sheet'!G31) -> 29558.42 | H22: =AVERAGE('Balance Sheet'!G31,'Balance Sheet'!H31) -> 47650.75 | I22: =AVERAGE('Balance Sheet'!H31,'Balance Sheet'!I31) -> 76775.762 | J22: =AVERAGE('Balance Sheet'!I31,'Balance Sheet'!J31) -> 111778.59 | K22: =AVERAGE('Balance Sheet'!J31,'Balance Sheet'!K31) -> 151233.8 | ... M22: =AVERAGE('Balance Sheet'!L31,'Balance Sheet'!M31) -> 244179.95
B23: Net Interest Margin – NIM % (NII ÷ Avg. Total Assets) | D23: =IFERROR(D21/D22,"") -> 0.080547787 | E23: =IFERROR(E21/E22,"") -> 0.061513272 | F23: =IFERROR(F21/F22,"") -> 0.082408057 | G23: =IFERROR(G21/G22,"") -> 0.079821926 | H23: =IFERROR(H21/H22,"") -> 0.070809798 | I23: =IFERROR(I21/I22,"") -> 0.07504631 | J23: =IFERROR(J21/J22,"") -> 0.07331932 | K23: =IFERROR(K21/K22,"") -> 0.070923355 | ... M23: =IFERROR(M21/M22,"") -> 0.066780811
B24: Average Loans (₹ Cr) | D24: =AVERAGE('Balance Sheet'!C14,'Balance Sheet'!D14) -> 13105.963 | E24: =AVERAGE('Balance Sheet'!D14,'Balance Sheet'!E14) -> 15034.614 | F24: =AVERAGE('Balance Sheet'!E14,'Balance Sheet'!F14) -> 18632.47 | G24: =AVERAGE('Balance Sheet'!F14,'Balance Sheet'!G14) -> 27370.685 | H24: =AVERAGE('Balance Sheet'!G14,'Balance Sheet'!H14) -> 44323.225 | I24: =AVERAGE('Balance Sheet'!H14,'Balance Sheet'!I14) -> 70381.175 | J24: =AVERAGE('Balance Sheet'!I14,'Balance Sheet'!J14) -> 101687.17 | K24: =AVERAGE('Balance Sheet'!J14,'Balance Sheet'!K14) -> 137680.56 | ... M24: =AVERAGE('Balance Sheet'!L14,'Balance Sheet'!M14) -> 222470.18
B25: Yield on Advances % (Interest Income ÷ Avg. Loans) | D25: =IFERROR('Profit & Loss'!D8/D24,"") -> 0.14577237 | E25: =IFERROR('Profit & Loss'!E8/E24,"") -> 0.12073406 | F25: =IFERROR('Profit & Loss'!F8/F24,"") -> 0.15561866 | G25: =IFERROR('Profit & Loss'!G8/G24,"") -> 0.14155656 | H25: =IFERROR('Profit & Loss'!H8/H24,"") -> 0.1385461 | I25: =IFERROR('Profit & Loss'!I8/I24,"") -> 0.14661274 | J25: =IFERROR('Profit & Loss'!J8/J24,"") -> 0.14351891 | K25: =IFERROR('Profit & Loss'!K8/K24,"") -> 0.13966433 | ... M25: =IFERROR('Profit & Loss'!M8/M24,"") -> 0.13309757
B26: Cost of Funds % (Finance Costs ÷ Avg. Borrowings, linked from Treasury) | D26: =IFERROR(Treasury!D19/100,"") -> 0.070413329 | E26: =IFERROR(Treasury!E19/100,"") -> 0.056616741 | F26: =IFERROR(Treasury!F19/100,"") -> 0.072542788 | G26: =IFERROR(Treasury!G19/100,"") -> 0.073977776 | H26: =IFERROR(Treasury!H19/100,"") -> 0.074796242 | I26: ='Funding Forecast'!D10 -> 0.075 | J26: ='Funding Forecast'!E10 -> 0.073 | K26: ='Funding Forecast'!F10 -> 0.072 | L26: ='Funding Forecast'!G10 -> 0.071 | M26: ='Funding Forecast'!H10 -> 0.07
B27: Interest Spread % (Yield − Cost of Funds) | D27: =IFERROR(D25-D26,"") -> 0.075359036 | E27: =IFERROR(E25-E26,"") -> 0.064117317 | F27: =IFERROR(F25-F26,"") -> 0.083075872 | G27: =IFERROR(G25-G26,"") -> 0.067578784 | H27: =IFERROR(H25-H26,"") -> 0.063749858 | I27: =IFERROR(I25-I26,"") -> 0.07161274 | J27: =IFERROR(J25-J26,"") -> 0.070518914 | K27: =IFERROR(K25-K26,"") -> 0.06766433 | ... M27: =IFERROR(M25-M26,"") -> 0.063097566
B28: Operating Expenses (₹ Cr) [Employee costs + D&A + Other expenses] | C28: ='Profit & Loss'!C21+'Profit & Loss'!C22+'Profit & Loss'!C23 -> 558.2843 | D28: ='Profit & Loss'!D21+'Profit & Loss'!D22+'Profit & Loss'!D23 -> 751.6504 | E28: ='Profit & Loss'!E21+'Profit & Loss'!E22+'Profit & Loss'!E23 -> 803.05 | F28: ='Profit & Loss'!F21+'Profit & Loss'!F22+'Profit & Loss'!F23 -> 807.36 | G28: ='Profit & Loss'!G21+'Profit & Loss'!G22+'Profit & Loss'!G23 -> 1276.85 | H28: ='Profit & Loss'!H21+'Profit & Loss'!H22+'Profit & Loss'!H23 -> 2095.45 | I28: ='Profit & Loss'!I21+'Profit & Loss'!I22+'Profit & Loss'!I23 -> 2746.5337 | J28: ='Profit & Loss'!J21+'Profit & Loss'!J22+'Profit & Loss'!J23 -> 3408.9553 | ... M28: ='Profit & Loss'!M21+'Profit & Loss'!M22+'Profit & Loss'!M23 -> 5376.0881
B29: Net Total Income (₹ Cr) [Total Income − Finance Costs] | C29: ='Profit & Loss'!C15-'Profit & Loss'!C17 -> 1252.0235 | D29: ='Profit & Loss'!D15-'Profit & Loss'!D17 -> 1324.8597 | E29: ='Profit & Loss'!E15-'Profit & Loss'!E17 -> 1413 | F29: ='Profit & Loss'!F15-'Profit & Loss'!F17 -> 2197.03 | G29: ='Profit & Loss'!G15-'Profit & Loss'!G17 -> 2707.75 | H29: ='Profit & Loss'!H15-'Profit & Loss'!H17 -> 4028.98 | I29: ='Profit & Loss'!I15-'Profit & Loss'!I17 -> 6693.3694 | J29: ='Profit & Loss'!J15-'Profit & Loss'!J17 -> 9555.6899 | ... M29: ='Profit & Loss'!M15-'Profit & Loss'!M17 -> 19340.005
B30: Cost-to-Income Ratio % (Opex ÷ Net Total Income) | C30: =IFERROR(C28/C29,"") -> 0.44590561 | D30: =IFERROR(D28/D29,"") -> 0.56734339 | E30: =IFERROR(E28/E29,"") -> 0.56832979 | F30: =IFERROR(F28/F29,"") -> 0.36747791 | G30: =IFERROR(G28/G29,"") -> 0.47155387 | H30: =IFERROR(H28/H29,"") -> 0.52009442 | I30: =IFERROR(I28/I29,"") -> 0.41033648 | J30: =IFERROR(J28/J29,"") -> 0.35674611 | ... M30: =IFERROR(M28/M29,"") -> 0.2779776
B31: Pre-Provisioning Operating Profit – PPOP (₹ Cr) [Net Total Income − Opex] | C31: =C29-C28 -> 693.7392 | D31: =D29-D28 -> 573.2093 | E31: =E29-E28 -> 609.95 | F31: =F29-F28 -> 1389.67 | G31: =G29-G28 -> 1430.9 | H31: =H29-H28 -> 1933.53 | I31: =I29-I28 -> 3946.8357 | J31: =J29-J28 -> 6146.7347 | ... M31: =M29-M28 -> 13963.917
B32: Average Total Equity (₹ Cr) | D32: =AVERAGE('Balance Sheet'!C55,'Balance Sheet'!D55) -> 4126.2624 | E32: =AVERAGE('Balance Sheet'!D55,'Balance Sheet'!E55) -> 6465.6952 | F32: =AVERAGE('Balance Sheet'!E55,'Balance Sheet'!F55) -> 7520.125 | G32: =AVERAGE('Balance Sheet'!F55,'Balance Sheet'!G55) -> 8170.87 | H32: =AVERAGE('Balance Sheet'!G55,'Balance Sheet'!H55) -> 9261.45 | I32: =AVERAGE('Balance Sheet'!H55,'Balance Sheet'!I55) -> 13730.302 | J32: =AVERAGE('Balance Sheet'!I55,'Balance Sheet'!J55) -> 20812.867 | K32: =AVERAGE('Balance Sheet'!J55,'Balance Sheet'!K55) -> 28647.424 | ... M32: =AVERAGE('Balance Sheet'!L55,'Balance Sheet'!M55) -> 46874.511
B33: Return on Assets – ROA % (PAT ÷ Avg. Total Assets) | D33: =IFERROR('Profit & Loss'!D38/D22,"") -> 0.025318596 | E33: =IFERROR('Profit & Loss'!E38/E22,"") -> 0.03454225 | F33: =IFERROR('Profit & Loss'!F38/F22,"") -> 0.07115403 | G33: =IFERROR('Profit & Loss'!G38/G22,"") -> -0.0033269708 | H33: =IFERROR('Profit & Loss'!H38/H22,"") -> 0.01137044 | I33: =IFERROR('Profit & Loss'!I38/I22,"") -> 0.023208797 | J33: =IFERROR('Profit & Loss'!J38/J22,"") -> 0.027889999 | K33: =IFERROR('Profit & Loss'!K38/K22,"") -> 0.029853932 | ... M33: =IFERROR('Profit & Loss'!M38/M22,"") -> 0.032075483
B34: Return on Equity – ROE % (PAT ÷ Avg. Total Equity) | D34: =IFERROR('Profit & Loss'!D38/D32,"") -> 0.090980641 | E34: =IFERROR('Profit & Loss'!E38/E32,"") -> 0.10594839 | F34: =IFERROR('Profit & Loss'!F38/F32,"") -> 0.22380745 | G34: =IFERROR('Profit & Loss'!G38/G32,"") -> -0.012035438 | H34: =IFERROR('Profit & Loss'!H38/H32,"") -> 0.058501639 | I34: =IFERROR('Profit & Loss'!I38/I32,"") -> 0.12977669 | J34: =IFERROR('Profit & Loss'!J38/J32,"") -> 0.14978737 | K34: =IFERROR('Profit & Loss'!K38/K32,"") -> 0.15760313 | ... M34: =IFERROR('Profit & Loss'!M38/M32,"") -> 0.16708846
B35: Profit After Tax – PAT (₹ Cr, linked from Profit & Loss) | C35: ='Profit & Loss'!C38 -> -558.9644 | D35: ='Profit & Loss'!D38 -> 375.41 | E35: ='Profit & Loss'!E38 -> 685.03 | F35: ='Profit & Loss'!F38 -> 1683.06 | G35: ='Profit & Loss'!G38 -> -98.34 | H35: ='Profit & Loss'!H38 -> 541.81 | I35: ='Profit & Loss'!I38 -> 1781.8731 | J35: ='Profit & Loss'!J38 -> 3117.5046 | ... M35: ='Profit & Loss'!M38 -> 7832.1898
B36: Fee & Commission Income (₹ Cr, linked from Profit & Loss) | C36: ='Profit & Loss'!C10 -> 71.6572 | D36: ='Profit & Loss'!D10 -> 63.917 | E36: ='Profit & Loss'!E10 -> 61.54 | F36: ='Profit & Loss'!F10 -> 73.22 | G36: ='Profit & Loss'!G10 -> 192.26 | H36: ='Profit & Loss'!H10 -> 419.75 | I36: ='Profit & Loss'!I10 -> 533.72984 | J36: ='Profit & Loss'!J10 -> 781.82315 | ... M36: ='Profit & Loss'!M10 -> 1981.7877
B37: Fee Income % of Total Income | C37: =IFERROR(C36/'Profit & Loss'!C15,"") -> 0.030460313 | D37: =IFERROR(D36/'Profit & Loss'!D15,"") -> 0.03131606 | E37: =IFERROR(E36/'Profit & Loss'!E15,"") -> 0.030643137 | F37: =IFERROR(F36/'Profit & Loss'!F15,"") -> 0.023264164 | G37: =IFERROR(G36/'Profit & Loss'!G15,"") -> 0.045528602 | H37: =IFERROR(H36/'Profit & Loss'!H15,"") -> 0.061767454 | I37: =IFERROR(I36/'Profit & Loss'!I15,"") -> 0.047440929 | J37: =IFERROR(J36/'Profit & Loss'!J15,"") -> 0.049004245 | ... M37: =IFERROR(M36/'Profit & Loss'!M15,"") -> 0.060709636
B38: Secured Lending Mix % (on-book AUM, company-disclosed) | F38: 0.49 | G38: 0.57 | H38: 0.54 | I38: 0.52 | J38: 0.51 | K38: 0.505 | L38: 0.5 | M38: 0.5
B39: Unsecured Lending Mix % | F39: =IFERROR(1-F38,"") -> 0.51 | G39: =IFERROR(1-G38,"") -> 0.43 | H39: =IFERROR(1-H38,"") -> 0.46 | I39: =IFERROR(1-I38,"") -> 0.48 | J39: =IFERROR(1-J38,"") -> 0.49 | K39: =IFERROR(1-K38,"") -> 0.495 | L39: =IFERROR(1-L38,"") -> 0.5 | M39: =IFERROR(1-M38,"") -> 0.5
B40: Operating Leverage (ppt) = Total Income Growth % − Opex Growth % | D40: =IFERROR(D9-(D28/C28-1),"") -> -0.47874929 | E40: =IFERROR(E9-(E28/D28-1),"") -> -0.084427853 | F40: =IFERROR(F9-(F28/E28-1),"") -> 0.56180985 | G40: =IFERROR(G9-(G28/F28-1),"") -> -0.23979119 | H40: =IFERROR(H9-(H28/G28-1),"") -> -0.031848387 | I40: =IFERROR(I9-(I28/H28-1),"") -> 0.34481787 | J40: =IFERROR(J9-(J28/I28-1),"") -> 0.17691431 | K40: =IFERROR(K9-(K28/J28-1),"") -> 0.12746615 | ... M40: =IFERROR(M9-(M28/L28-1),"") -> 0.093090038
B42: ASSET QUALITY
B43: Credit Cost % (Impairment on Fin. Instruments ÷ Avg. Loans) | D43: =IFERROR('Profit & Loss'!D20/D24,"") -> 0.0059181303 | E43: =IFERROR('Profit & Loss'!E20/E24,"") -> -0.0096131498 | F43: =IFERROR('Profit & Loss'!F20/F24,"") -> 0.0038652954 | G43: =IFERROR('Profit & Loss'!G20/G24,"") -> 0.053274882 | H43: =IFERROR('Profit & Loss'!H20/H24,"") -> 0.024910868 | I43: ='Credit Cost Forecast'!D10 -> 0.022 | J43: ='Credit Cost Forecast'!E10 -> 0.019 | K43: ='Credit Cost Forecast'!F10 -> 0.017 | L43: ='Credit Cost Forecast'!G10 -> 0.016 | M43: ='Credit Cost Forecast'!H10 -> 0.015
B44: Gross NPA % (linked, company-disclosed) | D44: ='Business Performance Scorecard'!D177 -> 3.29 | E44: ='Business Performance Scorecard'!E177 -> 1.44 | F44: ='Business Performance Scorecard'!F177 -> 1.16 | G44: ='Business Performance Scorecard'!G177 -> 1.84 | H44: ='Business Performance Scorecard'!H177 -> 1.44 | I44: ='Credit Cost Forecast'!D6*100 -> 1.35 | J44: ='Credit Cost Forecast'!E6*100 -> 1.3 | K44: ='Credit Cost Forecast'!F6*100 -> 1.25 | L44: ='Credit Cost Forecast'!G6*100 -> 1.2 | M44: ='Credit Cost Forecast'!H6*100 -> 1.15
B45: Net NPA % (linked, company-disclosed) | D45: ='Business Performance Scorecard'!D178 -> 1.3 | E45: ='Business Performance Scorecard'!E178 -> 0.78 | F45: ='Business Performance Scorecard'!F178 -> 0.59 | G45: ='Business Performance Scorecard'!G178 -> 0.85 | H45: ='Business Performance Scorecard'!H178 -> 0.74 | I45: ='Credit Cost Forecast'!D7*100 -> 0.68 | J45: ='Credit Cost Forecast'!E7*100 -> 0.63 | K45: ='Credit Cost Forecast'!F7*100 -> 0.6 | L45: ='Credit Cost Forecast'!G7*100 -> 0.57 | M45: ='Credit Cost Forecast'!H7*100 -> 0.55
B46: Implied Provision Coverage Ratio % (1 − NNPA ÷ GNPA) | D46: =IFERROR(1-D45/D44,"") -> 0.60486322 | E46: =IFERROR(1-E45/E44,"") -> 0.45833333 | F46: =IFERROR(1-F45/F44,"") -> 0.49137931 | G46: =IFERROR(1-G45/G44,"") -> 0.53804348 | H46: =IFERROR(1-H45/H44,"") -> 0.48611111 | I46: =IFERROR(1-I45/I44,"") -> 0.4962963 | J46: =IFERROR(1-J45/J44,"") -> 0.51538462 | K46: =IFERROR(1-K45/K44,"") -> 0.52 | ... M46: =IFERROR(1-M45/M44,"") -> 0.52173913
B48: CAPITAL STRUCTURE & LEVERAGE
B49: Total Borrowings (₹ Cr, linked from Treasury) | C49: =Treasury!C9 -> 10433.049 | D49: =Treasury!D9 -> 9908.8293 | E49: =Treasury!E9 -> 11119.58 | F49: =Treasury!F9 -> 15080.13 | G49: =Treasury!G9 -> 25880.55 | H49: =Treasury!H9 -> 48098.3 | I49: ='Balance Sheet'!I39+'Balance Sheet'!I40+'Balance Sheet'!I41 -> 73402.767 | J49: ='Balance Sheet'!J39+'Balance Sheet'!J40+'Balance Sheet'!J41 -> 101898.67 | K49: ='Balance Sheet'!K39+'Balance Sheet'!K40+'Balance Sheet'!K41 -> 134297.31 | L49: ='Balance Sheet'!L39+'Balance Sheet'!L40+'Balance Sheet'!L41 -> 170039.42 | M49: ='Balance Sheet'!M39+'Balance Sheet'!M40+'Balance Sheet'!M41 -> 210066.41
B50: Debt-to-Equity Ratio (x) (Total Borrowings ÷ Total Equity) | C50: =IFERROR(C49/'Balance Sheet'!C55,"") -> 4.7546044 | D50: =IFERROR(D49/'Balance Sheet'!D55,"") -> 1.6356007 | E50: =IFERROR(E49/'Balance Sheet'!E55,"") -> 1.6178241 | F50: =IFERROR(F49/'Balance Sheet'!F55,"") -> 1.8464531 | G50: =IFERROR(G49/'Balance Sheet'!G55,"") -> 3.1659482 | H50: =IFERROR(H49/'Balance Sheet'!H55,"") -> 4.6479691 | I50: =IFERROR(I49/'Balance Sheet'!I55,"") -> 4.2894582 | J50: =IFERROR(J49/'Balance Sheet'!J55,"") -> 4.1568606 | ... M50: =IFERROR(M49/'Balance Sheet'!M55,"") -> 4.0476336
B51: Borrowings / Total Assets % | C51: =IFERROR(C49/'Balance Sheet'!C31,"") -> 0.78965374 | D51: =IFERROR(D49/'Balance Sheet'!D31,"") -> 0.60262785 | E51: =IFERROR(E49/'Balance Sheet'!E31,"") -> 0.47886683 | F51: =IFERROR(F49/'Balance Sheet'!F31,"") -> 0.62607185 | G51: =IFERROR(G49/'Balance Sheet'!G31,"") -> 0.73881228 | H51: =IFERROR(H49/'Balance Sheet'!H31,"") -> 0.79802647 | I51: =IFERROR(I49/'Balance Sheet'!I31,"") -> 0.78690818 | J51: =IFERROR(J49/'Balance Sheet'!J31,"") -> 0.78216803 | ... M51: =IFERROR(M49/'Balance Sheet'!M31,"") -> 0.77806705
B52: Equity / Total Assets % (Capitalisation Ratio) | C52: =IFERROR('Balance Sheet'!C55/'Balance Sheet'!C31,"") -> 0.1660819 | D52: =IFERROR('Balance Sheet'!D55/'Balance Sheet'!D31,"") -> 0.36844437 | E52: =IFERROR('Balance Sheet'!E55/'Balance Sheet'!E31,"") -> 0.29599438 | F52: =IFERROR('Balance Sheet'!F55/'Balance Sheet'!F31,"") -> 0.33906729 | G52: =IFERROR('Balance Sheet'!G55/'Balance Sheet'!G31,"") -> 0.23336209 | H52: =IFERROR('Balance Sheet'!H55/'Balance Sheet'!H31,"") -> 0.17169358 | I52: =IFERROR('Balance Sheet'!I55/'Balance Sheet'!I31,"") -> 0.18345165 | J52: =IFERROR('Balance Sheet'!J55/'Balance Sheet'!J31,"") -> 0.18816316 | ... M52: =IFERROR('Balance Sheet'!M55/'Balance Sheet'!M31,"") -> 0.19222764
B53: Capital Adequacy Ratio – CRAR % (FY21-26A disclosed; FY27E-31E from RWA schedule) | C53: =IF('Business Performance Scorecard'!C179=0,"",'Business Performance Scorecard'!C179) | D53: ='Business Performance Scorecard'!D179 -> 49.06 | E53: =IF('Business Performance Scorecard'!E179=0,"",'Business Performance Scorecard'!E179) | F53: ='Business Performance Scorecard'!F179 -> 33.8 | G53: ='Business Performance Scorecard'!G179 -> 22.94 | H53: ='Business Performance Scorecard'!H179 -> 16.83 | I53: ='Regulatory Capital'!D32*100 -> 18.601956 | J53: ='Regulatory Capital'!E32*100 -> 18.583348 | K53: ='Regulatory Capital'!F32*100 -> 18.574912 | L53: ='Regulatory Capital'!G32*100 -> 18.57018 | M53: ='Regulatory Capital'!H32*100 -> 18.56802
B54: Liquidity Coverage Ratio – LCR % (company-disclosed, standalone) | H54: 181
B55: Modelled RAROC % — weighted average across products (illustrative numerator, regulatory capital denominator; Product Profitability tab, FY2026 only) | H55: ='Product Profitability'!L21 -> 0.15934125
B57: LIQUIDITY
B58: Cash & Cash Equivalents / Total Assets % | C58: =IFERROR('Balance Sheet'!C9/'Balance Sheet'!C31,"") -> 0.027082952 | D58: =IFERROR('Balance Sheet'!D9/'Balance Sheet'!D31,"") -> 0.021572782 | E58: =IFERROR('Balance Sheet'!E9/'Balance Sheet'!E31,"") -> 0.025898544 | F58: =IFERROR('Balance Sheet'!F9/'Balance Sheet'!F31,"") -> 0.01059414 | G58: =IFERROR('Balance Sheet'!G9/'Balance Sheet'!G31,"") -> 0.00070368376 | H58: =IFERROR('Balance Sheet'!H9/'Balance Sheet'!H31,"") -> 0.0047451899 | I58: =IFERROR('Balance Sheet'!I9/'Balance Sheet'!I31,"") -> 0.027276231 | J58: =IFERROR('Balance Sheet'!J9/'Balance Sheet'!J31,"") -> 0.027302584 | ... M58: =IFERROR('Balance Sheet'!M9/'Balance Sheet'!M31,"") -> 0.027336169
B59: Cash & Cash Equivalents / Total Borrowings % | C59: =IFERROR('Balance Sheet'!C9/C49,"") -> 0.03429725 | D59: =IFERROR('Balance Sheet'!D9/D49,"") -> 0.035797852 | E59: =IFERROR('Balance Sheet'!E9/E49,"") -> 0.054082978 | F59: =IFERROR('Balance Sheet'!F9/F49,"") -> 0.016921605 | G59: =IFERROR('Balance Sheet'!G9/G49,"") -> 0.00095245271 | H59: =IFERROR('Balance Sheet'!H9/H49,"") -> 0.0059461561 | I59: =IFERROR('Balance Sheet'!I9/I49,"") -> 0.034662533 | J59: =IFERROR('Balance Sheet'!J9/J49,"") -> 0.03490629 | ... M59: =IFERROR('Balance Sheet'!M9/M49,"") -> 0.035133437
B61: PER SHARE METRICS
B62: Face Value per Share (₹) | C62: 2 | D62: =C62 -> 2 | E62: =D62 -> 2 | F62: =E62 -> 2 | G62: =F62 -> 2 | H62: =G62 -> 2 | I62: =Assumptions!D18 -> 2 | J62: =Assumptions!E18 -> 2 | K62: =Assumptions!F18 -> 2 | L62: =Assumptions!G18 -> 2 | M62: =Assumptions!H18 -> 2
B63: Shares Outstanding (Cr) (Equity Share Capital ÷ Face Value) | C63: =IFERROR('Balance Sheet'!C52/C62,"") -> 26.96165 | D63: =IFERROR('Balance Sheet'!D52/D62,"") -> 76.49235 | E63: =IFERROR('Balance Sheet'!E52/E62,"") -> 76.795 | F63: =IFERROR('Balance Sheet'!F52/F62,"") -> 77.055 | G63: =IFERROR('Balance Sheet'!G52/G62,"") -> 77.29 | H63: =IFERROR('Balance Sheet'!H52/H62,"") -> 80.795 | I63: =IFERROR('Balance Sheet'!I52/I62,"") -> 133.60662 | J63: =IFERROR('Balance Sheet'!J52/J62,"") -> 191.39079 | ... M63: =IFERROR('Balance Sheet'!M52/M62,"") -> 405.20372
B64: Basic EPS (₹, linked from Profit & Loss) | C64: ='Profit & Loss'!C55 -> -0.2074 | D64: ='Profit & Loss'!D55 -> 0.0523 | E64: ='Profit & Loss'!E55 -> 8.95 | F64: ='Profit & Loss'!F55 -> 21.89 | G64: ='Profit & Loss'!G55 -> -1.27 | H64: ='Profit & Loss'!H55 -> 6.84 | I64: ='Profit & Loss'!I55 -> 13.336712 | J64: ='Profit & Loss'!J55 -> 16.288687 | ... M64: ='Profit & Loss'!M55 -> 19.329018
B65: Diluted EPS (₹, linked from Profit & Loss) | C65: ='Profit & Loss'!C56 -> -0.2074 | D65: ='Profit & Loss'!D56 -> 0.0517 | E65: ='Profit & Loss'!E56 -> 8.86 | F65: ='Profit & Loss'!F56 -> 21.63 | G65: ='Profit & Loss'!G56 -> -1.27 | H65: ='Profit & Loss'!H56 -> 6.82 | I65: ='Profit & Loss'!I56 -> 13.336712 | J65: ='Profit & Loss'!J56 -> 16.288687 | ... M65: ='Profit & Loss'!M56 -> 19.329018
B66: Book Value per Share (₹) (Total Equity ÷ Shares Outstanding) | C66: =IFERROR('Balance Sheet'!C55/C63,"") -> 81.386132 | D66: =IFERROR('Balance Sheet'!D55/D63,"") -> 79.200344 | E66: =IFERROR('Balance Sheet'!E55/E63,"") -> 89.500228 | F66: =IFERROR('Balance Sheet'!F55/F63,"") -> 105.99027 | G66: =IFERROR('Balance Sheet'!G55/G63,"") -> 105.76608 | H66: =IFERROR('Balance Sheet'!H55/H63,"") -> 128.0802 | I66: =IFERROR('Balance Sheet'!I55/I63,"") -> 128.0802 | J66: =IFERROR('Balance Sheet'!J55/J63,"") -> 128.0802 | ... M66: =IFERROR('Balance Sheet'!M55/M63,"") -> 128.0802
B68: EFFICIENCY
B69: Employees (count, company-disclosed) | C69: 7600 | D69: 8024 | E69: 2452 | F69: 2384 | G69: 3594 | H69: 5860 | I69: ='Business Drivers'!D29 -> 7475 | J69: ='Business Drivers'!E29 -> 8736 | K69: ='Business Drivers'!F29 -> 9680 | L69: ='Business Drivers'!G29 -> 10476 | M69: ='Business Drivers'!H29 -> 11130
B70: Revenue per Employee (₹ Cr) (Total Income ÷ Employees) | C70: =IFERROR('Profit & Loss'!C15/C69,"") -> 0.30953651 | D70: =IFERROR('Profit & Loss'!D15/D69,"") -> 0.25436558 | E70: =IFERROR('Profit & Loss'!E15/E69,"") -> 0.81903752 | F70: =IFERROR('Profit & Loss'!F15/F69,"") -> 1.3201888 | G70: =IFERROR('Profit & Loss'!G15/G69,"") -> 1.1749694 | H70: =IFERROR('Profit & Loss'!H15/H69,"") -> 1.1596672 | I70: =IFERROR('Profit & Loss'!I15/I69,"") -> 1.5050714 | J70: =IFERROR('Profit & Loss'!J15/J69,"") -> 1.8262583 | ... M70: =IFERROR('Profit & Loss'!M15/M69,"") -> 2.9329478
B71: Profit per Branch (₹ Cr, illustrative — linked from Branch Profitability tab) | E71: ='Branch Profitability'!C11 -> 0.22169297 | F71: ='Branch Profitability'!D11 -> -0.099976531 | G71: ='Branch Profitability'!E11 -> -1.4986084 | H71: ='Branch Profitability'!F11 -> -0.90199263
B72: Average Ticket Size (₹ Lakh, illustrative assumption) | D72: 3.5 | E72: 3.8 | F72: 4 | I72: 4.2 | J72: 4.4 | K72: 4.6 | L72: 4.8 | M72: 5
B73: Est. Number of Loans Disbursed (Lakh, illustrative) = Disbursements ÷ Ticket Size | D73: =IFERROR(D12/D72,"") -> 2149.7143 | E73: =IFERROR(E12/E72,"") -> 4145 | F73: =IFERROR(F12/F72,"") -> 8322.25 | G73: =IFERROR(G12/G72,"") | H73: =IFERROR(H12/H72,"") | I73: =IFERROR(I12/I72,"") -> 11906.667 | J73: =IFERROR(J12/J72,"") -> 14992.045 | K73: =IFERROR(K12/K72,"") -> 18129.13 | ... M73: =IFERROR(M12/M72,"") -> 24666.4
B74: Cost per Loan (₹ Lakh, illustrative) = Opex ÷ Number of Loans | D74: =IFERROR(D28/D73,"") -> 0.3496513 | E74: =IFERROR(E28/E73,"") -> 0.19373945 | F74: =IFERROR(F28/F73,"") -> 0.097012226 | I74: =IFERROR(I28/I73,"") -> 0.23067192 | J74: =IFERROR(J28/J73,"") -> 0.22738427 | K74: =IFERROR(K28/K73,"") -> 0.22369883 | L74: =IFERROR(L28/L73,"") -> 0.22121415 | M74: =IFERROR(M28/M73,"") -> 0.21795188
B75: Branch Productivity – Avg. AUM per Branch (₹ Cr, illustrative — linked from Branch Profitability tab) | E75: ='Branch Profitability'!C7 -> 23.061429 | F75: ='Branch Profitability'!D7 -> 25.865172 | G75: ='Branch Profitability'!E7 -> 28.129737 | H75: ='Branch Profitability'!F7 -> 36.2088 | I75: =IFERROR('Balance Sheet'!I14/'Business Drivers'!D27,"") -> 130.47825 | J75: =IFERROR('Balance Sheet'!J14/'Business Drivers'!E27,"") -> 152.00446 | K75: =IFERROR('Balance Sheet'!K14/'Business Drivers'!F27,"") -> 178.17914 | L75: =IFERROR('Balance Sheet'!L14/'Business Drivers'!G27,"") -> 205.08095 | M75: =IFERROR('Balance Sheet'!M14/'Business Drivers'!H27,"") -> 234.29698
B76: Digital Adoption – DDP Contribution % of Disbursements (company-disclosed) | E76: 0.81 | F76: 0.82
B78: RISK DRIVER
B79: Fraud Loss (₹ Cr / %) — not disclosed by the Company in any of the FY2021-FY2026 Annual Reports; left blank rather than estimated
B80: Collection Efficiency % — not numerically disclosed by the Company (qualitative commentary only, e.g. “improved collection efficiency”, AR FY2024-26); left blank rather than estimated
B82: OTHER OPERATIONAL METRICS (migrated from KPI Dashboard (Forecast), now consolidated here)
B83: Branch Network (count) | C83: =IF('Business Performance Scorecard'!C165=0,"",'Business Performance Scorecard'!C165) | D83: =IF('Business Performance Scorecard'!D165=0,"",'Business Performance Scorecard'!D165) | E83: =IF('Business Performance Scorecard'!E165=0,"",'Business Performance Scorecard'!E165) | F83: =IF('Business Performance Scorecard'!F165=0,"",'Business Performance Scorecard'!F165) | G83: =IF('Business Performance Scorecard'!G165=0,"",'Business Performance Scorecard'!G165) | H83: ='Business Performance Scorecard'!H165 -> 500 | I83: ='Business Drivers'!D27 -> 650 | J83: ='Business Drivers'!E27 -> 780 | K83: ='Business Drivers'!F27 -> 880 | L83: ='Business Drivers'!G27 -> 970 | M83: ='Business Drivers'!H27 -> 1050
B84: Capital Raised / (Returned) During the Year (₹ Cr, forecast only — DERIVED from the Regulatory Capital requirement, not a balancing figure) | I84: ='Balance Sheet'!I60 -> 4982.2501 | J84: ='Balance Sheet'!J60 -> 4283.5034 | K84: ='Balance Sheet'!K60 -> 3753.1823 | L84: ='Balance Sheet'!L60 -> 3129.3891 | M84: ='Balance Sheet'!M60 -> 2215.9366
B86: MANAGEMENT GUIDANCE CROSS-CHECK (migrated from KPI Dashboard (Forecast), now consolidated here)
B87: Management ROA Guidance — Low End (Jun-2028 exit) | K87: 0.03
B88: Management ROA Guidance — High End (Jun-2028 exit) | K88: 0.035
B89: This Model — Base Case ROA (row 34, for reference) | K89: =K33 -> 0.029853932
B90: This Model — Upside Case ROA (captured by toggling Scenario Analysis!C5, FY2029E) | K90: 0.0348
B92: ADDITIONAL CONSOLIDATED METRICS (for Executive Dashboard linkage)
B93: Total Income (₹ Cr, Consolidated) | C93: ='Profit & Loss'!C15 -> 2352.4775 | D93: ='Profit & Loss'!D15 -> 2041.0294 | E93: ='Profit & Loss'!E15 -> 2008.28 | F93: ='Profit & Loss'!F15 -> 3147.33 | G93: ='Profit & Loss'!G15 -> 4222.84 | H93: ='Profit & Loss'!H15 -> 6795.65 | I93: ='Profit & Loss'!I15 -> 11250.409 | J93: ='Profit & Loss'!J15 -> 15954.192 | ... M93: ='Profit & Loss'!M15 -> 32643.709
B94: Shareholders' Funds / Total Equity (₹ Cr, Consolidated) | C94: ='Balance Sheet'!C55 -> 2194.3044 | D94: ='Balance Sheet'!D55 -> 6058.2204 | E94: ='Balance Sheet'!E55 -> 6873.17 | F94: ='Balance Sheet'!F55 -> 8167.08 | G94: ='Balance Sheet'!G55 -> 8174.66 | H94: ='Balance Sheet'!H55 -> 10348.24 | I94: ='Balance Sheet'!I55 -> 17112.363 | J94: ='Balance Sheet'!J55 -> 24513.371 | ... M94: ='Balance Sheet'!M55 -> 51898.575
B95: AUM / Loan Book (₹ Cr, Reported FY21-26A / Consolidated Forecast) | F95: ='Business Performance Scorecard'!F161 -> 25003 | G95: ='Business Performance Scorecard'!G161 -> 35631 | H95: ='Business Performance Scorecard'!H161 -> 60348 | I95: ='Balance Sheet'!I14 -> 84810.861 | J95: ='Balance Sheet'!J14 -> 118563.48 | K95: ='Balance Sheet'!K14 -> 156797.64 | L95: ='Balance Sheet'!L14 -> 198928.52 | M95: ='Balance Sheet'!M14 -> 246011.83

Sheet C - Planning & Forecasting
B2: C | C2: SECTION C — PLANNING & FORECASTING | F2: ⌂ Home
C4: The driver-based FY2027E–FY2031E forecast engine. No line here is a growth-percentage guess — every projection builds from an operating driver, with each assumption cited to a disclosed figure or explicitly marked illustrative.
B6: WHAT THIS SECTION COVERS
C7: • Revenue built as Average AUM × Yield, plus fee and other income
C8: • Funding: borrowings scaled to AUM at a leverage consistent with CRAR headroom, and the cost-of-funds glide path
C9: • Treasury and liquidity: borrowing mix and implied cost of funds cross-check
C10: • Credit cost: GNPA/NNPA/PCR glide path converting to a provisioning charge
C11: • Operating costs forecast by category on their own drivers, plus capex and depreciation roll-forward
B13: SHEETS IN THIS SECTION
B14: Ref | C14: Sheet | D14: What it does
B15: C1 | C15: Assumptions | D15: All macro and strategic forecast inputs, each with rationale and source — the single editable entry point for the forecast
B16: C2 | C16: Revenue Forecast | D16: Average AUM × Yield = Interest Income; fee and other income as % of AUM
B17: C3 | C17: Funding Forecast | D17: Borrowings, cost of funds and interest expense
B18: C4 | C18: Treasury | D18: Borrowing mix, cost of borrowing and liquidity position
B19: C5 | C19: Credit Cost Forecast | D19: GNPA, NNPA, PCR glide path and the resulting credit cost
B20: C6 | C20: Operating Cost Forecast | D20: Cost lines forecast by category on their own drivers, feeding the cost-to-income ratio
B21: C7 | C21: Regulatory Capital | D21: RWA → CRAR → capital requirement; shows the growth plan is capital-constrained and sizes the equity need
B22: C8 | C22: CapEx & Depreciation Schedule | D22: Net block roll-forward feeding D&A into the P&L, Cash Flow and Balance Sheet

Sheet Assumptions
B1: POONAWALLA FINCORP LIMITED — Forecast Assumptions (FY2027E–FY2031E) | L1: ⌂ Home
B2: Macro assumptions are calibrated to FY2026 disclosed actuals and RBI's medium-term policy targets (illustrative glide, not an official RBI/IMF forecast). Strategic assumptions (branch, productivity) are calibrated to the Company's own disclosed FY2026 network and headcount. All feed the Business Drivers sheet.
B4: Particulars | C4: FY2026A | D4: FY2027E | E4: FY2028E | F4: FY2029E | G4: FY2030E | H4: FY2031E | J4: Rationale / Source
B6: MACRO ASSUMPTIONS
B7: Real GDP Growth % | C7: 0.077 | D7: 0.07 | E7: 0.068 | F7: 0.067 | G7: 0.066 | H7: 0.065 | J7: FY2026A: "GDP growth improved to 7.7% in FY26 from 7.1% in FY25" (AR FY2026 pg.20). Forecast years: illustrative normalisation toward India's medium-term potential growth (~6.5%); not an official RBI/IMF projection.
B8: Inflation (CPI) % | C8: 0.018 | D8: 0.035 | E8: 0.04 | F8: 0.04 | G8: 0.04 | H8: 0.04 | J8: FY2026A: "Inflation cooled off to 1.8% during the year" (AR FY2026 pg.20). Forecast years: illustrative normalisation toward RBI's 4% medium-term CPI target (mid-point of the 2-6% band).
B9: RBI Repo Rate % (year-end) | C9: 0.0525 | D9: 0.0525 | E9: 0.055 | F9: 0.0575 | G9: 0.0575 | H9: 0.0575 | J9: FY2026A: "RBI reduced the repo rate by a cumulative 100 bps, bringing it down to 5.25% by December 31, 2025" (AR FY2026 pg.20). Forecast years: illustrative mild normalisation as inflation firms toward target; not an official RBI forecast.
B10: NBFC Industry AUM / Credit Growth % | D10: 0.175 | E10: 0.16 | F10: 0.15 | G10: 0.145 | H10: 0.14 | J10: "AUM of NBFCs are expected to grow steadily at 16-19% during FY26 and FY27... sector's AUM is projected to cross ₹30 Lakh Crore by March 2027" (AR FY2026 pg.20, source: CRISIL). FY28-31: illustrative taper toward a long-run industry average (~14%). Used as a cross-check on Company AUM growth, not a direct driver.
B12: STRATEGIC / OPERATING ASSUMPTIONS
B13: Net Branch Additions (count, p.a.) | D13: 150 | E13: 130 | F13: 100 | G13: 90 | H13: 80 | J13: Decelerating expansion pace as the network matures. FY2026A base: "500+ branches (incl. 400 gold loan branches)" (AR FY2026 pg.2). Gold Loan branch build-out was itself rapid in FY26 (+400); assumed to moderate as coverage scales.
B14: Employees per Branch (avg., productivity ratio) | C14: 11.72 | D14: 11.5 | E14: 11.2 | F14: 11 | G14: 10.8 | H14: 10.6 | J14: FY2026A actual: 5,860 employees ÷ 500 branches = 11.72 (AR FY2026 pg.4 and pg.2, KPIs & Ratios tab). Gradual improvement assumed as digital/AI-led underwriting and collections reduce headcount intensity per branch (AR FY2026 pg.24-26 on AI/automation initiatives).
B15: Wage Inflation % p.a. (cost per employee growth) | D15: 0.08 | E15: 0.08 | F15: 0.08 | G15: 0.075 | H15: 0.075 | J15: Illustrative assumption consistent with typical Indian BFSI wage inflation (~8%), moderating slightly as inflation normalises toward the RBI target (row 8).
B16: Effective Tax Rate % | C16: 0.2517 | D16: 0.2517 | E16: 0.2517 | F16: 0.2517 | G16: 0.2517 | H16: 0.2517 | J16: Standard Indian corporate tax rate under Section 115BAA (25.17% incl. surcharge & cess), applicable to most Indian companies opting for the lower tax regime.
B18: Face Value per Equity Share (₹) | C18: 2 | D18: =C18 -> 2 | E18: =D18 -> 2 | F18: =E18 -> 2 | G18: =F18 -> 2 | H18: =G18 -> 2 | J18: Source: Poonawalla Fincorp Annual Reports FY2023-FY2026, EPS note ("Face value of ₹2/- each"). Unchanged historically; held flat.

Sheet Revenue Forecast
B1: POONAWALLA FINCORP LIMITED — Revenue Forecast (Average AUM × Yield = Interest Income) | L1: ⌂ Home
B2: Average AUM is linked from Business Drivers (derived from the Customer/Disbursement chain). Interest Income = Average AUM × Gross Yield. Fee and Other Income are forecast as a % of AUM.
B4: Particulars | C4: FY2026A | D4: FY2027E | E4: FY2028E | F4: FY2029E | G4: FY2030E | H4: FY2031E | J4: Rationale / Source
B6: Average AUM (₹ Cr, linked from Business Drivers) | D6: ='Business Drivers'!D18+('Business Drivers'!D21-'Business Drivers'!D18)/2 -> 71163.979 | E6: ='Business Drivers'!E18+('Business Drivers'!E21-'Business Drivers'!E18)/2 -> 104243.09 | F6: ='Business Drivers'!F18+('Business Drivers'!F21-'Business Drivers'!F18)/2 -> 142437.51 | G6: ='Business Drivers'!G18+('Business Drivers'!G21-'Business Drivers'!G18)/2 -> 185313.25 | H6: ='Business Drivers'!H18+('Business Drivers'!H21-'Business Drivers'!H18)/2 -> 233151.49
B7: Gross Yield on AUM % (Base + Scenario Adjustment) | D7: =0.145+'Scenario Analysis'!$C$17 -> 0.145 | E7: =0.14+'Scenario Analysis'!$C$17 -> 0.14 | F7: =0.135+'Scenario Analysis'!$C$17 -> 0.135 | G7: =0.13+'Scenario Analysis'!$C$17 -> 0.13 | H7: =0.127+'Scenario Analysis'!$C$17 -> 0.127 | J7: FY2026A consolidated Yield on Advances was ~13.9% (KPIs & Ratios tab). Gradual compression assumed as management continues shifting mix toward secured products (secured mix 49%→57%→54% across FY24-26, AR FY2024 pg.20, FY2025 pg.24, FY2026 pg.35/58); Gold Loan/LAP carry lower yields than unsecured Personal Loans.
B8: Interest Income (₹ Cr) | C8: ='Profit & Loss'!H8 -> 6140.81 | D8: =D6*D7 -> 10318.777 | E8: =E6*E7 -> 14594.032 | F8: =F6*F7 -> 19229.063 | G8: =G6*G7 -> 24090.723 | H8: =H6*H7 -> 29610.239
B9: Fee & Commission Income, % of AUM | D9: 0.0075 | E9: 0.0075 | F9: 0.008 | G9: 0.008 | H9: 0.0085 | J9: FY2026A actual: Fee & Commission Income ₹419.75 Cr ÷ AUM ₹55,951 Cr = 0.75% (Profit & Loss / Balance Sheet tabs). Modest improvement assumed with growing new-product cross-sell.
B10: Fee & Commission Income (₹ Cr) | C10: ='Profit & Loss'!H10 -> 419.75 | D10: =D6*D9 -> 533.72984 | E10: =E6*E9 -> 781.82315 | F10: =F6*F9 -> 1139.5 | G10: =G6*G9 -> 1482.506 | H10: =H6*H9 -> 1981.7877
B11: Other Income, % of AUM | D11: 0.0055 | E11: 0.0055 | F11: 0.0045 | G11: 0.0045 | H11: 0.0045 | J11: FY2026A actual: (Other Income + Rental Income + Net gains) ÷ AUM ≈ 0.6% (Profit & Loss tab). Held broadly flat.
B12: Other Income (₹ Cr) | C12: =C13-C8-C10 -> 235.09 | D12: =D6*D11 -> 391.40189 | E12: =E6*E11 -> 573.33698 | F12: =F6*F11 -> 640.96878 | G12: =G6*G11 -> 833.90964 | H12: =H6*H11 -> 1049.1817
B13: Total Income (₹ Cr) | C13: ='Profit & Loss'!H15 -> 6795.65 | D13: =D8+D10+D12 -> 11243.909 | E13: =E8+E10+E12 -> 15949.192 | F13: =F8+F10+F12 -> 21009.532 | G13: =G8+G10+G12 -> 26407.139 | H13: =H8+H10+H12 -> 32641.209

Sheet Funding Forecast
B1: POONAWALLA FINCORP LIMITED — Funding Forecast (Borrowings, Cost of Funds, Interest Expense) | L1: ⌂ Home
B2: Borrowings are NO LONGER an independent ratio. Total borrowings are now the residual funding requirement from the Balance Sheet — total assets less RWA-driven equity less non-debt liabilities. Regulatory capital therefore determines leverage: the borrowings/AUM ratio below is a computed OUTPUT, not an assumption.
B4: Particulars | C4: FY2026A | D4: FY2027E | E4: FY2028E | F4: FY2029E | G4: FY2030E | H4: FY2031E | J4: Rationale / Source
B6: AUM / Loan Book (₹ Cr, linked from Business Drivers) | C6: ='Business Drivers'!C21 -> 55951.49 | D6: ='Business Drivers'!D21 -> 86376.468 | E6: ='Business Drivers'!E21 -> 122109.7 | F6: ='Business Drivers'!F21 -> 162765.31 | G6: ='Business Drivers'!G21 -> 207861.2 | H6: ='Business Drivers'!H21 -> 258441.78
B7: Borrowings as % of AUM (OUTPUT — result of capital structure) | C7: 0.86 | D7: =IFERROR(D8/D6,"") -> 0.84980051 | E7: =IFERROR(E8/E6,"") -> 0.83448458 | F7: =IFERROR(F8/F6,"") -> 0.82509786 | G7: =IFERROR(G8/G6,"") -> 0.81804308 | H7: =IFERROR(H8/H6,"") -> 0.81281909 | J7: ="OUTPUT, not an assumption. FY2026A actual: Total Borrowings ÷ AUM = "&TEXT(C8,"#,##0")&" ÷ "&TEXT(C6,"#,##0")&" = "&TEXT(C7,"0.0%")&" (Treasury tab). "&"Forecast years are COMPUTED, not held flat: total borrowings are the residual funding requirement from the Balance Sheet - total assets less RWA-driven equity less non-debt liabilities - "&"so the ratio DECLINES to "&TEXT(H7,"0.0%")&" by FY2031E as equity is sized to the "&TEXT('Regulatory Capital'!$C$39,"0%")&" target CRAR. An earlier version of this model held the ratio flat as an input; it no longer does." -> OUTPUT, not an assumption. FY2026A actual: Total Borrowings ÷ AUM = 48,118 ÷ 55,951 = 86.0% (Treasury tab). Forecast years are COMPUTED, not held flat: total borrowings are the residual funding requirement from the Balance Sheet - total assets less RWA-driven equity less non-debt liabilities - so the ratio DECLINES to 81.3% by FY2031E as equity is sized to the 18% target CRAR. An earlier version of this model held the ratio flat as an input; it no longer does.
B8: Total Borrowings (₹ Cr, residual from Balance Sheet) | C8: =C6*C7 -> 48118.281 | D8: ='Balance Sheet'!I39+'Balance Sheet'!I40+'Balance Sheet'!I41 -> 73402.767 | E8: ='Balance Sheet'!J39+'Balance Sheet'!J40+'Balance Sheet'!J41 -> 101898.67 | F8: ='Balance Sheet'!K39+'Balance Sheet'!K40+'Balance Sheet'!K41 -> 134297.31 | G8: ='Balance Sheet'!L39+'Balance Sheet'!L40+'Balance Sheet'!L41 -> 170039.42 | H8: ='Balance Sheet'!M39+'Balance Sheet'!M40+'Balance Sheet'!M41 -> 210066.41
B9: Average Borrowings (₹ Cr) | D9: =AVERAGE(C8:D8) -> 60760.524 | E9: =AVERAGE(D8:E8) -> 87650.716 | F9: =AVERAGE(E8:F8) -> 118097.99 | G9: =AVERAGE(F8:G8) -> 152168.36 | H9: =AVERAGE(G8:H8) -> 190052.91
B10: Cost of Funds % (Base + Scenario Adjustment) | C10: 0.0773 | D10: =0.075+'Scenario Analysis'!$C$18 -> 0.075 | E10: =0.073+'Scenario Analysis'!$C$18 -> 0.073 | F10: =0.072+'Scenario Analysis'!$C$18 -> 0.072 | G10: =0.071+'Scenario Analysis'!$C$18 -> 0.071 | H10: =0.07+'Scenario Analysis'!$C$18 -> 0.07 | J10: Continues the disclosed downtrend (Cost of Borrowing: FY24 8.06% → FY25 8.09% → FY26 7.73%, AR FY2026 pg.19), aided by the RBI's cumulative 100bps repo rate cut in FY26 (linked to Assumptions row 9) and rising NCD diversification (AR FY2025 pg.22-23). Floors near 7.0%, in line with the Company's AAA/Stable rating (CRISIL, CARE).
B11: Interest Expense / Finance Costs (₹ Cr) | C11: ='Profit & Loss'!H17 -> 2766.67 | D11: =D9*D10 -> 4557.0393 | E11: =E9*E10 -> 6398.5023 | F11: =F9*F10 -> 8503.0551 | G11: =G9*G10 -> 10803.954 | H11: =H9*H10 -> 13303.704
B12: (Memo) Debt-to-Equity (x) — vs RWA-driven equity | D12: =IFERROR(D8/'Balance Sheet'!I55,"") -> 4.2894582 | E12: =IFERROR(E8/'Balance Sheet'!J55,"") -> 4.1568606 | F12: =IFERROR(F8/'Balance Sheet'!K55,"") -> 4.0967437 | G12: =IFERROR(G8/'Balance Sheet'!L55,"") -> 4.0630249 | H12: =IFERROR(H8/'Balance Sheet'!M55,"") -> 4.0476336
B13: (Memo) FY2026A Total Equity, Consolidated (₹ Cr) | C13: ='Balance Sheet'!H55 -> 10348.24
B15: MEMO — which AUM is the denominator in row 7?
B16: ="Row 7 divides borrowings by GROSS AUM (Business Drivers row 21, ₹"&TEXT(H6,"#,##0")&" Cr at FY2031E), the market convention for a funding ratio. The Balance Sheet carries Loans NET of expected credit loss (₹"&TEXT('Balance Sheet'!M14,"#,##0")&" Cr). "&"The ₹"&TEXT(H6-'Balance Sheet'!M14,"#,##0")&" Cr difference is cumulative forecast credit cost, not a reconciling error - both series start from the same ₹"&TEXT(C6,"#,##0")&" Cr FY2026A on-book base. "&"On the net-of-ECL denominator the same borrowings equal "&TEXT(H8/'Balance Sheet'!M14,"0.0%")&". Row 7 is the figure quoted everywhere else in the workbook - do not mix the two." -> Row 7 divides borrowings by GROSS AUM (Business Drivers row 21, ₹2,58,442 Cr at FY2031E), the market convention for a funding ratio. The Balance Sheet carries Loans NET of expected credit loss (₹2,46,012 Cr). The ₹12,430 Cr difference is cumulative forecast credit cost, not a reconciling error - both series start from the same ₹55,951 Cr FY2026A on-book base. On the net-of-ECL denominator the same borrowings equal 85.4%. Row 7 is the figure quoted everywhere else in the workbook - do not mix the two.

Sheet Treasury
B1: POONAWALLA FINCORP LIMITED — Treasury & Borrowing Mix (Consolidated) | J1: ⌂ Home
B2: Borrowing-mix figures are formula-linked to the Balance Sheet sheet in this workbook (₹ Crore). Cost of Borrowing % is a disclosed standalone figure (see notes); Implied Cost of Funds is computed as a cross-check.
B4: Particulars | C4: FY2021 | D4: FY2022 | E4: FY2023 | F4: FY2024 | G4: FY2025 | H4: FY2026
B6: Debt securities (₹ Cr) | C6: ='Balance Sheet'!C39 -> 1265.0223 | D6: ='Balance Sheet'!D39 -> 939.9589 | E6: ='Balance Sheet'!E39 -> 950.24 | F6: ='Balance Sheet'!F39 -> 1227.09 | G6: ='Balance Sheet'!G39 -> 1663.99 | H6: ='Balance Sheet'!H39 -> 14790.18
B7: Borrowings other than debt securities (₹ Cr) | C7: ='Balance Sheet'!C40 -> 8334.5873 | D7: ='Balance Sheet'!D40 -> 8380.4803 | E7: ='Balance Sheet'!E40 -> 9804.07 | F7: ='Balance Sheet'!F40 -> 13616.13 | G7: ='Balance Sheet'!G40 -> 23978.97 | H7: ='Balance Sheet'!H40 -> 32933.13
B8: Subordinated liabilities (₹ Cr) | C8: ='Balance Sheet'!C41 -> 833.4397 | D8: ='Balance Sheet'!D41 -> 588.3901 | E8: ='Balance Sheet'!E41 -> 365.27 | F8: ='Balance Sheet'!F41 -> 236.91 | G8: ='Balance Sheet'!G41 -> 237.59 | H8: ='Balance Sheet'!H41 -> 374.99
B9: Total Borrowings (₹ Cr) | C9: =SUM(C6:C8) -> 10433.049 | D9: =SUM(D6:D8) -> 9908.8293 | E9: =SUM(E6:E8) -> 11119.58 | F9: =SUM(F6:F8) -> 15080.13 | G9: =SUM(G6:G8) -> 25880.55 | H9: =SUM(H6:H8) -> 48098.3
B11: BORROWING MIX (% of Total)
B12: Debt securities % | C12: =IFERROR(C6/C$9,"") -> 0.12125144 | D12: =IFERROR(D6/D$9,"") -> 0.094860742 | E12: =IFERROR(E6/E$9,"") -> 0.085456465 | F12: =IFERROR(F6/F$9,"") -> 0.081371314 | G12: =IFERROR(G6/G$9,"") -> 0.064295001 | H12: =IFERROR(H6/H$9,"") -> 0.30749902
B13: Borrowings (other than debt securities) % | C13: =IFERROR(C7/C$9,"") -> 0.79886398 | D13: =IFERROR(D7/D$9,"") -> 0.84575887 | E13: =IFERROR(E7/E$9,"") -> 0.88169427 | F13: =IFERROR(F7/F$9,"") -> 0.90291861 | G13: =IFERROR(G7/G$9,"") -> 0.92652475 | H13: =IFERROR(H7/H$9,"") -> 0.68470466
B14: Subordinated liabilities % | C14: =IFERROR(C8/C$9,"") -> 0.079884574 | D14: =IFERROR(D8/D$9,"") -> 0.059380385 | E14: =IFERROR(E8/E$9,"") -> 0.032849262 | F14: =IFERROR(F8/F$9,"") -> 0.015710077 | G14: =IFERROR(G8/G$9,"") -> 0.0091802531 | H14: =IFERROR(H8/H$9,"") -> 0.0077963254
B16: COST OF FUNDS
B17: Finance costs, Consolidated (₹ Cr) | C17: ='Profit & Loss'!C17 -> 1100.454 | D17: ='Profit & Loss'!D17 -> 716.1697 | E17: ='Profit & Loss'!E17 -> 595.28 | F17: ='Profit & Loss'!F17 -> 950.3 | G17: ='Profit & Loss'!G17 -> 1515.09 | H17: ='Profit & Loss'!H17 -> 2766.67
B18: Average Total Borrowings (₹ Cr) | D18: =AVERAGE(C9:D9) -> 10170.939 | E18: =AVERAGE(D9:E9) -> 10514.205 | F18: =AVERAGE(E9:F9) -> 13099.855 | G18: =AVERAGE(F9:G9) -> 20480.34 | H18: =AVERAGE(G9:H9) -> 36989.425
B19: Implied Cost of Funds % (Finance costs ÷ Avg. borrowings) | D19: =IFERROR(D17/D18*100,"") -> 7.0413329 | E19: =IFERROR(E17/E18*100,"") -> 5.6616741 | F19: =IFERROR(F17/F18*100,"") -> 7.2542788 | G19: =IFERROR(G17/G18*100,"") -> 7.3977776 | H19: =IFERROR(H17/H18*100,"") -> 7.4796242
B20: Cost of Borrowing % (as disclosed, standalone) | F20: 8.06 | G20: 8.09 | H20: 7.73

Sheet Credit Cost Forecast
B1: POONAWALLA FINCORP LIMITED — Credit Cost Forecast (GNPA, NNPA, PCR, Credit Cost) | L1: ⌂ Home
B2: Asset-quality ratios are forecast directly (glide path); Credit Cost (₹) is derived from Average AUM × Credit Cost %, and flows into the P&L Forecast.
B4: Particulars | C4: FY2026A | D4: FY2027E | E4: FY2028E | F4: FY2029E | G4: FY2030E | H4: FY2031E | J4: Rationale / Source
B6: Gross NPA % | C6: 0.0144 | D6: 0.0135 | E6: 0.013 | F6: 0.0125 | G6: 0.012 | H6: 0.0115 | J6: FY2026A: 1.44% (AR FY2026 pg.19/35, KPIs & Ratios tab). Gradual improvement assumed as underwriting matures and secured mix rises (54% in FY26, AR pg.35/58), consistent with the disclosed trend (3.29% FY22 → 1.44% FY23 → 1.16% FY24).
B7: Net NPA % | C7: 0.0074 | D7: 0.0068 | E7: 0.0063 | F7: 0.006 | G7: 0.0057 | H7: 0.0055 | J7: FY2026A: 0.74% (AR FY2026 pg.19/35, KPIs & Ratios tab). Moves consistently with the GNPA glide above.
B8: Provision Coverage Ratio % (= 1 − NNPA ÷ GNPA) | C8: =IFERROR(1-C7/C6,"") -> 0.48611111 | D8: =IFERROR(1-D7/D6,"") -> 0.4962963 | E8: =IFERROR(1-E7/E6,"") -> 0.51538462 | F8: =IFERROR(1-F7/F6,"") -> 0.52 | G8: =IFERROR(1-G7/G6,"") -> 0.525 | H8: =IFERROR(1-H7/H6,"") -> 0.52173913 | J8: Derived. FY2025A disclosed PCR was 54.47% (AR FY2025 pg.34), broadly consistent with the level implied here.
B9: Average AUM (₹ Cr, linked from Revenue Forecast) | D9: ='Revenue Forecast'!D6 -> 71163.979 | E9: ='Revenue Forecast'!E6 -> 104243.09 | F9: ='Revenue Forecast'!F6 -> 142437.51 | G9: ='Revenue Forecast'!G6 -> 185313.25 | H9: ='Revenue Forecast'!H6 -> 233151.49
B10: Credit Cost, % of Avg. AUM (Base + Scenario Adjustment) | D10: =0.022+'Scenario Analysis'!$C$19 -> 0.022 | E10: =0.019+'Scenario Analysis'!$C$19 -> 0.019 | F10: =0.017+'Scenario Analysis'!$C$19 -> 0.017 | G10: =0.016+'Scenario Analysis'!$C$19 -> 0.016 | H10: =0.015+'Scenario Analysis'!$C$19 -> 0.015 | J10: FY2026A consolidated credit cost was ~2.5% (KPIs & Ratios tab), still elevated from the FY2025 STPL book recalibration. Assumed to normalise in line with the GNPA/NNPA improvement above, converging toward a typical diversified-NBFC long-run level.
B12: Credit Cost / Provisions (₹ Cr) | C12: ='Profit & Loss'!H20 -> 1104.13 | D12: =D9*D10 -> 1565.6075 | E12: =E9*E10 -> 1980.6186 | F12: =F9*F10 -> 2421.4376 | G12: =G9*G10 -> 2965.0121 | H12: =H9*H10 -> 3497.2724
B15: KNOWN LIMITATION — this is a credit-cost FORECAST, not an expected-loss engine
B16: Credit cost normalisation is the single largest driver of the PAT and ROE recovery in this model (Scenario Analysis row 30 shows a c.6-point FY2031E ROE swing on this line alone), so the reader is entitled to know exactly what stands behind it. What stands behind it: disclosed GNPA, NNPA, PCR and credit cost by year, plus a management-guided improvement glide path. What does NOT stand behind it: Stage 1 / Stage 2 / Stage 3 ECL staging, PD, LGD and EAD by product, vintage loss curves, 30+/60+/90+ DPD migration and roll-rates, cure rates, and write-off versus recovery splits. None of that is publicly disclosed at product level.
B17: Consequence to state plainly: the Collections Analytics tab is a monitoring FRAMEWORK, not a calibrated expected-loss model. Until internal bureau and DPD-bucket data is loaded, the credit-cost path is a management-guided trajectory with a scenario range around it — not a modelled loss outcome. This is the largest single concentration of forecast risk in the workbook, and the Downside scenario exists precisely to size it (Scenario Analysis rows 45-56 show the capital consequence if it does not normalise).
B19: WHY 1.5% AS THE TERMINAL CREDIT COST — the defensible answer
B20: It is NOT independently proven by this model, and it should not be claimed as such. Public disclosure does not contain the cohort-level inputs (PD, LGD, EAD, DPD migration, vintage loss curves) needed to derive a terminal loss rate bottom-up. WHAT SUPPORTS 1.5%: (a) the Company's own disclosed trajectory — GNPA 3.29% FY22 → 1.44% FY26 and NNPA 0.74% FY26, with management attributing the improvement to underwriting-model and collections changes (AR FY26 pg.19/35); (b) a 54% secured mix at FY26 rising toward management's 50:50 target, which structurally lowers loss-given-default; (c) FY2026A's ~2.5% is itself inflated by the FY2025 short-term personal loan recalibration, so the starting point is not a steady state. WHAT DOES NOT SUPPORT IT: any bottom-up loss model. It is a forecast assumption that is stressed, not a derived result.
B21: HOW TO FALSIFY IT: if Stage 2 balances, 30+ DPD flow rates or the FY2027-28 vintage loss curves do not improve in line with the GNPA glide in row 6, the terminal assumption is wrong and the Downside becomes the planning case — which the Scenario Analysis tab prices at c.6 points of FY2031E ROE and c.₹2,700 Cr of additional external equity. Loading internal DPD-bucket and bureau data should be the first production upgrade to this model.

Sheet Operating Cost Forecast
B1: POONAWALLA FINCORP LIMITED — Operating Cost Forecast (by Category) | L1: ⌂ Home
B2: Each cost category is forecast on its own driver, not as one lump Opex line. FY2026A Employee Cost is the Company's actual disclosed figure; the FY2026A split of the remaining costs (Branch/Technology/Marketing/Collections/Other) into sub-categories is an ILLUSTRATIVE allocation of the disclosed “Other expenses” and D&A lines, since the Company does not disclose this breakdown.
B4: Particulars | C4: FY2026A | D4: FY2027E | E4: FY2028E | F4: FY2029E | G4: FY2030E | H4: FY2031E | J4: Rationale / Source
B6: 1. EMPLOYEE COST (driven by Headcount)
B7: Employees (count, linked from Business Drivers) | C7: ='Business Drivers'!C29 -> 5860 | D7: ='Business Drivers'!D29 -> 7475 | E7: ='Business Drivers'!E29 -> 8736 | F7: ='Business Drivers'!F29 -> 9680 | G7: ='Business Drivers'!G29 -> 10476 | H7: ='Business Drivers'!H29 -> 11130
B8: Cost per Employee (₹ Lakh p.a.) | C8: ='Profit & Loss'!H21/C7*100 -> 17.364164 | D8: =C8*(1+Assumptions!D15) -> 18.753297 | E8: =D8*(1+Assumptions!E15) -> 20.253561 | F8: =E8*(1+Assumptions!F15) -> 21.873846 | G8: =F8*(1+Assumptions!G15) -> 23.514384 | H8: =G8*(1+Assumptions!H15) -> 25.277963 | J8: FY2026A: Employee Benefits Expense ₹1,017.54 Cr (Profit & Loss tab) ÷ 5,860 employees (AR FY2026 pg.4) = ₹17.36 Lakh/employee. Grown by the Wage Inflation assumption (Assumptions tab, row 15).
B9: Employee Cost (₹ Cr) | C9: ='Profit & Loss'!H21 -> 1017.54 | D9: =D7*D8/100 -> 1401.8089 | E9: =E7*E8/100 -> 1769.3511 | F9: =F7*F8/100 -> 2117.3882 | G9: =G7*G8/100 -> 2463.3669 | H9: =H7*H8/100 -> 2813.4373
B11: 2. BRANCH COST (driven by Branch Count)
B12: Branch Count (linked from Business Drivers) | C12: ='Business Drivers'!C27 -> 500 | D12: ='Business Drivers'!D27 -> 650 | E12: ='Business Drivers'!E27 -> 780 | F12: ='Business Drivers'!F27 -> 880 | G12: ='Business Drivers'!G27 -> 970 | H12: ='Business Drivers'!H27 -> 1050
B13: Cost per Branch (₹ Lakh p.a., illustrative) | C13: 68.86 | D13: 6 | E13: 6 | F13: 6 | G13: 5 | H13: 5 | J13: D13:H13 hold the % growth in cost-per-branch (not the level); see row 14 for the compounded ₹ Lakh figure. Illustrative rent/utility/local-staff inflation ~5-6% p.a.
B14: Cost per Branch, compounded (₹ Lakh p.a.) | D14: =C13*(1+D13/100) -> 72.9916 | E14: =D14*(1+E13/100) -> 77.371096 | F14: =E14*(1+F13/100) -> 82.013362 | G14: =F14*(1+G13/100) -> 86.11403 | H14: =G14*(1+H13/100) -> 90.419731
B15: Branch Cost (₹ Cr) | C15: 344.32 | D15: =D12*D14/100 -> 474.4454 | E15: =E12*E14/100 -> 603.49455 | F15: =F12*F14/100 -> 721.71758 | G15: =G12*G14/100 -> 835.30609 | H15: =H12*H14/100 -> 949.40718
B17: 3. TECHNOLOGY (driven by digital investment growth)
B18: Technology Spend Growth % p.a. | D18: 0.15 | E18: 0.13 | F18: 0.12 | G18: 0.1 | H18: 0.1 | J18: Reflects continued AI/ML and automation investment ("76 AI solutions, 42 delivered, 34 underway", AR FY2026 pg.2), tapering as the core platform build-out matures.
B19: Technology Cost (₹ Cr) | C19: 245.94 | D19: =C19*(1+D18) -> 282.831 | E19: =D19*(1+E18) -> 319.59903 | F19: =E19*(1+F18) -> 357.95091 | G19: =F19*(1+G18) -> 393.746 | H19: =G19*(1+H18) -> 433.12061
B21: 4. MARKETING (driven by disbursement / customer-acquisition growth)
B22: Total Disbursement Growth % (linked from Business Drivers) | E22: =IFERROR('Business Drivers'!E14/'Business Drivers'!D14-1,"") -> 0.31908895 | F22: =IFERROR('Business Drivers'!F14/'Business Drivers'!E14-1,"") -> 0.26421587 | G22: =IFERROR('Business Drivers'!G14/'Business Drivers'!F14-1,"") -> 0.22387402 | H22: =IFERROR('Business Drivers'!H14/'Business Drivers'!G14-1,"") -> 0.20838202
B23: Marketing Cost (₹ Cr) | C23: 196.75 | D23: =C23*1.32 -> 259.71 | E23: =D23*(1+E22) -> 342.58059 | F23: =E23*(1+F22) -> 433.09582 | G23: =F23*(1+G22) -> 530.05472 | H23: =G23*(1+H22) -> 640.50859 | J23: Scales with the pace of new disbursements (customer-acquisition cost driver). FY2027E growth of 32% approximates disbursement growth given FY2026A total disbursement is not separately disclosed (Business Drivers tab derives it bottom-up from FY2027E onward).
B25: 5. COLLECTIONS (driven by AUM growth — effort scales with book size)
B26: AUM Growth % (linked from Business Drivers) | D26: ='Business Drivers'!D22 -> 0.54377423 | E26: ='Business Drivers'!E22 -> 0.41369179 | F26: ='Business Drivers'!F22 -> 0.33294326 | G26: ='Business Drivers'!G22 -> 0.27706084 | H26: ='Business Drivers'!H22 -> 0.24333825
B27: Collections Cost (₹ Cr) | C27: 118.05 | D27: =C27*(1+D26*0.6) -> 156.56553 | E27: =D27*(1+E26*0.6) -> 195.42745 | F27: =E27*(1+F26*0.6) -> 234.46721 | G27: =F27*(1+G26*0.6) -> 273.44421 | H27: =G27*(1+H26*0.6) -> 313.36787 | J27: Grows at 60% of the AUM growth rate — collections infrastructure scales with book size but with productivity gains from AI-led collections ("GenAI-enabled co-pilots, intelligent voice bots", AR FY2026 pg.26), so cost intensity per unit of AUM declines over time.
B29: 6. OTHER OPERATING EXPENSES (inflation-linked)
B30: Inflation % (linked from Assumptions) | D30: =Assumptions!D8 -> 0.035 | E30: =Assumptions!E8 -> 0.04 | F30: =Assumptions!F8 -> 0.04 | G30: =Assumptions!G8 -> 0.04 | H30: =Assumptions!H8 -> 0.04
B31: Other Operating Expenses (₹ Cr) | C31: 78.7 | D31: =C31*(1+D30) -> 81.4545 | E31: =D31*(1+E30) -> 84.71268 | F31: =E31*(1+F30) -> 88.101187 | G31: =F31*(1+G30) -> 91.625235 | H31: =G31*(1+H30) -> 95.290244
B33: TOTAL OPERATING EXPENSES excl. D&A (₹ Cr) — D&A is forecast separately on the CapEx & Depreciation Schedule tab | C33: =C9+C15+C19+C23+C27+C31 -> 2001.3 | D33: =D9+D15+D19+D23+D27+D31 -> 2656.8154 | E33: =E9+E15+E19+E23+E27+E31 -> 3315.1654 | F33: =F9+F15+F19+F23+F27+F31 -> 3952.721 | G33: =G9+G15+G19+G23+G27+G31 -> 4587.5431 | H33: =H9+H15+H19+H23+H27+H31 -> 5245.1318
B34: (Check) FY2026A Total Opex excl. D&A, i.e. Employee + Other Expenses only (₹ Cr) | C34: ='Profit & Loss'!H21+'Profit & Loss'!H23 -> 2001.31
B36: OPEX GROWTH BY CATEGORY, FY2026A → FY2027E — drives the cost recommendation in Management Recommendations
B37: Category | C37: FY2026A (₹ Cr) | D37: FY2027E (₹ Cr) | E37: Growth %
B38: Employee Cost | C38: =C9 -> 1017.54 | D38: =D9 -> 1401.8089 | E38: =IFERROR(D38/C38-1,"") -> 0.37764505
B39: Branch Cost | C39: =C15 -> 344.32 | D39: =D15 -> 474.4454 | E39: =IFERROR(D39/C39-1,"") -> 0.37791996
B40: Technology | C40: =C19 -> 245.94 | D40: =D19 -> 282.831 | E40: =IFERROR(D40/C40-1,"") -> 0.15
B41: Marketing | C41: =C23 -> 196.75 | D41: =D23 -> 259.71 | E41: =IFERROR(D41/C41-1,"") -> 0.32
B42: Collections | C42: =C27 -> 118.05 | D42: =D27 -> 156.56553 | E42: =IFERROR(D42/C42-1,"") -> 0.32626454
B43: Other Operating Expenses | C43: =C31 -> 78.7 | D43: =D31 -> 81.4545 | E43: =IFERROR(D43/C43-1,"") -> 0.035
B45: Fastest-growing category, FY2027E | C45: =INDEX($B$38:$B$43,MATCH(MAX($E$38:$E$43),$E$38:$E$43,0)) -> Branch Cost | E45: =MAX($E$38:$E$43) -> 0.37791996
B46: Second fastest | C46: =INDEX($B$38:$B$43,MATCH(LARGE($E$38:$E$43,2),$E$38:$E$43,0)) -> Employee Cost | E46: =LARGE($E$38:$E$43,2) -> 0.37764505
B47: Slowest-growing category | C47: =INDEX($B$38:$B$43,MATCH(MIN($E$38:$E$43),$E$38:$E$43,0)) -> Other Operating Expenses | E47: =MIN($E$38:$E$43) -> 0.035
B49: COST-TO-INCOME BRIDGE, FY2026A → FY2031E — where the improvement actually comes from
B50: Cost-to-Income, FY2026A | C50: =('Profit & Loss'!H21+'Profit & Loss'!H22+'Profit & Loss'!H23)/('Profit & Loss'!H15-'Profit & Loss'!H17) -> 0.52009442
B51: Effect of INCOME SCALE alone — FY2026A opex held at FY2026A level against FY2031E net income (pp) | C51: =-(C50-('Profit & Loss'!H21+'Profit & Loss'!H22+'Profit & Loss'!H23)/('Profit & Loss'!M15-'Profit & Loss'!M17)) -> -0.41174646
B52: Effect of OPEX GROWTH — cost base rising with the network and headcount (pp) | C52: =(('Profit & Loss'!M21+'Profit & Loss'!M22+'Profit & Loss'!M23)-('Profit & Loss'!H21+'Profit & Loss'!H22+'Profit & Loss'!H23))/('Profit & Loss'!M15-'Profit & Loss'!M17) -> 0.16962965
B53: = Cost-to-Income, FY2031E | C53: =C50+C51+C52 -> 0.2779776
B54: Check vs Profit & Loss (must be zero) | C54: =C53-('Profit & Loss'!M21+'Profit & Loss'!M22+'Profit & Loss'!M23)/('Profit & Loss'!M15-'Profit & Loss'!M17) -> 0
B56: ="READ IT THIS WAY: none of the "&TEXT((C50-C53)*100,"0.0")&"-point improvement comes from cutting costs. Income scale delivers "&TEXT(-C51*100,"0.0")&" points; opex growth gives back "&TEXT(C52*100,"0.0")&" points as the branch network and headcount build out. "&"Opex itself rises from ₹"&TEXT('Profit & Loss'!H21+'Profit & Loss'!H22+'Profit & Loss'!H23,"#,##0")&" Cr to ₹"&TEXT('Profit & Loss'!M21+'Profit & Loss'!M22+'Profit & Loss'!M23,"#,##0")&" Cr - about "&TEXT(('Profit & Loss'!M21+'Profit & Loss'!M22+'Profit & Loss'!M23)/('Profit & Loss'!H21+'Profit & Loss'!H22+'Profit & Loss'!H23),"0.0")&"x. "&"So the efficiency claim is entirely a claim about the AUM path: if AUM undershoots, cost-to-income does NOT improve as modelled, because the cost base is committed ahead of the income. That is the honest version of the "&TEXT(C50,"0.0%")&" to "&TEXT(C53,"0.0%")&" story." -> READ IT THIS WAY: none of the 24.2-point improvement comes from cutting costs. Income scale delivers 41.2 points; opex growth gives back 17.0 points as the branch network and headcount build out. Opex itself rises from ₹2,095 Cr to ₹5,376 Cr - about 2.6x. So the efficiency claim is entirely a claim about the AUM path: if AUM undershoots, cost-to-income does NOT improve as modelled, because the cost base is committed ahead of the income. That is the honest version of the 52.0% to 27.8% story.

Sheet Regulatory Capital
B1: POONAWALLA FINCORP — REGULATORY CAPITAL: RWA → CRAR → CAPITAL REQUIREMENT | L1: ⌂ Home
B2: Replaces the Equity/Assets CRAR proxy with a risk-weighted build. Product AUM is Company-disclosed (AR FY26 pg.116-119); risk weights are RBI standardised norms (blue, cited per row). Capital is derived from the Balance Sheet. Capital requirement then CONSTRAINS the AUM forecast rather than being a balancing figure.
B3: ⚠ SCOPE: this is a STRATEGIC RWA APPROXIMATION for FP&A planning, built from public disclosure — it is NOT Poonawalla's regulatory capital computation. The model produces 15.03% CRAR at FY2026A against the DISCLOSED 16.83% (row 34). The gap is expected and explained: Tier 1 uses total equity without the regulatory deductions (goodwill, intangibles, DTA above threshold, investments in subsidiaries), an operational-risk charge is added that RBI does not mandate for NBFCs, product risk weights are standardised norms rather than the Company's actual asset-class mapping, and the build is consolidated while the disclosure is standalone. Use it to size the DIRECTION and MAGNITUDE of the capital requirement, not to reproduce a regulatory filing.
B4: 1. CREDIT RWA BUILD — FY2026A (by disclosed product)
B5: Product | C5: AUM (₹ Cr) | D5: Risk Weight % | E5: RWA (₹ Cr) | F5: Risk-weight basis
B6: ='Portfolio Mix'!B5 -> Loan Against Property (LAP) | C6: ='Portfolio Mix'!C5 -> 16935 | D6: 0.75 | E6: =C6*D6 -> 12701.25 | F6: Secured by property — 75% (RBI standardised, LAP/mortgage-backed)
B7: ='Portfolio Mix'!B6 -> Instant Consumer Loan | C7: ='Portfolio Mix'!C6 -> 11197 | D7: 1.25 | E7: =C7*D7 -> 13996.25 | F7: Unsecured consumer credit — 125% (RBI circular Nov-2023 raised NBFC consumer credit RW to 125%)
B8: ='Portfolio Mix'!B7 -> Pre-Owned Car Finance (POC) | C8: ='Portfolio Mix'!C7 -> 9245 | D8: 1 | E8: =C8*D8 -> 9245 | F8: Vehicle finance — 100% (excluded from the 125% consumer-credit uplift)
B9: ='Portfolio Mix'!B8 -> Business Loan | C9: ='Portfolio Mix'!C8 -> 7303 | D9: 0.75 | E9: =C9*D9 -> 5477.25 | F9: MSME / regulatory retail — 75%
B10: ='Portfolio Mix'!B9 -> Prime Personal Loan | C10: ='Portfolio Mix'!C9 -> 4802 | D10: 1.25 | E10: =C10*D10 -> 6002.5 | F10: Unsecured personal loan — 125% (RBI Nov-2023)
B11: ='Portfolio Mix'!B10 -> Gold Loan | C11: ='Portfolio Mix'!C10 -> 1299 | D11: 1 | E11: =C11*D11 -> 1299 | F11: Gold loan — 100% (secured by gold, no consumer-credit uplift)
B12: ='Portfolio Mix'!B11 -> Commercial Vehicle Loan | C12: ='Portfolio Mix'!C11 -> 939 | D12: 1 | E12: =C12*D12 -> 939 | F12: Commercial vehicle — 100%
B13: ='Portfolio Mix'!B12 -> Education Loan | C13: ='Portfolio Mix'!C12 -> 876 | D13: 1 | E13: =C13*D13 -> 876 | F13: Education loan — 100% (excluded from consumer-credit uplift)
B14: ='Portfolio Mix'!B13 -> Machinery & Medical Equipment Loan | C14: ='Portfolio Mix'!C13 -> 783 | D14: 1 | E14: =C14*D14 -> 783 | F14: Equipment finance — 100%
B15: ='Portfolio Mix'!B14 -> Professional Loan | C15: ='Portfolio Mix'!C14 -> 787 | D15: 1.25 | E15: =C15*D15 -> 983.75 | F15: Unsecured professional loan — 125%
B16: ='Portfolio Mix'!B15 -> Consumer Durable Loan | C16: ='Portfolio Mix'!C15 -> 382 | D16: 1.25 | E16: =C16*D16 -> 477.5 | F16: Unsecured consumer durable — 125%
B17: ='Portfolio Mix'!B16 -> Other / Legacy Portfolio (reconciling) | C17: ='Portfolio Mix'!C16 -> 5799 | D17: 1 | E17: =C17*D17 -> 5799 | F17: Other / legacy — 100% (blended)
B18: TOTAL CREDIT RWA | C18: =SUM(C6:C17) -> 60347 | D18: =IFERROR(E18/C18,"") -> 0.97071105 | E18: =SUM(E6:E17) -> 58579.5 | F18: ← Blended risk weight, used to risk-weight the forecast AUM below
B20: 2. RWA, CAPITAL & CRAR — ACTUAL AND FORECAST
B21: Particulars | C21: FY2026A | D21: FY2027E | E21: FY2028E | F21: FY2029E | G21: FY2030E | H21: FY2031E
B22: AUM / Loan Book (₹ Cr) | C22: ='KPIs & Ratios'!H95 -> 60348 | D22: ='KPIs & Ratios'!I95 -> 84810.861 | E22: ='KPIs & Ratios'!J95 -> 118563.48 | F22: ='KPIs & Ratios'!K95 -> 156797.64 | G22: ='KPIs & Ratios'!L95 -> 198928.52 | H22: ='KPIs & Ratios'!M95 -> 246011.83
B23: Blended risk weight % (FY26 product mix held constant) | C23: =$D$18 -> 0.97071105 | D23: =$D$18 -> 0.97071105 | E23: =$D$18 -> 0.97071105 | F23: =$D$18 -> 0.97071105 | G23: =$D$18 -> 0.97071105 | H23: =$D$18 -> 0.97071105
B24: Credit RWA (₹ Cr) | C24: =C22*C23 -> 58580.471 | D24: =D22*D23 -> 82326.84 | E24: =E22*E23 -> 115090.88 | F24: =F22*F23 -> 152205.21 | G24: =G22*G23 -> 193102.12 | H24: =H22*H23 -> 238806.4
B25: Operational risk RWA (₹ Cr, 15% of PRIOR-year gross income × 12.5) | C25: ='Profit & Loss'!H15*0.15*12.5 -> 12741.844 | D25: ='Profit & Loss'!H15*0.15*12.5 -> 12741.844 | E25: ='Profit & Loss'!I15*0.15*12.5 -> 21094.516 | F25: ='Profit & Loss'!J15*0.15*12.5 -> 29914.11 | G25: ='Profit & Loss'!K15*0.15*12.5 -> 39400.373 | H25: ='Profit & Loss'!L15*0.15*12.5 -> 49519.01
B26: TOTAL RWA (₹ Cr) | C26: =C24+C25 -> 71322.314 | D26: =D24+D25 -> 95068.684 | E26: =E24+E25 -> 136185.4 | F26: =F24+F25 -> 182119.32 | G26: =G24+G25 -> 232502.49 | H26: =H24+H25 -> 288325.41
B28: Tier 1 capital (₹ Cr) = Total equity less intangibles/DTA | C28: ='Balance Sheet'!H55 -> 10348.24 | D28: ='Balance Sheet'!I55 -> 17112.363 | E28: ='Balance Sheet'!J55 -> 24513.371 | F28: ='Balance Sheet'!K55 -> 32781.477 | G28: ='Balance Sheet'!L55 -> 41850.448 | H28: ='Balance Sheet'!M55 -> 51898.575
B29: Tier 2 capital (₹ Cr) = subordinated liabilities, capped at 100% of Tier 1 | C29: =MIN('Balance Sheet'!H41,C28) -> 374.99 | D29: =MIN('Balance Sheet'!I41,D28) -> 572.27186 | E29: =MIN('Balance Sheet'!J41,E28) -> 794.43516 | F29: =MIN('Balance Sheet'!K41,F28) -> 1047.0255 | G29: =MIN('Balance Sheet'!L41,G28) -> 1325.6826 | H29: =MIN('Balance Sheet'!M41,H28) -> 1637.7461
B30: TOTAL CAPITAL FUNDS (₹ Cr) | C30: =C28+C29 -> 10723.23 | D30: =D28+D29 -> 17684.635 | E30: =E28+E29 -> 25307.806 | F30: =F28+F29 -> 33828.503 | G30: =G28+G29 -> 43176.131 | H30: =H28+H29 -> 53536.321
B32: CRAR % (Total capital ÷ Total RWA) | C32: =IFERROR(C30/C26,"") -> 0.15034888 | D32: =IFERROR(D30/D26,"") -> 0.18601956 | E32: =IFERROR(E30/E26,"") -> 0.18583348 | F32: =IFERROR(F30/F26,"") -> 0.18574912 | G32: =IFERROR(G30/G26,"") -> 0.1857018 | H32: =IFERROR(H30/H26,"") -> 0.1856802
B33: Tier 1 % (Tier 1 ÷ Total RWA) | C33: =IFERROR(C28/C26,"") -> 0.1450912 | D33: =IFERROR(D28/D26,"") -> 0.18 | E33: =IFERROR(E28/E26,"") -> 0.18 | F33: =IFERROR(F28/F26,"") -> 0.18 | G33: =IFERROR(G28/G26,"") -> 0.18 | H33: =IFERROR(H28/H26,"") -> 0.18
B34: Memo: FY26A disclosed CRAR (standalone) for cross-check | C34: ='KPIs & Ratios'!H53 -> 16.83
B36: 3. CAPITAL REQUIREMENT & EQUITY GAP — does the growth plan fund itself?
B37: Regulatory minimum CRAR % (NBFC-Upper Layer) | C37: 0.15
B38: Management buffer % (above regulatory minimum) | C38: 0.03 | D38: ="WHY 3%? Anchored to the Company's own disclosed CRAR history: "&TEXT('KPIs & Ratios'!F53,"0.0")&"% (FY24), "&TEXT('KPIs & Ratios'!G53,"0.0")&"% (FY25), "&TEXT('KPIs & Ratios'!H53,"0.0")&"% (FY26), plus 20.74% simulated post-QIP on the March 2026 balance sheet (AR FY26 KPI page). "&"An 18% target therefore sits BELOW every level the Company has actually operated at, while 300bps above the NBFC-UL floor gives roughly one Downside year of loss absorption without breaching. "&"It is still a POLICY choice, not a regulation: the sensitivity at rows 108-110 prices it at about ₹"&TEXT($H$26*0.01,"#,##0")&" Cr of equity per percentage point." -> WHY 3%? Anchored to the Company's own disclosed CRAR history: 33.8% (FY24), 22.9% (FY25), 16.8% (FY26), plus 20.74% simulated post-QIP on the March 2026 balance sheet (AR FY26 KPI page). An 18% target therefore sits BELOW every level the Company has actually operated at, while 300bps above the NBFC-UL floor gives roughly one Downside year of loss absorption without breaching. It is still a POLICY choice, not a regulation: the sensitivity at rows 108-110 prices it at about ₹2,883 Cr of equity per percentage point.
B39: Target CRAR % (minimum + buffer) | C39: =C37+C38 -> 0.18
B41: Required capital at target CRAR (₹ Cr) | C41: =C26*$C$39 -> 12838.017 | D41: =D26*$C$39 -> 17112.363 | E41: =E26*$C$39 -> 24513.371 | F41: =F26*$C$39 -> 32781.477 | G41: =G26*$C$39 -> 41850.448 | H41: =H26*$C$39 -> 51898.575
B42: Available capital funds (₹ Cr) | C42: =C30 -> 10723.23 | D42: =D30 -> 17684.635 | E42: =E30 -> 25307.806 | F42: =F30 -> 33828.503 | G42: =G30 -> 43176.131 | H42: =H30 -> 53536.321
B43: Surplus / (Shortfall) vs target — on TOTAL capital funds, Tier 1 + Tier 2 (₹ Cr) | C43: =C42-C41 -> -2114.7866 | D43: =D42-D41 -> 572.27186 | E43: =E42-E41 -> 794.43516 | F43: =F42-F41 -> 1047.0255 | G43: =G42-G41 -> 1325.6826 | H43: =H42-H41 -> 1637.7461
B44: Status vs target CRAR | C44: =IF(C32>=$C$39,"ABOVE TARGET",IF(C32>=$C$37,"BELOW BUFFER","BREACH")) -> BELOW BUFFER | D44: =IF(D32>=$C$39,"ABOVE TARGET",IF(D32>=$C$37,"BELOW BUFFER","BREACH")) -> ABOVE TARGET | E44: =IF(E32>=$C$39,"ABOVE TARGET",IF(E32>=$C$37,"BELOW BUFFER","BREACH")) -> ABOVE TARGET | F44: =IF(F32>=$C$39,"ABOVE TARGET",IF(F32>=$C$37,"BELOW BUFFER","BREACH")) -> ABOVE TARGET | G44: =IF(G32>=$C$39,"ABOVE TARGET",IF(G32>=$C$37,"BELOW BUFFER","BREACH")) -> ABOVE TARGET | H44: =IF(H32>=$C$39,"ABOVE TARGET",IF(H32>=$C$37,"BELOW BUFFER","BREACH")) -> ABOVE TARGET
B46: Internal capital generation — PAT retained (₹ Cr, 0% payout assumed) | D46: ='KPIs & Ratios'!I35 -> 1781.8731 | E46: ='KPIs & Ratios'!J35 -> 3117.5046 | F46: ='KPIs & Ratios'!K35 -> 4514.9236 | G46: ='KPIs & Ratios'!L35 -> 5939.5821 | H46: ='KPIs & Ratios'!M35 -> 7832.1898
B47: Incremental capital needed in year (₹ Cr) | D47: =D41-C41 -> 4274.3465 | E47: =E41-D41 -> 7401.0081 | F47: =F41-E41 -> 8268.1059 | G47: =G41-F41 -> 9068.9712 | H47: =H41-G41 -> 10048.126
B48: EXTERNAL EQUITY REQUIRED in year (₹ Cr) | D48: =MAX(D47-D46,0) -> 2492.4735 | E48: =MAX(E47-E46,0) -> 4283.5034 | F48: =MAX(F47-F46,0) -> 3753.1823 | G48: =MAX(G47-G46,0) -> 3129.3891 | H48: =MAX(H47-H46,0) -> 2215.9366
B49: Cumulative external equity required FY27E-31E (₹ Cr) | C49: =SUM(D48:H48) -> 15874.485
B51: 4. CAPITAL-CONSTRAINED GROWTH CEILING — regulatory capital only. Funding availability, ALM, liquidity, origination capacity, collections infrastructure, risk appetite and concentration limits are NOT modelled here.
B52: Capital-constrained supportable AUM at target CRAR, on that year's internally-generated capital only (₹ Cr) | D52: =((C30+D46)/$C$39-D25)/D23 -> 58442.675 | E52: =((D30+E46)/$C$39-E25)/E23 -> 97323.426 | F52: =((E30+F46)/$C$39-F25)/F23 -> 139864.2 | G52: =((F30+G46)/$C$39-G25)/G23 -> 187010.78 | H52: =((G30+H46)/$C$39-H25)/H23 -> 240916.75
B53: Forecast AUM (₹ Cr) | D53: =D22 -> 84810.861 | E53: =E22 -> 118563.48 | F53: =F22 -> 156797.64 | G53: =G22 -> 198928.52 | H53: =H22 -> 246011.83
B54: AUM gap — forecast above internally-fundable ceiling (₹ Cr) | D54: =D53-D52 -> 26368.186 | E54: =E53-E52 -> 21240.052 | F54: =F53-F52 -> 16933.447 | G54: =G53-G52 -> 11917.745 | H54: =H53-H52 -> 5095.0849
B55: Verdict (capital constraint only) | C55: =IF(SUM(D54:H54)>0,"CAPITAL-CONSTRAINED: the forecast AUM path cannot be funded from retained earnings alone. ₹"&TEXT(C49,"#,##0")&" Cr of external equity is required across FY27E-31E to hold the "&TEXT($C$39,"0%")&" target CRAR.","Self-funding: retained earnings support the forecast AUM path at target CRAR.") -> CAPITAL-CONSTRAINED: the forecast AUM path cannot be funded from retained earnings alone. ₹15,874 Cr of external equity is required across FY27E-31E to hold the 18% target CRAR.
B57: 5. CAPITAL BRIDGE — regulatory requirement to Balance Sheet raise (must reconcile to zero)
B58: Incremental regulatory requirement FY27E-31E, net of retained earnings (₹ Cr) | C58: =SUM(D48:H48) -> 15874.485
B59: (+) FY2026A opening capital shortfall vs target CRAR — one-off catch-up, on Tier 1 / equity (₹ Cr) | C59: =C41-C28 -> 2489.7766
B60: = TOTAL external capital required FY27E-31E (₹ Cr) | C60: =C58+C59 -> 18364.261
B61: External capital raise per Balance Sheet, FY27E-31E (₹ Cr) | C61: =SUM('Balance Sheet'!I60:M60) -> 18364.261
B62: BRIDGE CHECK (must be zero) | C62: =C60-C61 -> 0 | D62: =IF(ABS(C62)<0.01,"✓ RECONCILED","⚠ DOES NOT RECONCILE") -> ✓ RECONCILED
B63: 6. KEY MANAGEMENT MESSAGES
B64: ="1. CRAR on a risk-weighted basis is "&TEXT(C32,"0.0%")&" at FY26A (actual) and "&TEXT(D32,"0.0%")&" to "&TEXT(H32,"0.0%")&" across the forecast — the forecast now holds the "&TEXT(C39,"0%")&" target because equity is sized to the requirement. FY26A itself sits below that buffer." -> 1. CRAR on a risk-weighted basis is 15.0% at FY26A (actual) and 18.6% to 18.6% across the forecast — the forecast now holds the 18% target because equity is sized to the requirement. FY26A itself sits below that buffer.
B65: ="2. Funding it needs ₹"&TEXT(SUM(D48:H48),"#,##0")&" Cr of external equity over FY27E-31E on an incremental basis, or ₹"&TEXT(SUM('Balance Sheet'!I60:M60),"#,##0")&" Cr including the FY27E catch-up from today's actual capital base. Retained earnings contribute ₹"&TEXT(SUM(D46:H46),"#,##0")&" Cr." -> 2. Funding it needs ₹15,874 Cr of external equity over FY27E-31E on an incremental basis, or ₹18,364 Cr including the FY27E catch-up from today's actual capital base. Retained earnings contribute ₹23,186 Cr.
B66: ="3. Capital, not origination capacity, is the binding constraint. On a single-year basis retained earnings fall ₹"&TEXT(H54,"#,##0")&" Cr short of funding the FY31E book. On a cumulative five-year equity freeze the shortfall is far larger: ₹"&TEXT(C81,"#,##0")&" Cr of AUM, or "&TEXT(1-C82,"0.0%")&" of the plan (section 7)." -> 3. Capital, not origination capacity, is the binding constraint. On a single-year basis retained earnings fall ₹5,095 Cr short of funding the FY31E book. On a cumulative five-year equity freeze the shortfall is far larger: ₹1,02,956 Cr of AUM, or 41.8% of the plan (section 7).
B67: ="4. Relief lever: shifting mix toward secured lending (management's 50:50 target) lowers the blended risk weight from "&TEXT(D18,"0.0%")&", cutting RWA and capital need without reducing AUM growth." -> 4. Relief lever: shifting mix toward secured lending (management's 50:50 target) lowers the blended risk weight from 97.1%, cutting RWA and capital need without reducing AUM growth.
B68: ARCHITECTURE NOTE
B69: ="Chain runs: Product AUM → RBI risk weights → RWA (+ operational risk) → target CRAR → required capital → Balance Sheet equity → less retained earnings → external equity raise. Balance Sheet equity (row 55) reads from row 41 of this sheet. "&"NO CIRCULARITY: RWA derives from loans and PRIOR-year income only. "&"BALANCING ITEM IS BORROWINGS, NOT CASH: total borrowings are the residual funding requirement (assets less equity less non-debt liabilities), allocated across instruments at the FY2026A mix - which is why borrowings/AUM falls from "&TEXT('Funding Forecast'!C7,"0.0%")&" to "&TEXT('Funding Forecast'!H7,"0.0%")&" as equity is sized to target. "&"Cash is DRIVEN by a liquidity ratio (Balance Sheet row 63, "&TEXT('Balance Sheet'!C63,"0.0%")&" of AUM), not used to absorb the difference. The Balance Sheet still ties to zero in every period." -> Chain runs: Product AUM → RBI risk weights → RWA (+ operational risk) → target CRAR → required capital → Balance Sheet equity → less retained earnings → external equity raise. Balance Sheet equity (row 55) reads from row 41 of this sheet. NO CIRCULARITY: RWA derives from loans and PRIOR-year income only. BALANCING ITEM IS BORROWINGS, NOT CASH: total borrowings are the residual funding requirement (assets less equity less non-debt liabilities), allocated across instruments at the FY2026A mix - which is why borrowings/AUM falls from 86.0% to 81.3% as equity is sized to target. Cash is DRIVEN by a liquidity ratio (Balance Sheet row 63, 3.0% of AUM), not used to absorb the difference. The Balance Sheet still ties to zero in every period.
B71: 7. BOARD CONSTRAINT TEST — what if no external equity is permitted for five years?
B72: Cumulative test: capital compounds from the FY2026A base through retained earnings only. No issuance in any year.
B73: FY2026A total capital funds (₹ Cr) | C73: =C30 -> 10723.23
B74: (+) Cumulative retained earnings FY2027E-FY2031E, 0% payout (₹ Cr) | C74: =SUM(D46:H46) -> 23186.073
B75: = Capital funds available at FY2031E with ZERO issuance (₹ Cr) | C75: =C73+C74 -> 33909.303
B76: Implied total RWA ceiling at target CRAR (₹ Cr) | C76: =C75/$C$39 -> 188385.02
B77: (-) Operational risk RWA, FY2031E (₹ Cr) | C77: =H25 -> 49519.01
B78: = Credit RWA available for lending (₹ Cr) | C78: =C76-C77 -> 138866.01
B79: Implied FY2031E AUM ceiling at the FY2026A blended risk weight (₹ Cr) | C79: =C78/H23 -> 143055.97
B80: Forecast FY2031E AUM (₹ Cr) | C80: =H22 -> 246011.83
B81: AUM that cannot be written without equity (₹ Cr) | C81: =C80-C79 -> 102955.87
B82: AUM ceiling as % of the forecast plan | C82: =C79/C80 -> 0.58150035
B83: Illustrative FY2031E PAT if unit margins hold on the smaller book (₹ Cr) | C83: ='Profit & Loss'!M38*C82 -> 4554.4211
B84: FY2031E PAT foregone vs the plan (₹ Cr) | C84: ='Profit & Loss'!M38-C83 -> 3277.7687
B85: Verdict | C85: ="An equity freeze caps FY2031E AUM at about ₹"&TEXT(C79,"#,##0")&" Cr - "&TEXT(C82,"0.0%")&" of the ₹"&TEXT(C80,"#,##0")&" Cr plan - and costs roughly ₹"&TEXT(C84,"#,##0")&" Cr of FY2031E PAT. "&"The constraint is absorbed by GROWTH, not by the capital ratio: PAT and required capital both scale with the book, so return per unit of capital is broadly unchanged. "&"The board's real trade-off is franchise scale versus dilution, not profitability versus dilution. Under a freeze the levers are: tilt the mix to secured to lower the blended risk weight, or slow disbursement onto the fundable path." -> An equity freeze caps FY2031E AUM at about ₹1,43,056 Cr - 58.2% of the ₹2,46,012 Cr plan - and costs roughly ₹3,278 Cr of FY2031E PAT. The constraint is absorbed by GROWTH, not by the capital ratio: PAT and required capital both scale with the book, so return per unit of capital is broadly unchanged. The board's real trade-off is franchise scale versus dilution, not profitability versus dilution. Under a freeze the levers are: tilt the mix to secured to lower the blended risk weight, or slow disbursement onto the fundable path.
B86: UPPER BOUND, not the expected case: this applies the forecast retained earnings, which were earned on the larger book. On a book c.42% smaller, PAT — and therefore internal capital formation — would be lower, compressing the ceiling further. It also holds the FY2026A blended risk weight constant and assumes 0% dividend payout throughout. Read it as the best case under an equity freeze.
B88: 8. CAPITAL-RAISE FEASIBILITY — is the requirement actually raisable, and at what dilution?
B89: Largest equity raise executed to date — QIP completed FY2026 (₹ Cr, DISCLOSED) | C89: 2500
B90: Average annual issuance implied by the plan, FY2027E-FY2031E (₹ Cr) | C90: =C60/5 -> 3672.8523
B91: Implied multiple of the largest raise achieved to date (x) | C91: =C90/C89 -> 1.4691409
B92: What this does and does not tell you | C92: ="The requirement averages ₹"&TEXT(C90,"#,##0")&" Cr a year for five consecutive years - "&TEXT(C91,"0.00")&"x the largest raise the Company has actually executed (the ₹"&TEXT(C89,"#,##0")&" Cr FY2026 QIP). "&"That is demanding but not implausible for an NBFC-UL with this growth profile; it does, however, assume an open capital-market window in every one of those five years. "&"NOT MODELLED HERE: QIP timing and pricing, promoter dilution, book-value and EPS dilution per tranche, maximum feasible issuance in a single window, or the growth-throttling response if a window closes. "&"Until those are tested, ₹"&TEXT(C60,"#,##0")&" Cr is the capital REQUIREMENT the growth plan generates - it is not a funding plan, and the model does not claim capital is available on demand." -> The requirement averages ₹3,673 Cr a year for five consecutive years - 1.47x the largest raise the Company has actually executed (the ₹2,500 Cr FY2026 QIP). That is demanding but not implausible for an NBFC-UL with this growth profile; it does, however, assume an open capital-market window in every one of those five years. NOT MODELLED HERE: QIP timing and pricing, promoter dilution, book-value and EPS dilution per tranche, maximum feasible issuance in a single window, or the growth-throttling response if a window closes. Until those are tested, ₹18,364 Cr is the capital REQUIREMENT the growth plan generates - it is not a funding plan, and the model does not claim capital is available on demand.
B94: 9. WHY ₹18,364 Cr — DECOMPOSITION. What the number is made of, and which part is a choice
B95: The calculations above answer "how much". This answers "why that much". Three drivers sum to the total capital build; retained earnings then fund part of it.
B96: Required capital at FY2031E, at target CRAR (₹ Cr) | C96: =H41 -> 51898.575
B97: (−) FY2026A Tier 1 capital already in place (₹ Cr) | C97: =-C28 -> -10348.24
B98: = TOTAL capital to be built, FY2027E-FY2031E (₹ Cr) | C98: =C96+C97 -> 41550.335
B99: Attribution of that build — what is actually driving it:
B100: (a) Growth in CREDIT RWA, at the FY2026A blended risk weight (₹ Cr) | C100: =(H24-C24)*$C$39 -> 32440.668
B101: (b) Growth in OPERATIONAL RISK RWA (₹ Cr) | C101: =(H25-C25)*$C$39 -> 6619.8899
B102: (c) Holding the target CRAR rather than FY2026A's actual level — the catch-up (₹ Cr) | C102: =C41-C28 -> 2489.7766
B103: Check: (a) + (b) + (c) less total capital to be built (must be zero) | C103: =C100+C101+C102-C98 -> 0
B104: (−) Funded from retained earnings, 0% payout (₹ Cr) | C104: =-SUM(D46:H46) -> -23186.073
B105: = EXTERNAL EQUITY REQUIRED (₹ Cr) | C105: =C98+C104 -> 18364.261
B106: Check vs the section 5 bridge (must be zero) | C106: =C105-C60 -> 0
B108: Sensitivity — external equity required at different target CRAR (base case shaded)
B109: Target CRAR | C109: =$C$39-0.02 -> 0.16 | D109: =$C$39-0.01 -> 0.17 | E109: =$C$39 -> 0.18 | F109: =$C$39+0.01 -> 0.19 | G109: =$C$39+0.02 -> 0.2
B110: External equity required FY2027E-FY2031E (₹ Cr) | C110: =MAX($H$26*C109-$C$28+$C$104,0) -> 12597.753 | D110: =MAX($H$26*D109-$C$28+$C$104,0) -> 15481.007 | E110: =MAX($H$26*E109-$C$28+$C$104,0) -> 18364.261 | F110: =MAX($H$26*F109-$C$28+$C$104,0) -> 21247.516 | G110: =MAX($H$26*G109-$C$28+$C$104,0) -> 24130.77
B111: ="Each 1 percentage point of target CRAR is worth about ₹"&TEXT($H$26*0.01,"#,##0")&" Cr of external equity. The "&TEXT(C38,"0%")&" management buffer above the "&TEXT(C37,"0%")&" regulatory minimum therefore accounts for ₹"&TEXT($H$26*C38,"#,##0")&" Cr of the ₹"&TEXT(C60,"#,##0")&" Cr "&"- it is the single largest DISCRETIONARY item in the capital plan. At the bare regulatory minimum the requirement falls to ₹"&TEXT(MAX($H$26*C37-$C$28+$C$104,0),"#,##0")&" Cr." -> Each 1 percentage point of target CRAR is worth about ₹2,883 Cr of external equity. The 3% management buffer above the 15% regulatory minimum therefore accounts for ₹8,650 Cr of the ₹18,364 Cr - it is the single largest DISCRETIONARY item in the capital plan. At the bare regulatory minimum the requirement falls to ₹9,714 Cr.
B112: ="So the honest answer to ""why ₹18,364 Cr and not ₹15,000 Cr?"" is that ₹15,000 Cr corresponds to a "&TEXT((15000+$C$28-$C$104)/$H$26,"0.0%")&" target CRAR. "&"The difference is a buffer POLICY choice of roughly "&TEXT($C$39-(15000+$C$28-$C$104)/$H$26,"0.0%")&", not a disagreement about growth or credit. Growth explains "&TEXT(C100/C98,"0%")&" of the capital build, operational risk "&TEXT(C101/C98,"0%")&", and the opening catch-up "&TEXT(C102/C98,"0%")&"." -> So the honest answer to "why ₹18,364 Cr and not ₹15,000 Cr?" is that ₹15,000 Cr corresponds to a 16.8% target CRAR. The difference is a buffer POLICY choice of roughly 1.2%, not a disagreement about growth or credit. Growth explains 78% of the capital build, operational risk 16%, and the opening catch-up 6%.

Sheet CapEx & Depreciation Schedule
B1: POONAWALLA FINCORP LIMITED — CapEx & Depreciation Schedule | L1: ⌂ Home
B2: Depreciation & Amortisation was previously embedded (unforecast) inside the Operating Cost Forecast's aggregate categories. This schedule properly rolls forward the Net Fixed & Intangible Asset block and feeds D&A into the Profit & Loss (row 22), the Cash Flow Statement (non-cash add-back row 9 and CapEx row 42), and the Balance Sheet's PP&E line (row 22).
B4: Particulars | C4: FY2026A | D4: FY2027E | E4: FY2028E | F4: FY2029E | G4: FY2030E | H4: FY2031E | J4: Rationale / Source
B6: Opening Net Block — PP&E + ROU Assets + Intangibles (₹ Cr) | D6: =C11 -> 427.23 | E6: =D11 -> 457.5117 | F6: =E11 -> 513.7218 | G6: =F11 -> 580.97744 | H6: =G11 -> 654.78195
B7: CapEx — Additions to PP&E / Intangibles (₹ Cr, illustrative) | D7: 120 | E7: 150 | F7: 170 | G7: 190 | H7: 210 | J7: Illustrative, scaled to branch network (Business Drivers tab) and technology investment growth (Operating Cost Forecast tab); the Company does not separately disclose a capex forecast. Consistent with the Cash Flow Statement's investing outflow (row 42).
B8: Depreciation Rate, % of Opening Net Block | C8: 0.2203 | D8: 0.21 | E8: 0.205 | F8: 0.2 | G8: 0.2 | H8: 0.2 | J8: FY2026A actual: D&A of ₹94.14 Cr (Profit & Loss tab) ÷ Opening Net Block of ₹427.53 Cr (PP&E ₹55.01 + ROU Assets ₹172.31 + Other Intangibles ₹16.41 + Intangible under development ₹10.43, all FY2025A closing, Balance Sheet tab) = 22.03%. Held broadly flat, consistent with a blended PP&E/ROU/intangible life of ~4.5-5 years.
B9: Depreciation, Amortisation & Impairment (₹ Cr) | C9: ='Profit & Loss'!H22 -> 94.14 | D9: =D6*D8 -> 89.7183 | E9: =E6*E8 -> 93.789898 | F9: =F6*F8 -> 102.74436 | G9: =G6*G8 -> 116.19549 | H9: =H6*H8 -> 130.95639
B11: Closing Net Block (₹ Cr) | C11: ='Balance Sheet'!H22+'Balance Sheet'!H26+'Balance Sheet'!H23+'Balance Sheet'!H25 -> 427.23 | D11: =D6+D7-D9 -> 457.5117 | E11: =E6+E7-E9 -> 513.7218 | F11: =F6+F7-F9 -> 580.97744 | G11: =G6+G7-G9 -> 654.78195 | H11: =H6+H7-H9 -> 733.82556

Sheet D - Performance & Risk
B2: D | C2: SECTION D — PERFORMANCE & RISK MANAGEMENT | F2: ⌂ Home
C4: Where capital is deployed and how the book is performing. This section answers the capital-allocation question: which products, branches and channels deserve more investment, and where is risk building?
B6: WHAT THIS SECTION COVERS
C7: • Product mix by disclosed AUM, with growth, yield, risk and a derived Expand / Grow / Maintain / Review decision
C8: • Product-level and branch-level profitability lenses
C9: • The collections funnel: bucket roll rates, recovery and write-off (framework illustrative; disclosed asset-quality metrics linked)
C10: • Digital transformation KPIs and their flow-through to cost efficiency
C11: • Enterprise risk cockpit with formula-driven RAG status, and the live scenario toggle
B13: SHEETS IN THIS SECTION
B14: Ref | C14: Sheet | D14: What it does
B15: D1 | C15: Portfolio Mix | D15: 12 products with disclosed Mar-26 AUM, growth, yield, risk and capital-allocation decision
B16: D2 | C16: Product Profitability | D16: Product-level economics and ROE (AUM disclosed; P&L allocation illustrative)
B17: D3 | C17: Branch Profitability | D17: Network productivity and profit per branch (illustrative — branch data not disclosed)
B18: D4 | C18: Collections Analytics | D18: Disclosed asset-quality metrics plus an illustrative bucket/roll-rate funnel
B19: D5 | C19: Digital Transformation | D19: DDP digital sourcing (disclosed FY23/24) plus modelled STP, AI and TAT metrics
B20: D6 | C20: Enterprise Risk Cockpit | D20: 10 enterprise risks with live KPI values, formula-driven RAG, heat map and early-warning indicators
B21: D7 | C21: Scenario Analysis | D21: Live Base / Upside / Downside toggle driving the entire forecast chain

Sheet Portfolio Mix
B1: POONAWALLA FINCORP — PORTFOLIO MIX & PRODUCT STRATEGY | K1: ⌂ Home
B2: Product AUM as of 31-Mar-2026 is Company-disclosed (AR FY2025-26, Segment-wise Business Performance, pg.116-119). Growth %, Yield and Risk columns use disclosed data where available; Capital Usage and Decision are model-derived. Linked to Product Profitability tab.
B4: Product | C4: AUM Mar-26 (₹ Cr) | D4: Mix % | E4: YoY Growth % | F4: Yield % | G4: Credit Cost % (Risk) | H4: Modelled RAROC % | I4: Screening flag (not an approved decision)
B5: ='Product Profitability'!B8 -> Loan Against Property (LAP) | C5: ='Product Profitability'!D8 -> 16935 | D5: ='Product Profitability'!C8 -> 0.28062239 | E5: 1.0004 | F5: ='Product Profitability'!E8 -> 0.10875 | G5: ='Product Profitability'!H8 -> 0.01 | H5: ='Product Profitability'!L8 -> 0.010740741 | I5: =IF(AND(H5>$C$27,G5<$C$28),"Expand",IF(H5>$C$27,"Grow Selectively",IF(G5>$C$29,"Review","Maintain"))) -> Maintain
B6: ='Product Profitability'!B9 -> Instant Consumer Loan | C6: ='Product Profitability'!D9 -> 11197 | D6: ='Product Profitability'!C9 -> 0.18554053 | E6: 0.6815 | F6: ='Product Profitability'!E9 -> 0.255 | G6: ='Product Profitability'!H9 -> 0.06 | H6: ='Product Profitability'!L9 -> 0.32311111 | I6: =IF(AND(H6>$C$27,G6<$C$28),"Expand",IF(H6>$C$27,"Grow Selectively",IF(G6>$C$29,"Review","Maintain"))) -> Grow Selectively
B7: ='Product Profitability'!B10 -> Pre-Owned Car Finance (POC) | C7: ='Product Profitability'!D10 -> 9245 | D7: ='Product Profitability'!C10 -> 0.1531948 | E7: 0.4278 | F7: ='Product Profitability'!E10 -> 0.14 | G7: ='Product Profitability'!H10 -> 0.015 | H7: ='Product Profitability'!L10 -> 0.12611111 | I7: =IF(AND(H7>$C$27,G7<$C$28),"Expand",IF(H7>$C$27,"Grow Selectively",IF(G7>$C$29,"Review","Maintain"))) -> Maintain
B8: ='Product Profitability'!B11 -> Business Loan | C8: ='Product Profitability'!D11 -> 7303 | D8: ='Product Profitability'!C11 -> 0.12101478 | E8: 0.275 | F8: ='Product Profitability'!E11 -> 0.195 | G8: ='Product Profitability'!H11 -> 0.035 | H8: ='Product Profitability'!L11 -> 0.37555556 | I8: =IF(AND(H8>$C$27,G8<$C$28),"Expand",IF(H8>$C$27,"Grow Selectively",IF(G8>$C$29,"Review","Maintain"))) -> Grow Selectively
B9: ='Product Profitability'!B12 -> Prime Personal Loan | C9: ='Product Profitability'!D12 -> 4802 | D9: ='Product Profitability'!C12 -> 0.079571817 | F9: ='Product Profitability'!E12 -> 0.13 | G9: ='Product Profitability'!H12 -> 0.02 | H9: ='Product Profitability'!L12 -> 0.034222222 | I9: =IF(AND(H9>$C$27,G9<$C$28),"Expand",IF(H9>$C$27,"Grow Selectively",IF(G9>$C$29,"Review","Maintain"))) -> Maintain
B10: ='Product Profitability'!B13 -> Gold Loan | C10: ='Product Profitability'!D13 -> 1299 | D10: ='Product Profitability'!C13 -> 0.021525154 | F10: ='Product Profitability'!E13 -> 0.12 | G10: ='Product Profitability'!H13 -> 0.004 | H10: ='Product Profitability'!L13 -> 0.020555556 | I10: =IF(AND(H10>$C$27,G10<$C$28),"Expand",IF(H10>$C$27,"Grow Selectively",IF(G10>$C$29,"Review","Maintain"))) -> Maintain
B11: ='Product Profitability'!B14 -> Commercial Vehicle Loan | C11: ='Product Profitability'!D14 -> 939 | D11: ='Product Profitability'!C14 -> 0.015559753 | F11: ='Product Profitability'!E14 -> 0.135 | G11: ='Product Profitability'!H14 -> 0.018 | H11: ='Product Profitability'!L14 -> 0.053888889 | I11: =IF(AND(H11>$C$27,G11<$C$28),"Expand",IF(H11>$C$27,"Grow Selectively",IF(G11>$C$29,"Review","Maintain"))) -> Maintain
B12: ='Product Profitability'!B15 -> Education Loan | C12: ='Product Profitability'!D15 -> 876 | D12: ='Product Profitability'!C15 -> 0.014515808 | F12: ='Product Profitability'!E15 -> 0.115 | G12: ='Product Profitability'!H15 -> 0.008 | H12: ='Product Profitability'!L15 -> 0.026111111 | I12: =IF(AND(H12>$C$27,G12<$C$28),"Expand",IF(H12>$C$27,"Grow Selectively",IF(G12>$C$29,"Review","Maintain"))) -> Maintain
B13: ='Product Profitability'!B16 -> Machinery & Medical Equipment Loan | C13: ='Product Profitability'!D16 -> 783 | D13: ='Product Profitability'!C16 -> 0.012974746 | F13: ='Product Profitability'!E16 -> 0.1175 | G13: ='Product Profitability'!H16 -> 0.01 | H13: ='Product Profitability'!L16 -> 0.028888889 | I13: =IF(AND(H13>$C$27,G13<$C$28),"Expand",IF(H13>$C$27,"Grow Selectively",IF(G13>$C$29,"Review","Maintain"))) -> Maintain
B14: ='Product Profitability'!B17 -> Professional Loan | C14: ='Product Profitability'!D17 -> 787 | D14: ='Product Profitability'!C17 -> 0.013041029 | F14: ='Product Profitability'!E17 -> 0.14 | G14: ='Product Profitability'!H17 -> 0.02 | H14: ='Product Profitability'!L17 -> 0.056444444 | I14: =IF(AND(H14>$C$27,G14<$C$28),"Expand",IF(H14>$C$27,"Grow Selectively",IF(G14>$C$29,"Review","Maintain"))) -> Maintain
B15: ='Product Profitability'!B18 -> Consumer Durable Loan | C15: ='Product Profitability'!D18 -> 382 | D15: ='Product Profitability'!C18 -> 0.0063299529 | F15: ='Product Profitability'!E18 -> 0.2 | G15: ='Product Profitability'!H18 -> 0.03 | H15: ='Product Profitability'!L18 -> 0.23422222 | I15: =IF(AND(H15>$C$27,G15<$C$28),"Expand",IF(H15>$C$27,"Grow Selectively",IF(G15>$C$29,"Review","Maintain"))) -> Grow Selectively
B16: ='Product Profitability'!B20 -> Other / Legacy Portfolio (reconciling) | C16: ='Product Profitability'!D20 -> 5799 | D16: ='Product Profitability'!C20 -> 0.096092663 | F16: ='Product Profitability'!E20 -> 0.15 | G16: ='Product Profitability'!H20 -> 0.018 | H16: ='Product Profitability'!L20 -> 0.165
B17: TOTAL | C17: =SUM(C5:C16) -> 60347 | D17: =SUM(D5:D16) -> 0.99998343
B19: PORTFOLIO COMPOSITION (Company-disclosed)
B20: Secured lending % of on-book AUM (Mar-2026) | C20: ='KPIs & Ratios'!H38 -> 0.54
B21: Unsecured lending % of on-book AUM (Mar-2026) | C21: ='KPIs & Ratios'!H39 -> 0.46
B22: Secured : Unsecured mix (Q1 FY27 actual) | C22: ='Business Performance Scorecard'!C201 -> 53% secured : 47% unsecured
B23: Management medium-term target mix | C23: ='Business Performance Scorecard'!C206 -> 50% secured : 50% unsecured
B24: New products launched FY26 — contribution to AUM | C24: 0.14
B26: SCREENING THRESHOLDS — management-set inputs; the flags in column I update from these
B27: Modelled RAROC hurdle for expansion | C27: 0.15
B28: Credit cost ceiling to qualify as "Expand" | C28: 0.015
B29: Credit cost level that triggers "Review" | C29: 0.025
B30: ILLUSTRATIVE thresholds — not disclosed policy. They were previously hardcoded inside the column I formulas; they now sit here so the screen can be re-run at a different hurdle. Column I is a SCREEN on modelled economics, not an approved capital decision: the RAROC numerator still rests on illustrative cost of funds, opex and credit cost (see Product Profitability rows 29-30).

Sheet Product Profitability
B1: POONAWALLA FINCORP LIMITED — Product Profitability | N1: ⌂ Home
B2: AUM by product is Company-disclosed (AR FY26 pg.116-119). Yield is disclosed as a range for 5 products. Cost of Funds, Opex % and Credit Cost % remain ILLUSTRATIVE (yellow). The CAPITAL DENOMINATOR is no longer illustrative: column K derives regulatory capital consumed as RBI risk weight × 18% target CRAR (Regulatory Capital tab). Column L is therefore a MODELLED RAROC — a regulatory-capital-adjusted return, NOT a measured one: the denominator is regulatory, but the numerator still rests on illustrative cost of funds, opex and credit cost. Treat column L as a SCREENING metric for where to look harder, not as evidence of realised product returns.
B3: Source: Annual Report FY2025-26, Segment-wise Business Performance, pg.116-119 (product AUM as of Mar-2026, and disbursement yield ranges where disclosed). "Other/Legacy Portfolio" is a reconciling balance (Total AUM per KPI disclosure less the sum of named products above), not a separately disclosed line.
B5: Total AUM FY2026, Reported/Standalone (₹ Cr) | C5: ='Business Performance Scorecard'!H161 -> 60348
B7: Product | C7: AUM Mix % | D7: AUM (₹ Cr, Disclosed Mar-2026) | E7: Yield % (Disclosed range midpoint where cited; else Illustrative) | F7: Cost of Funds % (Illustrative) | G7: Opex % of AUM (Illustrative) | H7: Credit Cost % of AUM (Illustrative) | I7: Net Margin % | J7: Est. Profit (₹ Cr) | K7: Regulatory Capital Consumed % of AUM (risk weight × target CRAR) | L7: Modelled RAROC % (illustrative profit ÷ regulatory capital consumed)
B8: Loan Against Property (LAP) | C8: =D8/$D$21 -> 0.28062239 | D8: 16935 | E8: 0.10875 | F8: 0.0773 | G8: 0.02 | H8: 0.01 | I8: =E8-F8-G8-H8 -> 0.00145 | J8: =D8*I8 -> 24.55575 | K8: ='Regulatory Capital'!D6*'Regulatory Capital'!$C$39 -> 0.135 | L8: =IFERROR(J8/(D8*K8),"") -> 0.010740741
B9: Instant Consumer Loan | C9: =D9/$D$21 -> 0.18554053 | D9: 11197 | E9: 0.255 | F9: 0.0773 | G9: 0.045 | H9: 0.06 | I9: =E9-F9-G9-H9 -> 0.0727 | J9: =D9*I9 -> 814.0219 | K9: ='Regulatory Capital'!D7*'Regulatory Capital'!$C$39 -> 0.225 | L9: =IFERROR(J9/(D9*K9),"") -> 0.32311111
B10: Pre-Owned Car Finance (POC) | C10: =D10/$D$21 -> 0.1531948 | D10: 9245 | E10: 0.14 | F10: 0.0773 | G10: 0.025 | H10: 0.015 | I10: =E10-F10-G10-H10 -> 0.0227 | J10: =D10*I10 -> 209.8615 | K10: ='Regulatory Capital'!D8*'Regulatory Capital'!$C$39 -> 0.18 | L10: =IFERROR(J10/(D10*K10),"") -> 0.12611111
B11: Business Loan | C11: =D11/$D$21 -> 0.12101478 | D11: 7303 | E11: 0.195 | F11: 0.0773 | G11: 0.032 | H11: 0.035 | I11: =E11-F11-G11-H11 -> 0.0507 | J11: =D11*I11 -> 370.2621 | K11: ='Regulatory Capital'!D9*'Regulatory Capital'!$C$39 -> 0.135 | L11: =IFERROR(J11/(D11*K11),"") -> 0.37555556
B12: Prime Personal Loan | C12: =D12/$D$21 -> 0.079571817 | D12: 4802 | E12: 0.13 | F12: 0.0773 | G12: 0.025 | H12: 0.02 | I12: =E12-F12-G12-H12 -> 0.0077 | J12: =D12*I12 -> 36.9754 | K12: ='Regulatory Capital'!D10*'Regulatory Capital'!$C$39 -> 0.225 | L12: =IFERROR(J12/(D12*K12),"") -> 0.034222222
B13: Gold Loan | C13: =D13/$D$21 -> 0.021525154 | D13: 1299 | E13: 0.12 | F13: 0.0773 | G13: 0.035 | H13: 0.004 | I13: =E13-F13-G13-H13 -> 0.0037 | J13: =D13*I13 -> 4.8063 | K13: ='Regulatory Capital'!D11*'Regulatory Capital'!$C$39 -> 0.18 | L13: =IFERROR(J13/(D13*K13),"") -> 0.020555556
B14: Commercial Vehicle Loan | C14: =D14/$D$21 -> 0.015559753 | D14: 939 | E14: 0.135 | F14: 0.0773 | G14: 0.03 | H14: 0.018 | I14: =E14-F14-G14-H14 -> 0.0097 | J14: =D14*I14 -> 9.1083 | K14: ='Regulatory Capital'!D12*'Regulatory Capital'!$C$39 -> 0.18 | L14: =IFERROR(J14/(D14*K14),"") -> 0.053888889
B15: Education Loan | C15: =D15/$D$21 -> 0.014515808 | D15: 876 | E15: 0.115 | F15: 0.0773 | G15: 0.025 | H15: 0.008 | I15: =E15-F15-G15-H15 -> 0.0047 | J15: =D15*I15 -> 4.1172 | K15: ='Regulatory Capital'!D13*'Regulatory Capital'!$C$39 -> 0.18 | L15: =IFERROR(J15/(D15*K15),"") -> 0.026111111
B16: Machinery & Medical Equipment Loan | C16: =D16/$D$21 -> 0.012974746 | D16: 783 | E16: 0.1175 | F16: 0.0773 | G16: 0.025 | H16: 0.01 | I16: =E16-F16-G16-H16 -> 0.0052 | J16: =D16*I16 -> 4.0716 | K16: ='Regulatory Capital'!D14*'Regulatory Capital'!$C$39 -> 0.18 | L16: =IFERROR(J16/(D16*K16),"") -> 0.028888889
B17: Professional Loan | C17: =D17/$D$21 -> 0.013041029 | D17: 787 | E17: 0.14 | F17: 0.0773 | G17: 0.03 | H17: 0.02 | I17: =E17-F17-G17-H17 -> 0.0127 | J17: =D17*I17 -> 9.9949 | K17: ='Regulatory Capital'!D15*'Regulatory Capital'!$C$39 -> 0.225 | L17: =IFERROR(J17/(D17*K17),"") -> 0.056444444
B18: Consumer Durable Loan | C18: =D18/$D$21 -> 0.0063299529 | D18: 382 | E18: 0.2 | F18: 0.0773 | G18: 0.04 | H18: 0.03 | I18: =E18-F18-G18-H18 -> 0.0527 | J18: =D18*I18 -> 20.1314 | K18: ='Regulatory Capital'!D16*'Regulatory Capital'!$C$39 -> 0.225 | L18: =IFERROR(J18/(D18*K18),"") -> 0.23422222
B19: Shopkeeper Loan | C19: =D19/$D$21 -> 1.6570557e-05 | D19: 1 | E19: 0.18 | F19: 0.0773 | G19: 0.035 | H19: 0.025 | I19: =E19-F19-G19-H19 -> 0.0427 | J19: =D19*I19 -> 0.0427 | K19: =1.25*'Regulatory Capital'!$C$39 -> 0.225 | L19: =IFERROR(J19/(D19*K19),"") -> 0.18977778
B20: Other / Legacy Portfolio (reconciling) | C20: =D20/$D$21 -> 0.096092663 | D20: =$C$5-SUM(D8:D19) -> 5799 | E20: 0.15 | F20: 0.0773 | G20: 0.025 | H20: 0.018 | I20: =E20-F20-G20-H20 -> 0.0297 | J20: =D20*I20 -> 172.2303 | K20: ='Regulatory Capital'!D17*'Regulatory Capital'!$C$39 -> 0.18 | L20: =IFERROR(J20/(D20*K20),"") -> 0.165
B21: TOTAL / WEIGHTED AVERAGE | C21: =SUM(C8:C20) -> 1 | D21: =SUM(D8:D20) -> 60348 | E21: =SUMPRODUCT(E8:E20,D8:D20)/D21 -> 0.15860606 | I21: =IFERROR(J21/D21,"") -> 0.027841508 | J21: =SUM(J8:J20) -> 1680.1794 | K21: =SUMPRODUCT(K8:K20,D8:D20)/D21 -> 0.17472882 | L21: =IFERROR(J21/(D21*K21),"") -> 0.15934125
B23: WHY THE RANKING CHANGED — modelled RAROC vs the old illustrative ROE
B24: ="Previously Instant Consumer Loan ranked highest at ~40% illustrative ROE. On regulatory capital it falls to "&TEXT(L9,"0.0%")&", because its 125% risk weight consumes "&TEXT(K9,"0.0%")&" of AUM in capital versus the 18% previously assumed. Business Loan now ranks highest at "&TEXT(L11,"0.0%")&" on a 75% risk weight. Gold Loan falls from ~4.6% to "&TEXT(L13,"0.0%")&"." -> Previously Instant Consumer Loan ranked highest at ~40% illustrative ROE. On regulatory capital it falls to 32.3%, because its 125% risk weight consumes 22.5% of AUM in capital versus the 18% previously assumed. Business Loan now ranks highest at 37.6% on a 75% risk weight. Gold Loan falls from ~4.6% to 2.1%.
B26: STRATEGIC RESOLUTION — does high-yield unsecured still win after capital?
B27: ="Unsecured consumer lending still screens well on modelled RAROC ("&TEXT(L9,"0.0%")&") even after the 125% risk-weight penalty. Secured Business Loan screens higher still ("&TEXT(L11,"0.0%")&") on a 75% risk weight, and a heavier secured mix lowers the blended "&"risk weight (currently "&TEXT('Regulatory Capital'!D18,"0.0%")&"), easing the group capital requirement. SCREENING CONCLUSION, not an allocation decision: "&"secured Business Loan is the strongest candidate on both return per unit of capital AND capital relief, with selective unsecured consumer retained for returns. "&"Before capital is reallocated this needs product-level actual credit cost, fully-allocated acquisition and servicing cost, and vintage loss behaviour - none of which the Company discloses." -> Unsecured consumer lending still screens well on modelled RAROC (32.3%) even after the 125% risk-weight penalty. Secured Business Loan screens higher still (37.6%) on a 75% risk weight, and a heavier secured mix lowers the blended risk weight (currently 97.1%), easing the group capital requirement. SCREENING CONCLUSION, not an allocation decision: secured Business Loan is the strongest candidate on both return per unit of capital AND capital relief, with selective unsecured consumer retained for returns. Before capital is reallocated this needs product-level actual credit cost, fully-allocated acquisition and servicing cost, and vintage loss behaviour - none of which the Company discloses.
B30: WHAT WOULD MAKE THIS DECISION-GRADE — the evidence gap between screening and allocation
B31: Column L ranks products on a numerator that is three-parts illustrative (cost of funds allocated flat at the blended 7.73%, opex % of AUM, credit cost % of AUM) and one-part disclosed (AUM; yield for 5 products). Four internal inputs are required to turn this from a hypothesis into a capital-allocation decision, in priority order: (1) product-level ACTUAL credit cost by vintage — the largest swing factor, since 100bps of credit-cost error moves Instant Consumer Loan RAROC by c.4.4 points and Business Loan by c.7.4 points; (2) fully-allocated acquisition and servicing cost per product, replacing the flat opex % assumption; (3) MARGINAL rather than blended cost of funds by product tenor — short-tenor consumer and long-tenor LAP do not carry the same funding cost; (4) through-cycle loss curves, so the ranking is not a point-in-time artefact of a benign credit year. Until those exist, the defensible statement is "Business Loan and Instant Consumer Loan screen attractively on capital-adjusted returns and merit deeper validation" — not "allocate incremental capital here".

Sheet Branch Profitability
B1: POONAWALLA FINCORP LIMITED — ILLUSTRATIVE BRANCH CONTRIBUTION ANALYSIS | H1: ⌂ Home
B2: ⚠ ILLUSTRATIVE — NOT branch P&L. Poonawalla does not disclose branch-level financials; only the FY26 branch count (500+, AR pg.2) is disclosed. This is a CONTRIBUTION waterfall, not profit: revenue less funding charge, credit cost, direct opex and allocated overhead. Portfolio-level yield, cost of funds and credit cost are taken from KPIs & Ratios (real), so the network total reconciles against actual PAT in the check row below.
B4: Particulars | C4: FY2023 | D4: FY2024 | E4: FY2025 | F4: FY2026
B5: Branch Count (FY26 disclosed; prior years illustrative) | C5: 210 | D5: 290 | E5: 380 | F5: 500
B6: Branch-sourced AUM (₹ Cr) = Total AUM × branch channel share | C6: ='Business Performance Scorecard'!E161*'Distribution Analytics'!C5 -> 4842.9 | D6: ='KPIs & Ratios'!F95*'Distribution Analytics'!C5 -> 7500.9 | E6: ='KPIs & Ratios'!G95*'Distribution Analytics'!C5 -> 10689.3 | F6: ='KPIs & Ratios'!H95*'Distribution Analytics'!C5 -> 18104.4
B7: Avg. AUM per Branch (₹ Cr) | C7: =IFERROR(C6/C5,"") -> 23.061429 | D7: =IFERROR(D6/D5,"") -> 25.865172 | E7: =IFERROR(E6/E5,"") -> 28.129737 | F7: =IFERROR(F6/F5,"") -> 36.2088
B8: Gross Yield % (portfolio actual, from KPIs & Ratios) | C8: ='KPIs & Ratios'!E25 -> 0.12073406 | D8: ='KPIs & Ratios'!F25 -> 0.15561866 | E8: ='KPIs & Ratios'!G25 -> 0.14155656 | F8: ='KPIs & Ratios'!H25 -> 0.1385461
B9: Revenue per Branch (₹ Cr) | C9: =C7*C8 -> 2.7842998 | D9: =D7*D8 -> 4.0251035 | E9: =E7*E8 -> 3.9819488 | F9: =F7*F8 -> 5.0165881
B10: (−) Funding Charge per Branch (₹ Cr, at portfolio cost of funds) | C10: =-C7*'KPIs & Ratios'!E26 -> -1.3056629 | D10: =-D7*'KPIs & Ratios'!F26 -> -1.8763317 | E10: =-E7*'KPIs & Ratios'!G26 -> -2.0809754 | F10: =-F7*'KPIs & Ratios'!H26 -> -2.7082822
B11: (−) Credit Cost per Branch (₹ Cr, at portfolio credit cost %) | C11: =-C7*'KPIs & Ratios'!E43 -> 0.22169297 | D11: =-D7*'KPIs & Ratios'!F43 -> -0.099976531 | E11: =-E7*'KPIs & Ratios'!G43 -> -1.4986084 | F11: =-F7*'KPIs & Ratios'!H43 -> -0.90199263
B12: (−) Direct Opex per Branch (₹ Cr, illustrative) | C12: -0.45 | D12: -0.45 | E12: -0.45 | F12: -0.45
B13: (−) Allocated Central Overhead per Branch (₹ Cr, illustrative) | C13: -0.15 | D13: -0.15 | E13: -0.15 | F13: -0.15
B14: = Pre-tax Contribution per Branch (₹ Cr) | C14: =SUM(C9:C13) -> 1.1003299 | D14: =SUM(D9:D13) -> 1.4487952 | E14: =SUM(E9:E13) -> -0.19763499 | F14: =SUM(F9:F13) -> 0.80631324
B15: (−) Tax at effective rate | C15: =-C14*Assumptions!C16 -> -0.27695303 | D15: =-D14*Assumptions!C16 -> -0.36466175 | E15: =-E14*Assumptions!C16 -> 0.049744728 | F15: =-F14*Assumptions!C16 -> -0.20294904
B16: = Post-tax Contribution per Branch (₹ Cr) | C16: =C14+C15 -> 0.82337685 | D16: =D14+D15 -> 1.0841335 | E16: =E14+E15 -> -0.14789027 | F16: =F14+F15 -> 0.6033642
B17: × Branch Count = Network Contribution (₹ Cr) | C17: =C16*C5 -> 172.90914 | D17: =D16*D5 -> 314.3987 | E17: =E16*E5 -> -56.198301 | F17: =F16*F5 -> 301.6821
B19: RECONCILIATION CHECK — does this hang together?
B20: Network Contribution above (₹ Cr) | F20: =F17 -> 301.6821
B21: Actual Company PAT FY26 (₹ Cr, disclosed) | F21: ='KPIs & Ratios'!H35 -> 541.81
B22: Variance (₹ Cr) | F22: =F20-F21 -> -240.1279
B24: Interpretation
B26: WHAT THIS TAB CAN AND CANNOT ANSWER
B27: CAN: show how branch contribution would be constructed - revenue at portfolio yield, less a funding charge at portfolio cost of funds, less credit cost at the portfolio rate, less direct opex and allocated overhead, taxed - and show that on illustrative inputs the 500-branch network explains roughly 56% of FY2026 PAT, with the balance coming from digital/DSA origination and treasury. The reconciliation row below is the discipline: it stops the analysis drifting away from actual reported profit.
B29: CANNOT: compare one branch with another, one format with another (gold-loan vs personal-loan branch), or one vintage with another. Every branch here carries identical assumed economics, so the tab has no dispersion in it - by construction. It also cannot answer where to open the next branch. Those questions need branch-level MIS: revenue, opex, headcount, disbursement and delinquency by branch and cohort. None of that is publicly disclosed, so this is the METHOD, not a finding. Do not present it as one of the model's main conclusions.

Sheet Collections Analytics
B1: POONAWALLA FINCORP — COLLECTIONS ANALYTICS | H1: ⌂ Home
B2: ⚠ ILLUSTRATIVE MODEL — Poonawalla does NOT numerically disclose collection efficiency, bucket-wise roll rates, recovery rates or write-off detail; the annual reports give only qualitative commentary (e.g. "improvements in monthly bounce and flow metrics, significant reduction in slippages", AR FY26 pg.20). Only GNPA, NNPA, PCR and credit cost are disclosed (linked below, green). The bucket/roll-rate framework is a modelled illustration.
B4: DISCLOSED ASSET-QUALITY METRICS (linked, cited)
B5: Metric | C5: FY2024 | D5: FY2025 | E5: FY2026 | F5: Q1 FY2027
B6: Gross NPA % | C6: ='KPIs & Ratios'!F44 -> 1.16 | D6: ='KPIs & Ratios'!G44 -> 1.84 | E6: ='KPIs & Ratios'!H44 -> 1.44 | F6: ='Business Performance Scorecard'!C192*100 -> 1.37
B7: Net NPA % | C7: ='KPIs & Ratios'!F45 -> 0.59 | D7: ='KPIs & Ratios'!G45 -> 0.85 | E7: ='KPIs & Ratios'!H45 -> 0.74 | F7: ='Business Performance Scorecard'!C193*100 -> 0.7
B8: Provision Coverage Ratio % | C8: ='KPIs & Ratios'!F46*100 -> 49.137931 | D8: ='KPIs & Ratios'!G46*100 -> 53.804348 | E8: ='KPIs & Ratios'!H46*100 -> 48.611111 | F8: 49.11
B9: Credit Cost % of Avg. AUM | C9: ='KPIs & Ratios'!F43*100 -> 0.38652954 | D9: ='KPIs & Ratios'!G43*100 -> 5.3274882 | E9: ='KPIs & Ratios'!H43*100 -> 2.4910868 | F9: ='Business Performance Scorecard'!C191*100 -> 2.4
B11: ILLUSTRATIVE COLLECTIONS FUNNEL (modelled — not disclosed)
B12: Stage | C12: Illustrative Rate | D12: What it measures
B13: Current bucket collection efficiency % | C13: 0.985 | D13: Share of due EMIs collected within the month
B14: Roll rate: Current → 1-30 DPD % | C14: 0.025 | D14: Fresh delinquency formation (bounce/flow)
B15: Roll rate: 1-30 → 31-60 DPD % | C15: 0.28 | D15: Early-bucket containment effectiveness
B16: Roll rate: 31-60 → 61-90 DPD % | C16: 0.42 | D16: Mid-bucket cure vs. slippage
B17: Roll rate: 61-90 → NPA (90+ DPD) % | C17: 0.55 | D17: Slippage into GNPA
B18: Recovery rate on NPA pool % | C18: 0.35 | D18: Cash recovered from the 90+ pool
B19: Write-off rate % of NPA pool | C19: 0.3 | D19: Charged off after recovery efforts exhausted
B21: Management commentary (disclosed, qualitative)
B22: FY26: GNPA improvement "achieved through enhancements in the underwriting model and strengthening of the collection infrastructure... improvements in monthly bounce and flow metrics, along with a significant reduction in slippages." (AR FY2026, KPI section)

Sheet Digital Transformation
B1: POONAWALLA FINCORP — DIGITAL TRANSFORMATION KPIs | H1: ⌂ Home
B2: Mixed disclosure: DDP (Direct Digital Platform) share of disbursement IS disclosed for FY23 and FY24 (81% / 82%, AR FY2024 pg.14) but not thereafter. STP rate, AI-underwriting share, digital collections share, TAT and cost-per-loan are NOT disclosed — those rows are modelled assumptions (yellow), included to show the KPI framework management uses.
B4: Digital KPI | C4: FY2023 | D4: FY2024 | E4: FY2026 (modelled) | F4: Disclosure Status
B5: DDP digital sourcing % of disbursement | C5: ='KPIs & Ratios'!E76 -> 0.81 | D5: ='KPIs & Ratios'!F76 -> 0.82 | F5: DISCLOSED (AR FY2024 pg.14); not published FY25-26
B6: Straight-Through Processing (STP) rate % | E6: 0.62 | F6: Not disclosed — illustrative
B7: AI/ML-assisted underwriting share % | E7: 0.55 | F7: Not disclosed — illustrative (AR FY26 pg.24-26 confirms AI initiatives qualitatively)
B8: Digital collections share % | E8: 0.68 | F8: Not disclosed — illustrative
B9: Average turnaround time — TAT (days) | E9: 1.5 | F9: Not disclosed — illustrative (AR notes "consistently reduced TAT")
B10: Illustrative cost per loan sourced (₹) | E10: ='Distribution Analytics'!D10 -> 2364 | F10: Blended CAC from Distribution Analytics (illustrative)
B12: DIGITAL IMPACT ON FINANCIALS (linked, real data)
B13: Opex / Avg. AUM % (Q1 FY27 actual, vs 4.13% prior qtr) | E13: ='Business Performance Scorecard'!C194*100 -> 4.06 | F13: DISCLOSED — Q1 FY27 earnings call
B14: Cost-to-Income Ratio % (FY26A) | E14: ='KPIs & Ratios'!H30*100 -> 52.009442 | F14: Computed; cross-checked to company disclosure (52.01%)
B15: Revenue per Employee (₹ Cr, FY26A) | E15: ='KPIs & Ratios'!H70 -> 1.1596672 | F15: Computed from disclosed headcount (5,860, AR pg.4)
B16: Employees per Branch (FY26A) | E16: =Assumptions!C14 -> 11.72 | F16: Computed from disclosed headcount ÷ branch count

Sheet Enterprise Risk Cockpit
B1: POONAWALLA FINCORP LIMITED — Enterprise Risk & Opportunity Cockpit | I1: ⌂ Home
B2: One-page executive risk view for CFO/Board review. RAG status and financial-impact framing are FORMULA-DRIVEN off this workbook's live KPIs (KPIs & Ratios, Treasury, Branch/Customer Analytics), not typed-in colors — thresholds are documented in each row's note.
B5: EXECUTIVE RISK REGISTER
B6: Risk Area | C6: Key KPI | D6: Current Value | E6: Status | F6: Financial Impact | G6: FP&A Recommendation
B7: Credit Risk | C7: GNPA % (Q1 FY27 actual) | D7: ='Business Performance Scorecard'!C192 -> 0.0137 | E7: =IF(D7<0.01,"GREEN",IF(D7<0.02,"YELLOW","RED")) -> YELLOW | F7: Lower PAT & ROE via higher provisioning | G7: Improve underwriting and collections (Credit Cost Forecast tab: glide path to 1.5% by FY31E)
B8: Liquidity Risk | C8: LCR % (FY26A) | D8: ='KPIs & Ratios'!H54 -> 181 | E8: =IF(D8>150,"GREEN",IF(D8>120,"YELLOW","RED")) -> GREEN | F8: Business continuity under stress | G8: Maintain funding diversification (Treasury tab: NCD/bank mix)
B9: Interest Rate Risk | C9: NIM % (Q1 FY27 actual) | D9: ='Business Performance Scorecard'!C190 -> 0.091 | E9: =IF(D9>0.09,"GREEN",IF(D9>0.07,"YELLOW","RED")) -> GREEN | F9: Margin pressure if Cost of Funds outpaces Yield | G9: Reprice assets and optimise borrowing mix (Funding Forecast tab)
B10: Operational Risk | C10: Cost-to-Income % (FY26A) | D10: ='KPIs & Ratios'!H30*100 -> 52.009442 | E10: =IF(D10<45,"GREEN",IF(D10<55,"YELLOW","RED")) -> YELLOW | F10: Higher operating cost dilutes PPOP | G10: Process automation and digital-led underwriting (AR FY26 pg.24-26 initiatives)
B11: Business Growth Risk | C11: AUM Growth % (FY26A YoY) | D11: ='KPIs & Ratios'!H8*100 -> 69.369369 | E11: =IF(D11>20,"GREEN",IF(D11>10,"YELLOW","RED")) -> GREEN | F11: Lower revenue growth if AUM deceleration | G11: Focus incremental capital on highest-ROE products (Product Profitability tab)
B12: Branch Productivity Risk | C12: Profit per Branch Growth % (illustrative) | D12: =IFERROR('Branch Profitability'!F11/'Branch Profitability'!E11-1,"") -> -0.39811319 | E12: =IF(D12>0.15,"GREEN",IF(D12>0,"YELLOW","RED")) -> RED | F12: Lower operating leverage as new branches mature | G12: Optimise branch network mix (gold-loan branch ramp-up curve)
B13: Customer Risk | C13: Cross-sell / Repeat Rate % (illustrative) | D13: ='Customer Analytics'!F8 -> 0.27 | E13: =IF(D13>0.3,"GREEN",IF(D13>0.2,"YELLOW","RED")) -> YELLOW | F13: Lower profitability if acquisition cost stays elevated vs. cross-sell | G13: Increase cross-sell and retention via analytics-led targeting (Value Creation Tracker, Initiative 5)
B14: Regulatory Risk | C14: Capital Adequacy — CRAR % (Q1 FY27 actual) | D14: ='Business Performance Scorecard'!C199 -> 0.1946 | E14: =IF(D14>0.18,"GREEN",IF(D14>0.15,"YELLOW","RED")) -> GREEN | F14: Compliance impact / capital raise dilution if breached | G14: Maintain capital buffer; ₹2,500 Cr QIP (Apr-2026) already strengthened headroom
B15: Technology Risk | C15: Digital (DDP) Disbursement Share % (last disclosed: FY24) | D15: ='KPIs & Ratios'!F76 -> 0.82 | E15: YELLOW | F15: Customer experience / cost efficiency impact if digital adoption stalls | G15: Continue investment in digital platforms and AI-led underwriting/collections
B16: Strategic Risk | C16: Return on Equity — ROE % (Consolidated, FY26A) | D16: ='Business Performance Scorecard'!H173 -> 0 | E16: =IF(D16>15,"GREEN",IF(D16>8,"YELLOW","RED")) -> RED | F16: Lower valuation if ROE stays below cost of equity | G16: Improve capital allocation toward highest-ROE products and businesses
B19: EXECUTIVE HEAT MAP
B20: Illustrative risk assessment (analyst judgement, 1-5 scale) — probability/impact scoring is inherently qualitative and not derivable from financial data alone, consistent with standard enterprise risk management practice.
B21: Risk Area | C21: Probability (1-5) | D21: Impact (1-5)
B22: Credit Risk | C22: 3 | D22: 5
B23: Liquidity Risk | C23: 2 | D23: 5
B24: Interest Rate Risk | C24: 2.85 | D24: 2.9
B25: Operational Risk | C25: 3.15 | D25: 3.1
B26: Business Growth Risk | C26: 1.85 | D26: 3.9
B27: Branch Productivity Risk | C27: 3.15 | D27: 2.1
B28: Customer Risk | C28: 2.85 | D28: 1.9
B29: Regulatory Risk | C29: 2.15 | D29: 4.1
B30: Technology Risk | C30: 2 | D30: 2
B31: Strategic Risk | C31: 3 | D31: 4
B58: EARLY WARNING INDICATORS
B59: Indicator | C59: Latest Value | D59: Trend | E59: Why Monitor?
B60: GNPA Trend | C60: ='Business Performance Scorecard'!C192 -> 0.0137 | D60: =IF(C60<'KPIs & Ratios'!H44/100,"↓ Improving","↑ Worsening") -> ↓ Improving | E60: Leading indicator of asset quality deterioration
B61: Collection Efficiency | C61: Not disclosed | D61: n/a | E61: Predicts future NPA formation before it shows up in GNPA
B62: Cost of Borrowing | C62: ='Business Performance Scorecard'!C200 -> 0.0772 | D62: =IF(C62<0.0763,"↓ Improving","↑ Worsening") -> ↑ Worsening | E62: Margin pressure if funding costs rise faster than yields
B63: AUM Growth | C63: ='Business Performance Scorecard'!C189 -> 67054 | D63: ="QoQ +"&TEXT('Business Performance Scorecard'!C189/'Balance Sheet'!H14-1,"0.0%") -> QoQ +19.8% | E63: Revenue outlook — disbursement momentum feeds AUM feeds NII
B64: Branch Productivity | C64: ='Branch Profitability'!F7 -> 36.2088 | D64: =IF('Branch Profitability'!F7>'Branch Profitability'!E7,"↑ Improving","↓ Worsening") -> ↑ Improving | E64: Operating leverage — AUM per branch trend as new branches mature
B65: Cross-sell Ratio | C65: ='Customer Analytics'!F8 -> 0.27 | D65: =IF(C65>'Customer Analytics'!E8,"↑ Improving","↓ Worsening") -> ↑ Improving | E65: Customer profitability — lower acquisition cost per incremental AUM
B66: Employee Productivity | C66: ='KPIs & Ratios'!H70 -> 1.1596672 | D66: =IF(C66>'KPIs & Ratios'!G70,"↑ Improving","↓ Worsening") -> ↓ Worsening | E66: Cost efficiency — revenue per employee trend
B67: Capital Adequacy | C67: ='Business Performance Scorecard'!C199 -> 0.1946 | D67: =IF(C67>'KPIs & Ratios'!H53/100,"↑ Improving","↓ Worsening") -> ↑ Improving | E67: Regulatory strength — headroom for continued AUM growth
B69: FINANCIAL IMPACT WATERFALL (Downside Scenario Transmission)
B70: Economic Slowdown | D70: Cross-check: this transmission chain is exactly the causal path already modelled in this workbook. A slowdown flows through Business Drivers (disbursement) → Business Drivers (AUM) → Revenue Forecast (interest income) → P&L (NII, PAT) → KPI Dashboard metrics (ROE). Use the Downside scenario on the Scenario Analysis tab to quantify this chain with live numbers rather than illustrative direction only.
B71: ↓
B72: Lower Disbursement
B73: ↓
B74: Lower AUM
B75: ↓
B76: Lower Interest Income
B77: ↓
B78: Lower NII
B79: ↓
B80: Lower PAT
B81: ↓
B82: Lower ROE
... B87: FP&A ACTION PLAN (linked to Value Creation Tracker, ranked by financial impact)
B88: Priority | C88: Initiative | D88: KPI Improved | E88: Expected Impact (₹ Cr p.a.) | F88: Effect
B89: 1 | C89: ='Value Creation Tracker'!C7 -> Treasury diversification — higher NCD mix, longer tenor | D89: ='Value Creation Tracker'!D7 -> Cost of Borrowing % | E89: ='Value Creation Tracker'!G7 -> 120 | F89: ↑ NIM (lower cost of funds)
B90: 2 | C90: ='Value Creation Tracker'!C5 -> Branch productivity uplift (staggered gold-loan branch ramp-up) | D90: ='Value Creation Tracker'!D5 -> Cost-to-Income Ratio % | E90: ='Value Creation Tracker'!G5 -> 90 | F90: ↑ ROE (lower cost-to-income)
B91: 3 | C91: ='Value Creation Tracker'!C8 -> Predictive collections analytics for early-bucket flows | D91: ='Value Creation Tracker'!D8 -> GNPA % | E91: ='Value Creation Tracker'!G8 -> 60 | F91: ↑ PAT (lower credit cost)
B92: 4 | C92: ='Value Creation Tracker'!C6 -> Digital/DSA channel mix optimisation to lower CAC | D92: ='Value Creation Tracker'!D6 -> Customer Acquisition Cost (₹) | E92: ='Value Creation Tracker'!G6 -> 45 | F92: ↑ Revenue (lower acquisition cost)
B93: 5 | C93: ='Value Creation Tracker'!C9 -> Cross-sell to existing customer base via analytics-led targeting | D93: ='Value Creation Tracker'!D9 -> Repeat / Cross-sell Rate % | E93: ='Value Creation Tracker'!G9 -> 35 | F93: ↑ Revenue (cross-sell)
B94: TOTAL | E94: =SUM(E89:E93) -> 350

Sheet Scenario Analysis
B1: POONAWALLA FINCORP LIMITED — Scenario Analysis (Live Selector) | J1: ⌂ Home
B2: Choose a scenario in the yellow cell below — the Business Drivers, Revenue, Funding and Credit Cost Forecast sheets (and everything downstream: P&L, Balance Sheet, Cash Flow, KPI Dashboard) update automatically. This is a genuine model toggle, not a static what-if table.
B3: ⚠ SCOPE: this is STRATEGIC SCENARIO ANALYSIS, not a regulatory or credit stress test. Stress enters through four macro-level inputs — customer acquisition, yield, cost of funds and credit cost — applied uniformly across the book. A genuine credit stress test would deteriorate the portfolio operationally: migrate balances through DPD buckets, apply cohort-specific PD/LGD shocks, model collection-capacity strain and cure-rate collapse, and let losses emerge by vintage. That requires internal MIS this model does not have (see Credit Cost Forecast rows 15-21). What this tab DOES do well: it sizes the earnings AND capital consequences of a plausible range, and it holds the Base Case honest by showing what the Downside costs.
B4: SCENARIO SELECTOR
B5: Active Scenario ▶ | C5: Base
B6: (helper) Scenario Index | C6: =MATCH(C5,{"Base","Upside","Downside"},0) -> 1
B8: ADJUSTMENT FACTORS BY SCENARIO (drive the Business Drivers / Revenue / Funding / Credit Cost Forecast sheets)
B9: Particulars | C9: Base | D9: Upside | E9: Downside
B10: New Customer Acquisition Multiplier (x) | C10: 1 | D10: 1.15 | E10: 0.85
B11: Yield Adjustment (ppt, added to Base yield each year) | C11: 0 | D11: 0.003 | E11: -0.003
B12: Cost of Funds Adjustment (ppt, added to Base CoF each year) | C12: 0 | D12: -0.002 | E12: 0.004
B13: Credit Cost Adjustment (ppt, added to Base credit cost each year) | C13: 0 | D13: -0.003 | E13: 0.006
B15: Active values (CHOOSE-linked to the selector above; these feed the model)
B16: Active New Customer Multiplier | C16: =CHOOSE($C$6,C10,D10,E10) -> 1
B17: Active Yield Adjustment (ppt) | C17: =CHOOSE($C$6,C11,D11,E11) -> 0
B18: Active Cost of Funds Adjustment (ppt) | C18: =CHOOSE($C$6,C12,D12,E12) -> 0
B19: Active Credit Cost Adjustment (ppt) | C19: =CHOOSE($C$6,C13,D13,E13) -> 0
B21: FY2031E RESULTS BY SCENARIO (captured by toggling the selector above; re-toggle C5 to recompute live)
B22: Particulars | C22: Base | D22: Upside | E22: Downside
B23: AUM / Loan Book (₹ Cr) | C23: 258441.78 | D23: 284759.14 | E23: 232124.42
B24: AUM Growth % YoY | C24: 0.2433 | D24: 0.2518 | E24: 0.2331
B25: Yield on AUM % | C25: 0.127 | D25: 0.13 | E25: 0.124
B26: Cost of Funds % | C26: 0.07 | D26: 0.068 | E26: 0.074
B27: Cost-to-Income Ratio % | C27: 0.2943 | D27: 0.255 | E27: 0.3521
B28: Profit After Tax – PAT (₹ Cr) | C28: 7211.28 | D28: 9772.64 | E28: 4175.98
B29: Return on Assets – ROA % | C29: 0.0287 | D29: 0.0354 | E29: 0.0184
B30: Return on Equity – ROE % | C30: 0.1673 | D30: 0.2064 | E30: 0.1075
B32: MANAGEMENT GUIDANCE ANCHOR
B33: Management (Q1 FY27 call, 17-Jul-2026) guided an ROA exit of 3.0%-3.5% by June 2028. This model's Upside scenario — built independently before this guidance was reviewed — reaches ~3.4%-3.5% average ROA by FY2028E-FY2029E (KPIs & Ratios!K34/K91), closely tracking management's own target. The Base Case is deliberately more conservative (~2.8% by FY2029E) and is not calibrated to guidance. See KPIs & Ratios!B87:M91 and Executive Dashboard!B50:C55 for the full detail.
B35: CAPITAL CONSEQUENCES OF THE ACTIVE SCENARIO (live — follows the selector above)
B36: Metric | C36: FY2027E | D36: FY2031E | E36: Why it matters
B37: CRAR % (RWA-based) | C37: ='Regulatory Capital'!D32 -> 0.18601956 | D37: ='Regulatory Capital'!H32 -> 0.1856802 | E37: Held at target by construction — equity is sized to the requirement
B38: Total RWA (₹ Cr) | C38: ='Regulatory Capital'!D26 -> 95068.684 | D38: ='Regulatory Capital'!H26 -> 288325.41 | E38: Stress shrinks AUM so RWA falls — but capital generation falls too
B39: Cumulative external capital required FY27E-31E (₹ Cr) | C39: ='Regulatory Capital'!C60 -> 18364.261 | E39: THE key stress output: how much more equity is needed if things go wrong
B40: Retained earnings contribution FY27E-31E (₹ Cr) | C40: =SUM('Regulatory Capital'!D46:H46) -> 23186.073 | E40: Falls sharply in downside — weaker PAT means less internal capital
B41: Capital-constrained AUM ceiling, FY31E (₹ Cr) | C41: ='Regulatory Capital'!H52 -> 240916.75 | E41: Max AUM fundable from retained earnings alone
B42: Forecast AUM FY31E (₹ Cr) | C42: ='Regulatory Capital'!H53 -> 246011.83
B43: AUM above internally-fundable ceiling (₹ Cr) | C43: ='Regulatory Capital'!H54 -> 5095.0849 | E43: The growth that cannot happen without raising equity
B45: CAPITAL STRESS COMPARISON — column order matches the scenario table above (Base | Upside | Downside). Values are STATIC captures taken by toggling the selector; re-toggle to verify.
B46: Metric | C46: Base | D46: Upside | E46: Downside
B47: External capital required FY27E-31E (₹ Cr) | C47: 18364 | D47: 16918 | E47: 21032
B48: Retained earnings contribution (₹ Cr) | C48: 23186 | D48: 30486 | E48: 14405
B49: FY31E AUM above internally-fundable ceiling (₹ Cr) | C49: 5095 | D49: -1218 | E49: 13219
B50: FY31E Total RWA (₹ Cr) | C50: 288325 | D50: 320847 | E50: 254364
B51: Memo: TOTAL regulatory capital required at target CRAR, FY31E (₹ Cr) | C51: =C50*'Regulatory Capital'!$C$39 -> 51898.5 | D51: =D50*'Regulatory Capital'!$C$39 -> 57752.46 | E51: =E50*'Regulatory Capital'!$C$39 -> 45785.52
B52: THE KEY STRESS FINDING
B53: ="In the Downside the company needs MORE external equity (₹"&TEXT(E47,"#,##0")&" Cr vs ₹"&TEXT(C47,"#,##0")&" Cr Base) despite carrying a SMALLER balance sheet (FY31E RWA ₹"&TEXT(E50,"#,##0")&" Cr vs ₹"&TEXT(C50,"#,##0")&" Cr). "&"Retained earnings fall from ₹"&TEXT(C48,"#,##0")&" Cr to ₹"&TEXT(E48,"#,##0")&" Cr, so internal capital formation deteriorates faster than the requirement shrinks. Stress does not relieve the capital problem - it worsens it. "&"Capital planning must therefore be sized off the Downside, not the Base." -> In the Downside the company needs MORE external equity (₹21,032 Cr vs ₹18,364 Cr Base) despite carrying a SMALLER balance sheet (FY31E RWA ₹2,54,364 Cr vs ₹2,88,325 Cr). Retained earnings fall from ₹23,186 Cr to ₹14,405 Cr, so internal capital formation deteriorates faster than the requirement shrinks. Stress does not relieve the capital problem - it worsens it. Capital planning must therefore be sized off the Downside, not the Base.
B55: THE SECOND STRESS FINDING — growth is not capital-free
B56: ="Higher profitability does not mean lower capital dependence. The Upside carries the LARGEST absolute capital requirement of the three cases (₹"&TEXT(D51,"#,##0")&" Cr at target CRAR vs ₹"&TEXT(C51,"#,##0")&" Cr Base and ₹"&TEXT(E51,"#,##0")&" Cr Downside), because faster growth builds more RWA. It needs the LEAST external equity (₹"&TEXT(D47,"#,##0")&" Cr) only because retained earnings reach ₹"&TEXT(D48,"#,##0")&" Cr - it funds a bigger book out of its own profits. "&"So a reader comparing only FY31E ROE (Upside "&TEXT(D30,"0.0%")&" vs Downside "&TEXT(E30,"0.0%")&") sees half the picture: the Upside wins on return and on external funding need, but it is the most capital-hungry case in absolute terms - "&"and the Downside, not the Upside, is the case that dictates how much equity headroom must be pre-arranged with the board and the market." -> Higher profitability does not mean lower capital dependence. The Upside carries the LARGEST absolute capital requirement of the three cases (₹57,752 Cr at target CRAR vs ₹51,899 Cr Base and ₹45,786 Cr Downside), because faster growth builds more RWA. It needs the LEAST external equity (₹16,918 Cr) only because retained earnings reach ₹30,486 Cr - it funds a bigger book out of its own profits. So a reader comparing only FY31E ROE (Upside 20.6% vs Downside 10.8%) sees half the picture: the Upside wins on return and on external funding need, but it is the most capital-hungry case in absolute terms - and the Downside, not the Upside, is the case that dictates how much equity headroom must be pre-arranged with the board and the market.

Sheet E - Executive Decision Support
B2: E | C2: SECTION E — EXECUTIVE DECISION SUPPORT | F2: ⌂ Home
C4: Converting analysis into decisions, and decisions into tracked outcomes. This section closes the loop between what the model shows and what management should actually do.
B6: WHAT THIS SECTION COVERS
C7: • Data-backed answers to the questions management actually asks, each citing the tab and cell that supports it
C8: • The value-creation initiative pipeline with quantified financial impact, owner and timeline
C9: • The link from each initiative to the specific KPI it moves and the shareholder-value outcome it drives
B11: SHEETS IN THIS SECTION
B12: Ref | C12: Sheet | D12: What it does
B13: E1 | C13: Management Recommendations | D13: Five management questions answered from workbook data, with live cell references
B14: E2 | C14: Value Creation Tracker | D14: Five initiatives with baseline, target, quantified ₹ Cr impact, timeline and owner (₹350 Cr total identified)

Sheet Management Recommendations
B1: POONAWALLA FINCORP LIMITED — Management Recommendations | J1: ⌂ Home
B2: Answers below are derived from the data in this workbook (cell references shown), not restated financials — each recommendation cites the tab and figure that supports it. Section 7 grades how much evidence sits behind each one; read it before quoting any figure from this sheet.
B4: 1. WHICH PRODUCT SHOULD RECEIVE MORE CAPITAL?
B5: Highest modelled RAROC — material products (Product Profitability col L; ranking at row 39 below): | D5: =C41&" — "&TEXT(D41,"0.0%")&" modelled RAROC" -> Business Loan — 37.6% modelled RAROC
B6: Second highest: | D6: =C42&" — "&TEXT(D42,"0.0%")&" modelled RAROC" -> Instant Consumer Loan — 32.3% modelled RAROC
B7: Lowest (candidate to de-prioritise): | D7: =C43&" — "&TEXT(D43,"0.0%")&" modelled RAROC" -> Loan Against Property (LAP) — 1.1% modelled RAROC
B8: ="SCREENING CONCLUSION, not an allocation instruction. On modelled RAROC the two strongest candidates are "&C41&" ("&TEXT(D41,"0.0%")&" on "&TEXT(F41,"0.0%")&" capital consumed) and "&C42&" ("&TEXT(D42,"0.0%")&" on "&TEXT(F42,"0.0%")&"), while "&C43&" screens weakest at "&TEXT(D43,"0.0%")&". "&"WHAT THIS JUSTIFIES: directing incremental origination capacity toward the top two and capping further AUM concentration in the weakest, subject to validation. "&"WHAT IT DOES NOT JUSTIFY: a hard capital reallocation. Product AUM and part of the yield are Company-disclosed (AR FY26 pg.116-119) and the capital denominator is regulatory, but cost of funds, opex and credit cost remain illustrative "&"- see Product Profitability row 30 for the four inputs that would close that gap. Note also that the top-ranked product is SECURED, so here return and capital relief point the same way; that will not always hold." -> SCREENING CONCLUSION, not an allocation instruction. On modelled RAROC the two strongest candidates are Business Loan (37.6% on 13.5% capital consumed) and Instant Consumer Loan (32.3% on 22.5%), while Loan Against Property (LAP) screens weakest at 1.1%. WHAT THIS JUSTIFIES: directing incremental origination capacity toward the top two and capping further AUM concentration in the weakest, subject to validation. WHAT IT DOES NOT JUSTIFY: a hard capital reallocation. Product AUM and part of the yield are Company-disclosed (AR FY26 pg.116-119) and the capital denominator is regulatory, but cost of funds, opex and credit cost remain illustrative - see Product Profitability row 30 for the four inputs that would close that gap. Note also that the top-ranked product is SECURED, so here return and capital relief point the same way; that will not always hold.
B10: 2. WHICH BRANCH FORMAT SHOULD EXPAND?
B11: Post-tax Contribution per Branch, FY2023→FY2026 (Branch Profitability row 16 — ILLUSTRATIVE, not a branch P&L): | D11: =TEXT('Branch Profitability'!C16,"0.00;(0.00)")&" → "&TEXT('Branch Profitability'!D16,"0.00;(0.00)")&" → "&TEXT('Branch Profitability'!E16,"0.00;(0.00)")&" → "&TEXT('Branch Profitability'!F16,"0.00;(0.00)")&" ₹ Cr" -> 0.82 → 1.08 → (0.15) → 0.60 ₹ Cr
B12: ="The series above is not a straight line: FY2025 was NEGATIVE at ₹("&TEXT(-'Branch Profitability'!E16,"0.00")&") Cr per branch before recovering to ₹"&TEXT('Branch Profitability'!F16,"0.00")&" Cr in FY2026, and the network total of ₹"&TEXT('Branch Profitability'!F17,"#,##0")&" Cr still sits ₹"&TEXT(-'Branch Profitability'!F22,"#,##0")&" Cr below actual PAT. "&"WHAT THE DISCLOSED DATA SUPPORTS: continuing the expansion pace in Assumptions row 13. AUM per branch (Business Drivers row 30) rises every year, and the FY2026 build-out of 400 gold-loan branches, "&">90% of them Tier II/III (AR pg.2), is a validated fast-scaling secured channel. "&"WHAT IT DOES NOT SUPPORT: choosing between individual branches, formats or vintages. That needs branch-level MIS - revenue, opex and delinquency by branch and cohort - which is not disclosed. "&"Treat the Branch Profitability tab as the METHOD for building branch contribution, not as evidence about any particular branch or format." -> The series above is not a straight line: FY2025 was NEGATIVE at ₹(0.15) Cr per branch before recovering to ₹0.60 Cr in FY2026, and the network total of ₹302 Cr still sits ₹240 Cr below actual PAT. WHAT THE DISCLOSED DATA SUPPORTS: continuing the expansion pace in Assumptions row 13. AUM per branch (Business Drivers row 30) rises every year, and the FY2026 build-out of 400 gold-loan branches, >90% of them Tier II/III (AR pg.2), is a validated fast-scaling secured channel. WHAT IT DOES NOT SUPPORT: choosing between individual branches, formats or vintages. That needs branch-level MIS - revenue, opex and delinquency by branch and cohort - which is not disclosed. Treat the Branch Profitability tab as the METHOD for building branch contribution, not as evidence about any particular branch or format.
B14: 3. WHERE CAN COSTS BE REDUCED?
B15: Fastest-growing Opex categories, FY2026A→FY2027E (Operating Cost Forecast rows 36-47): | D15: ='Operating Cost Forecast'!C45&" +"&TEXT('Operating Cost Forecast'!E45,"0.0%")&", "&'Operating Cost Forecast'!C46&" +"&TEXT('Operating Cost Forecast'!E46,"0.0%")&" (slowest: "&'Operating Cost Forecast'!C47&" +"&TEXT('Operating Cost Forecast'!E47,"0.0%")&")" -> Branch Cost +37.8%, Employee Cost +37.8% (slowest: Other Operating Expenses +3.5%)
B16: Cost-to-Income improvement built into the model (decomposed on Operating Cost Forecast rows 49-56 — it is income scale, not cost cutting): | D16: =TEXT(('Profit & Loss'!H21+'Profit & Loss'!H22+'Profit & Loss'!H23)/('Profit & Loss'!H15-'Profit & Loss'!H17),"0.0%")&" (FY26A) → "&TEXT(('Profit & Loss'!M21+'Profit & Loss'!M22+'Profit & Loss'!M23)/('Profit & Loss'!M15-'Profit & Loss'!M17),"0.0%")&" (FY31E)" -> 52.0% (FY26A) → 27.8% (FY31E)
B17: ="The two fastest-growing lines are "&'Operating Cost Forecast'!C45&" and "&'Operating Cost Forecast'!C46&" - both NETWORK-BUILD costs, not inefficiency. Cutting them cuts growth, so they are not the place to start. "&"Cost-to-income still falls from "&TEXT(('Profit & Loss'!H21+'Profit & Loss'!H22+'Profit & Loss'!H23)/('Profit & Loss'!H15-'Profit & Loss'!H17),"0.0%")&" to "&TEXT(('Profit & Loss'!M21+'Profit & Loss'!M22+'Profit & Loss'!M23)/('Profit & Loss'!M15-'Profit & Loss'!M17),"0.0%")&" because income compounds faster than cost - so the efficiency claim is CONDITIONAL on the AUM path, not independent of it. "&"The three genuine levers, in order of leverage: (a) hold cost per branch flat in real terms while AUM per branch rises (Operating Cost Forecast row 13); "&"(b) continue the employees-per-branch productivity glide (Assumptions row 14) via AI-led underwriting and collections (AR FY2026 pg.24-26); "&"(c) keep marketing growth below disbursement growth through higher cross-sell (Business Drivers row 8), which lowers acquisition intensity. "&"Marketing is NOT the fastest-growing line - an earlier version of this sheet said it was, and that was wrong." -> The two fastest-growing lines are Branch Cost and Employee Cost - both NETWORK-BUILD costs, not inefficiency. Cutting them cuts growth, so they are not the place to start. Cost-to-income still falls from 52.0% to 27.8% because income compounds faster than cost - so the efficiency claim is CONDITIONAL on the AUM path, not independent of it. The three genuine levers, in order of leverage: (a) hold cost per branch flat in real terms while AUM per branch rises (Operating Cost Forecast row 13); (b) continue the employees-per-branch productivity glide (Assumptions row 14) via AI-led underwriting and collections (AR FY2026 pg.24-26); (c) keep marketing growth below disbursement growth through higher cross-sell (Business Drivers row 8), which lowers acquisition intensity. Marketing is NOT the fastest-growing line - an earlier version of this sheet said it was, and that was wrong.
B19: 4. WHAT ARE THE BIGGEST RISKS?
B20: Risk 1 — Capital / Dilution: cumulative capital raise required, FY2027E–FY2031E (Balance Sheet tab, memo row 60): | D20: =TEXT(SUM('Balance Sheet'!I60:M60),"#,##0")&" ₹ Cr" -> 18,364 ₹ Cr
B21: ="DERIVED from the Regulatory Capital schedule, not an assumption. Holding the 18% target CRAR (15% NBFC-UL minimum + 3% buffer) against the forecast RWA profile requires ₹"&TEXT('Regulatory Capital'!C60,"#,##0")&" Cr of external equity over FY27E-31E: ₹"&TEXT('Regulatory Capital'!C58,"#,##0")&" Cr incremental net of retained earnings, plus ₹"&TEXT('Regulatory Capital'!C59,"#,##0")&" Cr one-off catch-up because FY26A capital already sits below target. "&"FEASIBILITY: that is ₹"&TEXT('Regulatory Capital'!C90,"#,##0")&" Cr a year for five consecutive years, "&TEXT('Regulatory Capital'!C91,"0.00")&"x the largest raise the Company has executed (the ₹"&TEXT('Regulatory Capital'!C89,"#,##0")&" Cr FY2026 QIP). "&"IF THE BOARD REFUSES ISSUANCE: FY2031E AUM caps at "&TEXT('Regulatory Capital'!C82,"0.0%")&" of plan and ₹"&TEXT('Regulatory Capital'!C84,"#,##0")&" Cr of FY2031E PAT is foregone (Regulatory Capital section 7). Dilution, timing and market-window risk are NOT modelled." -> DERIVED from the Regulatory Capital schedule, not an assumption. Holding the 18% target CRAR (15% NBFC-UL minimum + 3% buffer) against the forecast RWA profile requires ₹18,364 Cr of external equity over FY27E-31E: ₹15,874 Cr incremental net of retained earnings, plus ₹2,490 Cr one-off catch-up because FY26A capital already sits below target. FEASIBILITY: that is ₹3,673 Cr a year for five consecutive years, 1.47x the largest raise the Company has executed (the ₹2,500 Cr FY2026 QIP). IF THE BOARD REFUSES ISSUANCE: FY2031E AUM caps at 58.2% of plan and ₹3,278 Cr of FY2031E PAT is foregone (Regulatory Capital section 7). Dilution, timing and market-window risk are NOT modelled.
B23: Risk 2 — Credit Cost normalisation: ROE swing, Downside vs Base (Scenario Analysis, row 30): | D23: =TEXT('Scenario Analysis'!E30,"0.0%")&" (Downside) vs "&TEXT('Scenario Analysis'!C30,"0.0%")&" (Base) FY2031E ROE" -> 10.8% (Downside) vs 16.7% (Base) FY2031E ROE
B24: ="If GNPA and credit cost do not improve as assumed (Credit Cost Forecast tab), FY2031E ROE falls by "&TEXT(('Scenario Analysis'!C30-'Scenario Analysis'!E30)*100,"0.0")&" points and external equity need rises to ₹"&TEXT('Scenario Analysis'!E47,"#,##0")&" Cr. "&"The entire profitability recovery depends on credit cost normalising from FY2026A's elevated ~2.5% to "&TEXT('Credit Cost Forecast'!H10,"0.0%")&" - an assumption stressed but NOT proven by this model (Credit Cost Forecast rows 19-21 sets out what does and does not support it)." -> If GNPA and credit cost do not improve as assumed (Credit Cost Forecast tab), FY2031E ROE falls by 6.0 points and external equity need rises to ₹21,032 Cr. The entire profitability recovery depends on credit cost normalising from FY2026A's elevated ~2.5% to 1.5% - an assumption stressed but NOT proven by this model (Credit Cost Forecast rows 19-21 sets out what does and does not support it).
B26: Risk 3 — Funding concentration: Debt-to-Equity Ratio, FY2031E (Balance Sheet tab, memo row 61): | D26: =TEXT('Balance Sheet'!M61,"0.00")&"x" -> 4.05x
B27: ="With "&TEXT('Funding Forecast'!H7,"0.0%")&" of FY2031E AUM funded by borrowings (Funding Forecast row 7) and leverage at "&TEXT('Balance Sheet'!M61,"0.00")&"x by FY2031E, a Cost of Funds shock "&"(the +40bps modelled in the Downside scenario) compresses NIM directly - Finance Costs are the single largest expense line in the Profit & Loss forecast columns. "&"Funding concentration is an availability risk as well as a price risk: borrowings are the residual funding requirement in the Balance Sheet, which assumes debt markets absorb that balance at the FY2026A instrument mix." -> With 81.3% of FY2031E AUM funded by borrowings (Funding Forecast row 7) and leverage at 4.05x by FY2031E, a Cost of Funds shock (the +40bps modelled in the Downside scenario) compresses NIM directly - Finance Costs are the single largest expense line in the Profit & Loss forecast columns. Funding concentration is an availability risk as well as a price risk: borrowings are the residual funding requirement in the Balance Sheet, which assumes debt markets absorb that balance at the FY2026A instrument mix.
B29: 5. WHICH INITIATIVES IMPROVE ROE THE MOST?
B30: Scenario spread on FY2031E ROE (Scenario Analysis, row 30): | D30: ="Upside "&TEXT('Scenario Analysis'!D30,"0.0%")&" | Base "&TEXT('Scenario Analysis'!C30,"0.0%")&" | Downside "&TEXT('Scenario Analysis'!E30,"0.0%") -> Upside 20.6% | Base 16.7% | Downside 10.8%
B31: Ranked by leverage on ROE, based on the Scenario Analysis adjustment factors (rows 10-13) and the Product Profitability tab:
B32: 1. Credit cost discipline — the single largest driver of the Upside/Downside ROE spread (Credit Cost Forecast tab); underwriting and collections initiatives (AI-led, AR FY2026 pg.24-26) that keep credit cost on the improving glide path are the highest-leverage lever.
B33: =" 2. Product mix shift on capital-adjusted returns - "&C41&" and "&C42&" screen highest on modelled RAROC ("&TEXT(D41,"0.0%")&" / "&TEXT(D42,"0.0%")&") against "&C43&" at "&TEXT(D43,"0.0%")&"; "&"tilting incremental origination there raises return per unit of regulatory capital consumed without relying on AUM growth alone. Subject to the section 1 caveat - these are screening ranks built on illustrative product cost lines." -> 2. Product mix shift on capital-adjusted returns - Business Loan and Instant Consumer Loan screen highest on modelled RAROC (37.6% / 32.3%) against Loan Against Property (LAP) at 1.1%; tilting incremental origination there raises return per unit of regulatory capital consumed without relying on AUM growth alone. Subject to the section 1 caveat - these are screening ranks built on illustrative product cost lines.
B34: 3. Cross-sell penetration — raising the rate (Business Drivers row 8) grows AUM with a lower incremental cost base than pure new-customer acquisition, improving both Cost-to-Income and capital efficiency (less capital raise needed per unit of AUM growth).
B35: =" 4. Cost of Funds management - NCD diversification and rating-driven funding cost reduction (Funding Forecast tab); the 40bps swing between scenarios is worth several ROE points given "&TEXT('Funding Forecast'!H7,"0.0%")&" of FY2031E AUM is debt-funded. "&"This is the lowest-risk of the five levers: the model only assumes c.48bps of improvement over five years." -> 4. Cost of Funds management - NCD diversification and rating-driven funding cost reduction (Funding Forecast tab); the 40bps swing between scenarios is worth several ROE points given 81.3% of FY2031E AUM is debt-funded. This is the lowest-risk of the five levers: the model only assumes c.48bps of improvement over five years.
